Workbook

Sheet README
A1: Marginal Analysis - farm bed-mix optimization model
A2: Read me / spec for reviewers. Built from capabilities/marginal-analysis/spec.md.
A4: Purpose | B4: Choose non-negative integer numbers of tomato, carrot and mesclun grow beds that maximize seasonal (36-week) farm profit, subject to crop bed caps, the 64-bed farm, and permanent + temporary labor limits. Labor per bed compounds with each crop's own bed count, so the highest-revenue crop (tomato) is not automatically the best to expand.
A6: SHEETS
A7: Summary | B7: One-page optimization summary: recommendation, all required outputs, formula-generated statements of which constraints limit the solution, and the standalone P = MC points.
A8: Inputs | B8: Every case assumption as a named range with unit and source. The only editable cells (yellow, blue text). Two derived inputs (TEMP_HOURS_CAP, TOTAL_LABOR_HOURS_CAP).
A9: Cost Structure | B9: Revenue, fertilizer, crop labor hours, permanent-then-temporary labor allocation, labor dollars, total costs and profit for the current bed mix.
A10: Marginal Cost | B10: Integer q = 0 to each crop's cap: labor hours, fertilizer, and marginal labor hours; marginal labor cost and marginal total cost priced at each crop's MC_RATE (the spec schedule), at the permanent and temporary rates (reference), and permanent hours first (information, spec.md Audit finding A1). Standalone P = MC points and charts of price vs marginal cost.
A11: Optimization | B11: Decision cells (Solver changing cells), objective, constraint checks (green), +1/−1 bed marginal analysis at the current mix, farm-level constraint statements, optimized solution vs enumeration (gold), Solver settings.
A12: Enumeration | B12: Solver-independent proof of the global optimum: profit for every integer mix (21 × 21 × 31 = 13,671), blank where a constraint is broken.
A13: Checks | B13: spec.md Validation Rules V1–V6 (with cells to record Solver and Farm Profit Lab results by hand), then supporting optimum, constraint, error, logic, information and hand-calculation checks.
A15: CONVENTIONS
A16: Yellow fill, blue text | B16: Editable input (Inputs sheet), check tolerance, or result recorded by hand (Checks sheet).
A17: Orange fill, thick red border | B17: Decision cell (Solver changing cell): integer, non-negative.
A18: Green fill | B18: Constraint-check cell.
A19: Gold fill | B19: Recommendation / optimized solution.
A20: Red fill | B20: Excel error, negative or non-integer quantity, or failed check (conditional formatting).
A21: Formulas | B21: Every calculated cell is a formula that refers to named ranges, not hard-coded values. The exceptions are the published check figures and the typed base-case hand calculations on the Checks sheet.
A23: FORMULA DEFINITIONS
A24: LABOR_HOURS(q) | B24: q × HRS_PER_WEEK_PER_BED × SEASON_WEEKS × (1 + DIM_RTRN)^q, per crop with its own parameters. Not linearized. LABOR_HOURS(0) = 0.
A25: Revenue(q) | B25: q × REVENUE_PER_BED; TOTAL_REVENUE = sum over crops.
A26: Fertilizer(q) | B26: q × FERTILIZER_PER_BED; TOTAL_FERTILIZER = sum over crops.
A27: Labor allocation | B27: PERMANENT_HOURS_USED = MIN(TOTAL_LABOR_HOURS, PERMANENT_FIELD_LABOR_HOURS); TEMP_HOURS_USED = MAX(0, TOTAL_LABOR_HOURS − PERMANENT_FIELD_LABOR_HOURS).
A28: Labor cost | B28: PERMANENT_HOURS_USED × PERMANENT_HOURLY_RATE + TEMP_HOURS_USED × TEMP_HOURLY_RATE; BLENDED_LABOR_RATE = TOTAL_LABOR_COST / TOTAL_LABOR_HOURS when hours > 0.
A29: Labor cost by crop | B29: CROP_LABOR_COST = CROP_LABOR_HRS × BLENDED_LABOR_RATE (0 when TOTAL_LABOR_HOURS = 0); the three sum to TOTAL_LABOR_COST. CROP_CONTRIBUTION = CROP_REVENUE − CROP_FERTILIZER − CROP_LABOR_COST. Reporting only.
A30: SEASONAL_PROFIT | B30: TOTAL_REVENUE − TOTAL_FERTILIZER − TOTAL_LABOR_COST − FIXED_SEASON_COST.
A31: Marginal cost | B31: LABOR_COST(q) = LABOR_HOURS(q) × MC_RATE; MARGINAL_LABOR_COST(q) = LABOR_COST(q) − LABOR_COST(q − 1); MARGINAL_COST(q) = MARGINAL_LABOR_COST(q) + FERTILIZER_PER_BED. MC_RATE = TEMP_HOURLY_RATE for tomatoes, PERMANENT_HOURLY_RATE for carrots and mesclun.
A32: Standalone P = MC point | B32: Largest q with REVENUE_PER_BED ≥ MARGINAL_COST(q). A diagnostic only: it ignores the shared labor pool and the 64-bed limit.
A33: Temporary workers required | B33: ROUNDUP(TEMP_HOURS_USED / TEMP_HOURS_LABOR_PER_WORKER, 0); FTE shown alongside. Cost is charged on hours used, per the spec.
A35: SOLVER SETTINGS
A36: Objective | B36: Max OBJECTIVE_SEASONAL_PROFIT (Optimization!C11).
A37: Changing cells | B37: TOMATO_BEDS, CARROT_BEDS, MESCLUN_BEDS (Optimization!C6:C8): integer, non-negative.
A38: Constraints | B38: Each crop's beds ≤ its bed cap; TOTAL_BEDS_USED ≤ TOTAL_BEDS_AVAILABLE; TEMP_HOURS_USED ≤ TEMP_HOURS_CAP; TOTAL_LABOR_HOURS ≤ TOTAL_LABOR_HOURS_CAP. All 64 beds are NOT required to be used.
A39: Method | B39: GRG Nonlinear, Integer Optimality 0%, Make Unconstrained Variables Non-Negative checked. The hidden Solver names on the Optimization sheet pre-load these settings. Run in desktop Excel on 2026-10-13; see Decision cell values below.
A40: Decision cell values | B40: The decision cells hold 10 / 20 / 30. Solver (GRG Nonlinear, integer, Integer Optimality 0%) was run in desktop Excel on 2026-10-13 from 0 / 0 / 0, returning 10 / 20 / 30 and $42,775.16, and from 20 / 0 / 0, returning 10 / 20 / 30 and $42,775.16 ("Solver found a solution" both times). Both runs are recorded on the Checks sheet (V5) and agree with the Enumeration sheet. Checks fails if the decision cells differ from the enumerated optimum.
A42: SPEC DEFECTS FOUND IN THE BUILD (now corrected in spec.md; see its Audit findings)
A43: Labor exponent | B43: spec.md wrote (1 − DIM_RTRN)^q but described labor that increases per added bed. spec.md now writes (1 + DIM_RTRN)^q, which reproduces the 10/20/30 check mix. (1 − DIM_RTRN)^q would give 20/20/24.
A44: Bed-cap constraints | B44: spec.md wrote TOMATO_BEDS ≥ TOMATO_BED_CAP; it now writes ≤ for each crop, as built.
A45: Acceptance mix | B45: spec.md Expected Outputs now names 10/20/30. The brief's 12/20/30 hypothesis is shown on Checks (R1) for reconciliation only.
A46: Profit check | B46: Spec formulas give $42,775.16 vs published $42,762 (+$13.16). Passes V2 within PROFIT_TOLERANCE ($25). The gap is rounding of $34.72, $17.36 and 0.833 (spec.md Audit finding A2).
A47: Standalone P = MC | B47: spec.md now prices each schedule at MC_RATE (tomatoes temporary, carrots and mesclun permanent), which reproduces ~10 / ~10 / ~6; V3 tests at MC_RATE only. Both single rates and the permanent-hours-first schedule are shown for reference.
A48: Renamed inputs | B48: Excel names cannot contain % or spaces: *_DIM_RTRN_% → *_DIM_RTRN_PCT; TEMP_HOURS_LABOR_PER WORKER → TEMP_HOURS_LABOR_PER_WORKER. PERMANENT_FIELD_HOURS in the spec formulas = PERMANENT_FIELD_LABOR_HOURS. SEASON_PROFIT = SEASONAL_PROFIT. TOTAL_RETILIZER = TOTAL_FERTILIZER.
A49: Added inputs | B49: None. PROFIT_TOLERANCE and BED_TOLERANCE are check settings defined in spec.md Validation Rules; MC_RATE per crop is defined in spec.md Calculation Logic.
A50: Schedule size | B50: Marginal Cost and Enumeration rows are built for the base-case caps (20/20/30). Lowering a cap is handled automatically. Raising one needs more rows, and a Coverage check on Checks will fail until they are added.
A52: NAMED RANGES | B52: Full list below: name, location, definition.
A54: Name | B54: Location / definition
A55: TOMATO_BED_CAP | B55: Inputs!$B$5 — Input: 20 beds
A56: CARROT_BED_CAP | B56: Inputs!$B$6 — Input: 20 beds
... A183: CHECKS_OVERALL | B183: Checks!$B$4 — ALL CHECKS PASS, PENDING count, or count of failures

Sheet Summary
A1: Optimization summary - seasonal bed mix
A2: Every value below is a live formula. Re-run Solver after changing an input; the Checks sheet confirms the result.
A4: Recommendation | B4: =RECOMMENDATION_TEXT -> Plant 10 tomato, 20 carrot and 30 mesclun beds (60 of 64 beds) for a seasonal profit of $42,775.
A5: Workbook checks | B5: =CHECKS_OVERALL -> ALL CHECKS PASS
A7: Output | B7: Value | C7: Unit | D7: Named range
A8: Optimized tomato beds | B8: =TOMATO_BEDS -> 10 | C8: beds | D8: TOMATO_BEDS
A9: Optimized carrot beds | B9: =CARROT_BEDS -> 20 | C9: beds | D9: CARROT_BEDS
A10: Optimized mesclun beds | B10: =MESCLUN_BEDS -> 30 | C10: beds | D10: MESCLUN_BEDS
A11: Total beds used | B11: =TOTAL_BEDS_USED -> 60 | C11: beds | D11: TOTAL_BEDS_USED
A12: Unused beds | B12: =UNUSED_BEDS -> 4 | C12: beds | D12: UNUSED_BEDS
A13: Total revenue | B13: =TOTAL_REVENUE -> 210880 | C13: $/season | D13: TOTAL_REVENUE
A14: Total fertilizer cost | B14: =TOTAL_FERTILIZER -> 44000 | C14: $/season | D14: TOTAL_FERTILIZER
A15: Total labor hours | B15: =TOTAL_LABOR_HOURS -> 5276.8228 | C15: hours/season | D15: TOTAL_LABOR_HOURS
A16: Remaining unused labor hours | B16: =UNUSED_LABOR_HOURS -> 1203.1772 | C16: hours/season | D16: UNUSED_LABOR_HOURS
A17: Permanent hours used | B17: =PERMANENT_HOURS_USED -> 720 | C17: hours/season | D17: PERMANENT_HOURS_USED
A18: Temporary hours used | B18: =TEMP_HOURS_USED -> 4556.8228 | C18: hours/season | D18: TEMP_HOURS_USED
A19: Temporary workers required (whole workers) | B19: =TEMP_WORKERS_REQUIRED -> 4 | C19: workers | D19: TEMP_WORKERS_REQUIRED
A20: Temporary workers required (full-time equivalent) | B20: =TEMP_WORKERS_FTE -> 3.1644603 | C20: workers | D20: TEMP_WORKERS_FTE
A21: Total labor cost | B21: =TOTAL_LABOR_COST -> 104104.84 | C21: $/season | D21: TOTAL_LABOR_COST
A22: Blended labor rate | B22: =BLENDED_LABOR_RATE -> 19.728698 | C22: $/hour | D22: BLENDED_LABOR_RATE
A23: Fixed seasonal cost | B23: =FIXED_SEASON_COST -> 20000 | C23: $/season | D23: FIXED_SEASON_COST
A24: Seasonal profit | B24: =SEASONAL_PROFIT -> 42775.155 | C24: $/season | D24: SEASONAL_PROFIT
A26: What limits the optimization
A27: Limit | B27: Statement (formula-generated)
A28: Tomato beds | B28: =TOMATO_LIMIT_STATEMENT -> Not constraint-limited: stops on marginal cost. Bed 11 would add 490 labor hours and change profit by -$590.
A29: Carrot beds | B29: =CARROT_LIMIT_STATEMENT -> BINDING: carrot bed cap (20 beds). One more bed would change profit by $353, so the cap limits profit.
A30: Mesclun beds | B30: =MESCLUN_LIMIT_STATEMENT -> BINDING: mesclun bed cap (30 beds). One more bed would change profit by $247, so the cap limits profit.
A31: Farm beds | B31: =BEDS_LIMIT_STATEMENT -> Not binding: 4 beds unused, so this limit has no opportunity cost at the current mix.
A32: Total labor hours | B32: =LABOR_LIMIT_STATEMENT -> Not binding: 1,203.2 labor hours unused, so this limit has no opportunity cost at the current mix.
A33: Temporary labor hours | B33: =TEMP_LIMIT_STATEMENT -> Not binding: 1,203.2 temporary hours unused, so this limit has no opportunity cost at the current mix.
A34: Permanent labor hours | B34: =PERM_LIMIT_STATEMENT -> Fully used (permanent hours are allocated first). Further hours are bought at the temporary rate of $17.36/hr, which is the marginal labor rate.
A36: Standalone P = MC points (Marginal Cost sheet)
A37: Crop | B37: @ MC_RATE (spec, V3) | C37: Permanent hours first (info) | D37: Bed cap
A38: Tomato | B38: =TOMATO_PMC_Q -> 10 | C38: =TOMATO_PMC_Q_OWNER -> 10 | D38: =TOMATO_BED_CAP -> 20
A39: Carrot | B39: =CARROT_PMC_Q -> 10 | C39: =CARROT_PMC_Q_OWNER -> 20 | D39: =CARROT_BED_CAP -> 20
A40: Mesclun | B40: =MESCLUN_PMC_Q -> 6 | C40: =MESCLUN_PMC_Q_OWNER -> 30 | D40: =MESCLUN_BED_CAP -> 30
A41: MC_RATE: tomatoes at TEMP_HOURLY_RATE, carrots and mesclun at PERMANENT_HOURLY_RATE (spec.md, Calculation Logic). The permanent-hours-first schedule prices labor as SEASONAL_PROFIT does; see spec.md Audit finding A1.
A43: Contribution by crop (labor at the blended rate; reporting only)
A44: Crop | B44: Crop labor cost | C44: Crop contribution | D44: Named ranges
A45: Tomato | B45: =TOMATO_LABOR_COST -> 46054.046 | C45: =TOMATO_CONTRIBUTION -> 33145.954 | D45: TOMATO_LABOR_COST, TOMATO_CONTRIBUTION
A46: Carrot | B46: =CARROT_LABOR_COST -> 19388.903 | C46: =CARROT_CONTRIBUTION -> 13691.097 | D46: CARROT_LABOR_COST, CARROT_CONTRIBUTION
A47: Mesclun | B47: =MESCLUN_LABOR_COST -> 38661.896 | C47: =MESCLUN_CONTRIBUTION -> 15938.104 | D47: MESCLUN_LABOR_COST, MESCLUN_CONTRIBUTION

Sheet Inputs
A1: Inputs - case assumptions
A2: Yellow cells with blue text are the only editable assumptions. Every value is a workbook-level named range. Grey cells are derived formulas.
A4: Name (named range) | B4: Value | C4: Unit | D4: Source | E4: Note
A5: TOMATO_BED_CAP | B5: 20 | C5: beds | D5: Case data, spec.md §Inputs
A6: CARROT_BED_CAP | B6: 20 | C6: beds | D6: Case data, spec.md §Inputs
A7: MESCLUN_BED_CAP | B7: 30 | C7: beds | D7: Case data, spec.md §Inputs
A8: TOMATO_REVENUE_PER_BED | B8: 8800 | C8: $/bed/season | D8: Case data, spec.md §Inputs
A9: CARROT_REVENUE_PER_BED | B9: 2094 | C9: $/bed/season | D9: Case data, spec.md §Inputs
A10: MESCLUN_REVENUE_PER_BED | B10: 2700 | C10: $/bed/season | D10: Case data, spec.md §Inputs
A11: TOMATO_HRS_PER_WEEK_PER_BED | B11: 2.5 | C11: hour/week/bed | D11: Case data, spec.md §Inputs
A12: CARROT_HRS_PER_WEEK_PER_BED | B12: 0.833 | C12: hour/week/bed | D12: Case data, spec.md §Inputs | E12: 5/6 hour (0.8333…) rounded to three decimals; used as published. Effect on profit: spec.md Audit finding A2.
A13: MESCLUN_HRS_PER_WEEK_PER_BED | B13: 1.25 | C13: hour/week/bed | D13: Case data, spec.md §Inputs
A14: TOMATO_FERTILIZER_PER_BED | B14: 880 | C14: $/bed/season | D14: Case data, spec.md §Inputs
A15: CARROT_FERTILIZER_PER_BED | B15: 440 | C15: $/bed/season | D15: Case data, spec.md §Inputs
A16: MESCLUN_FERTILIZER_PER_BED | B16: 880 | C16: $/bed/season | D16: Case data, spec.md §Inputs
A17: TOMATO_DIM_RTRN_PCT | B17: 0.1 | C17: % | D17: Case data, spec.md §Inputs | E17: Spec name TOMATO_DIM_RTRN_% (Excel names cannot contain %). Stored as a decimal: 10% = 0.10.
A18: CARROT_DIM_RTRN_PCT | B18: 0.025 | C18: % | D18: Case data, spec.md §Inputs | E18: Spec name CARROT_DIM_RTRN_%.
A19: MESCLUN_DIM_RTRN_PCT | B19: 0.0125 | C19: % | D19: Case data, spec.md §Inputs | E19: Spec name MESCLUN_DIM_RTRN_%.
A20: SEASON_WEEKS | B20: 36 | C20: weeks | D20: Case data, spec.md §Inputs
A21: TOTAL_BEDS_AVAILABLE | B21: 64 | C21: beds | D21: Case data, spec.md §Inputs
A22: PERMANENT_FIELD_LABOR_HOURS | B22: 720 | C22: hours/season | D22: Case data, spec.md §Inputs | E22: Spec formulas also call this PERMANENT_FIELD_HOURS.
A23: PERMANENT_HOURLY_RATE | B23: 34.72 | C23: $/hour | D23: Case data, spec.md §Inputs | E23: $34.7222… ($25,000 ÷ 720 hours) rounded to the cent; used as published. Effect on profit: spec.md Audit finding A2.
A24: TEMP_WORKER_CAP | B24: 4 | C24: workers | D24: Case data, spec.md §Inputs
A25: TEMP_HOURS_LABOR_PER_WORKER | B25: 1440 | C25: hours/worker/season | D25: Case data, spec.md §Inputs | E25: Spec name TEMP_HOURS_LABOR_PER WORKER (Excel names cannot contain spaces).
A26: TEMP_HOURLY_RATE | B26: 17.36 | C26: $/hour | D26: Case data, spec.md §Inputs | E26: Half the unrounded permanent rate ($17.3611…) rounded to the cent; used as published. Effect on profit: spec.md Audit finding A2.
A27: FIXED_SEASON_COST | B27: 20000 | C27: $/season | D27: Case data, spec.md §Inputs
A29: Derived inputs (formulas - do not edit)
A30: Name (named range) | B30: Value | C30: Unit | D30: Formula | E30: Note
A31: TEMP_HOURS_CAP | B31: =TEMP_HOURS_LABOR_PER_WORKER*TEMP_WORKER_CAP -> 5760 | C31: hours/season | D31: TEMP_HOURS_LABOR_PER_WORKER × TEMP_WORKER_CAP | E31: Spec check value: 5,760 hours
A32: TOTAL_LABOR_HOURS_CAP | B32: =TEMP_HOURS_CAP+PERMANENT_FIELD_LABOR_HOURS -> 6480 | C32: hours/season | D32: TEMP_HOURS_CAP + PERMANENT_FIELD_LABOR_HOURS | E32: Spec check value: 6,480 hours

Sheet Cost Structure
A1: Cost Structure - economics of the current bed mix
A2: Driven by the decision cells on the Optimization sheet. All cells are formulas; named ranges are shown in column A/B.
A4: Crop | B4: Beds | C4: Revenue per bed | D4: Revenue | E4: Fertilizer per bed | F4: Fertilizer | G4: Hours/week/bed | H4: Dim. return | I4: Labor hours | J4: Labor-hours formula
A5: Tomato | B5: =TOMATO_BEDS -> 10 | C5: =TOMATO_REVENUE_PER_BED -> 8800 | D5: =TOMATO_BEDS*TOMATO_REVENUE_PER_BED -> 88000 | E5: =TOMATO_FERTILIZER_PER_BED -> 880 | F5: =TOMATO_BEDS*TOMATO_FERTILIZER_PER_BED -> 8800 | G5: =TOMATO_HRS_PER_WEEK_PER_BED -> 2.5 | H5: =TOMATO_DIM_RTRN_PCT -> 0.1 | I5: =TOMATO_BEDS*TOMATO_HRS_PER_WEEK_PER_BED*SEASON_WEEKS*(1+TOMATO_DIM_RTRN_PCT)^TOMATO_BEDS -> 2334.3682 | J5: TOMATO_BEDS × TOMATO_HRS_PER_WEEK_PER_BED × SEASON_WEEKS × (1 + TOMATO_DIM_RTRN_PCT)^TOMATO_BEDS
A6: Carrot | B6: =CARROT_BEDS -> 20 | C6: =CARROT_REVENUE_PER_BED -> 2094 | D6: =CARROT_BEDS*CARROT_REVENUE_PER_BED -> 41880 | E6: =CARROT_FERTILIZER_PER_BED -> 440 | F6: =CARROT_BEDS*CARROT_FERTILIZER_PER_BED -> 8800 | G6: =CARROT_HRS_PER_WEEK_PER_BED -> 0.833 | H6: =CARROT_DIM_RTRN_PCT -> 0.025 | I6: =CARROT_BEDS*CARROT_HRS_PER_WEEK_PER_BED*SEASON_WEEKS*(1+CARROT_DIM_RTRN_PCT)^CARROT_BEDS -> 982.7766 | J6: CARROT_BEDS × CARROT_HRS_PER_WEEK_PER_BED × SEASON_WEEKS × (1 + CARROT_DIM_RTRN_PCT)^CARROT_BEDS
A7: Mesclun | B7: =MESCLUN_BEDS -> 30 | C7: =MESCLUN_REVENUE_PER_BED -> 2700 | D7: =MESCLUN_BEDS*MESCLUN_REVENUE_PER_BED -> 81000 | E7: =MESCLUN_FERTILIZER_PER_BED -> 880 | F7: =MESCLUN_BEDS*MESCLUN_FERTILIZER_PER_BED -> 26400 | G7: =MESCLUN_HRS_PER_WEEK_PER_BED -> 1.25 | H7: =MESCLUN_DIM_RTRN_PCT -> 0.0125 | I7: =MESCLUN_BEDS*MESCLUN_HRS_PER_WEEK_PER_BED*SEASON_WEEKS*(1+MESCLUN_DIM_RTRN_PCT)^MESCLUN_BEDS -> 1959.678 | J7: MESCLUN_BEDS × MESCLUN_HRS_PER_WEEK_PER_BED × SEASON_WEEKS × (1 + MESCLUN_DIM_RTRN_PCT)^MESCLUN_BEDS
A8: Total | B8: =SUM(B5:B7) -> 60 | D8: =TOMATO_REVENUE+CARROT_REVENUE+MESCLUN_REVENUE -> 210880 | F8: =TOMATO_FERTILIZER+CARROT_FERTILIZER+MESCLUN_FERTILIZER -> 44000 | I8: =TOMATO_LABOR_HRS+CARROT_LABOR_HRS+MESCLUN_LABOR_HRS -> 5276.8228
A11: Labor allocation (permanent hours first, then temporary hours)
A12: Quantity | B12: Named range | C12: Value | D12: Unit | E12: Formula
A13: Total labor hours required | B13: TOTAL_LABOR_HOURS | C13: =TOTAL_LABOR_HOURS -> 5276.8228 | D13: hours | E13: (sum of crop labor hours, above)
A14: Permanent hours used | B14: PERMANENT_HOURS_USED | C14: =MIN(TOTAL_LABOR_HOURS,PERMANENT_FIELD_LABOR_HOURS) -> 720 | D14: hours | E14: MIN(TOTAL_LABOR_HOURS, PERMANENT_FIELD_LABOR_HOURS)
A15: Temporary hours used | B15: TEMP_HOURS_USED | C15: =MAX(0,TOTAL_LABOR_HOURS-PERMANENT_FIELD_LABOR_HOURS) -> 4556.8228 | D15: hours | E15: MAX(0, TOTAL_LABOR_HOURS − PERMANENT_FIELD_LABOR_HOURS)
A16: Permanent labor cost | B16: PERMANENT_LABOR_COST | C16: =PERMANENT_HOURS_USED*PERMANENT_HOURLY_RATE -> 24998.4 | D16: $ | E16: PERMANENT_HOURS_USED × PERMANENT_HOURLY_RATE
A17: Temporary labor cost | B17: TEMP_LABOR_COST | C17: =TEMP_HOURS_USED*TEMP_HOURLY_RATE -> 79106.445 | D17: $ | E17: TEMP_HOURS_USED × TEMP_HOURLY_RATE
A18: Total labor cost | B18: TOTAL_LABOR_COST | C18: =PERMANENT_LABOR_COST+TEMP_LABOR_COST -> 104104.84 | D18: $ | E18: PERMANENT_LABOR_COST + TEMP_LABOR_COST
A19: Blended labor rate | B19: BLENDED_LABOR_RATE | C19: =IF(TOTAL_LABOR_HOURS>0,TOTAL_LABOR_COST/TOTAL_LABOR_HOURS,"n/a - zero labor hours") -> 19.728698 | D19: $/hour | E19: TOTAL_LABOR_COST / TOTAL_LABOR_HOURS, only when TOTAL_LABOR_HOURS > 0 (division-by-zero guard)
A20: Temporary workers required (whole workers) | B20: TEMP_WORKERS_REQUIRED | C20: =ROUNDUP(TEMP_HOURS_USED/TEMP_HOURS_LABOR_PER_WORKER,0) -> 4 | D20: workers | E20: ROUNDUP(TEMP_HOURS_USED / TEMP_HOURS_LABOR_PER_WORKER, 0)
A21: Temporary workers required (full-time equivalent) | B21: TEMP_WORKERS_FTE | C21: =TEMP_HOURS_USED/TEMP_HOURS_LABOR_PER_WORKER -> 3.1644603 | D21: workers | E21: TEMP_HOURS_USED / TEMP_HOURS_LABOR_PER_WORKER
A22: Remaining unused labor hours | B22: UNUSED_LABOR_HOURS | C22: =TOTAL_LABOR_HOURS_CAP-TOTAL_LABOR_HOURS -> 1203.1772 | D22: hours | E22: TOTAL_LABOR_HOURS_CAP − TOTAL_LABOR_HOURS
A23: Unused beds | B23: UNUSED_BEDS | C23: =TOTAL_BEDS_AVAILABLE-TOTAL_BEDS_USED -> 4 | D23: beds | E23: TOTAL_BEDS_AVAILABLE − TOTAL_BEDS_USED
A25: Seasonal profit and loss
A26: Line | B26: Named range | C26: Value | D26: Unit | E26: Formula
A27: Total revenue | B27: TOTAL_REVENUE | C27: =TOTAL_REVENUE -> 210880 | D27: $ | E27: (from crop table)
A28: Less: total fertilizer | B28: TOTAL_FERTILIZER | C28: =-TOTAL_FERTILIZER -> -44000 | D28: $ | E28: (from crop table)
A29: Less: total labor cost | B29: TOTAL_LABOR_COST | C29: =-TOTAL_LABOR_COST -> -104104.84 | D29: $ | E29: (from labor allocation)
A30: Less: fixed season cost | B30: FIXED_SEASON_COST | C30: =-FIXED_SEASON_COST -> -20000 | D30: $ | E30: (input)
A31: Total costs | B31: TOTAL_COSTS | C31: =TOTAL_FERTILIZER+TOTAL_LABOR_COST+FIXED_SEASON_COST -> 168104.84 | D31: $ | E31: TOTAL_FERTILIZER + TOTAL_LABOR_COST + FIXED_SEASON_COST
A32: Seasonal profit | B32: SEASONAL_PROFIT | C32: =TOTAL_REVENUE-TOTAL_FERTILIZER-TOTAL_LABOR_COST-FIXED_SEASON_COST -> 42775.155 | D32: $ | E32: TOTAL_REVENUE − TOTAL_FERTILIZER − TOTAL_LABOR_COST − FIXED_SEASON_COST
A35: Labor cost and contribution by crop (blended labor rate; for reporting only, the optimization uses SEASONAL_PROFIT)
A36: Crop | B36: Labor hours | C36: Blended labor rate | D36: Crop labor cost | E36: Formula | F36: Revenue | G36: Fertilizer | H36: Crop contribution | J36: Named ranges
A37: Tomato | B37: =TOMATO_LABOR_HRS -> 2334.3682 | C37: =IF(TOTAL_LABOR_HOURS>0,BLENDED_LABOR_RATE,0) -> 19.728698 | D37: =IF(TOTAL_LABOR_HOURS>0,TOMATO_LABOR_HRS*BLENDED_LABOR_RATE,0) -> 46054.046 | E37: TOMATO_LABOR_COST = TOMATO_LABOR_HRS × BLENDED_LABOR_RATE (0 when TOTAL_LABOR_HOURS = 0) | F37: =TOMATO_REVENUE -> 88000 | G37: =TOMATO_FERTILIZER -> 8800 | H37: =TOMATO_REVENUE-TOMATO_FERTILIZER-TOMATO_LABOR_COST -> 33145.954 | J37: TOMATO_LABOR_COST, TOMATO_CONTRIBUTION = TOMATO_REVENUE − TOMATO_FERTILIZER − TOMATO_LABOR_COST
A38: Carrot | B38: =CARROT_LABOR_HRS -> 982.7766 | C38: =IF(TOTAL_LABOR_HOURS>0,BLENDED_LABOR_RATE,0) -> 19.728698 | D38: =IF(TOTAL_LABOR_HOURS>0,CARROT_LABOR_HRS*BLENDED_LABOR_RATE,0) -> 19388.903 | E38: CARROT_LABOR_COST = CARROT_LABOR_HRS × BLENDED_LABOR_RATE (0 when TOTAL_LABOR_HOURS = 0) | F38: =CARROT_REVENUE -> 41880 | G38: =CARROT_FERTILIZER -> 8800 | H38: =CARROT_REVENUE-CARROT_FERTILIZER-CARROT_LABOR_COST -> 13691.097 | J38: CARROT_LABOR_COST, CARROT_CONTRIBUTION = CARROT_REVENUE − CARROT_FERTILIZER − CARROT_LABOR_COST
A39: Mesclun | B39: =MESCLUN_LABOR_HRS -> 1959.678 | C39: =IF(TOTAL_LABOR_HOURS>0,BLENDED_LABOR_RATE,0) -> 19.728698 | D39: =IF(TOTAL_LABOR_HOURS>0,MESCLUN_LABOR_HRS*BLENDED_LABOR_RATE,0) -> 38661.896 | E39: MESCLUN_LABOR_COST = MESCLUN_LABOR_HRS × BLENDED_LABOR_RATE (0 when TOTAL_LABOR_HOURS = 0) | F39: =MESCLUN_REVENUE -> 81000 | G39: =MESCLUN_FERTILIZER -> 26400 | H39: =MESCLUN_REVENUE-MESCLUN_FERTILIZER-MESCLUN_LABOR_COST -> 15938.104 | J39: MESCLUN_LABOR_COST, MESCLUN_CONTRIBUTION = MESCLUN_REVENUE − MESCLUN_FERTILIZER − MESCLUN_LABOR_COST
A40: Total | B40: =SUM(B37:B39) -> 5276.8228 | D40: =SUM(D37:D39) -> 104104.84 | E40: Crop labor costs sum to TOTAL_LABOR_COST (tested on Checks, L1) | F40: =SUM(F37:F39) -> 210880 | G40: =SUM(G37:G39) -> 44000 | H40: =SUM(H37:H39) -> 62775.155
A41: Contribution = revenue − fertilizer − labor at the blended rate. It does not include FIXED_SEASON_COST, and it shows each crop's average share of labor cost, not its cost at the margin.

Sheet Marginal Cost
A1: Marginal cost schedules and standalone P = MC diagnostics
A2: Integer q = 0 to each crop's bed cap. The spec schedule (columns O–R) prices each crop at its MC_RATE (spec.md, Calculation Logic): tomatoes at TEMP_HOURLY_RATE, carrots and mesclun at PERMANENT_HOURLY_RATE. Columns C–D and G–N show both single rates for reference. Columns S–V price labor permanent hours first, as SEASONAL_PROFIT does (information only).
A4: Standalone P = MC points (largest q where price ≥ marginal total cost). Each single-rate schedule is priced at one labor rate, so its marginal cost rises with q; the farm's actual labor cost uses permanent hours first (see spec.md Audit finding A1), and that schedule falls where the 720 permanent hours run out: in one step for tomatoes, over two beds for carrots and mesclun.
A5: Crop | B5: Price (revenue per bed) | C5: P = MC point @ permanent rate (beds) | D5: P = MC point @ temporary rate (beds) | E5: Bed cap | F5: MC_RATE ($/hr) | G5: MC_RATE is | H5: P = MC point @ MC_RATE (spec, V3) | I5: P = MC point, permanent hours first (info) | J5: Times MC falls, permanent hours first (info)
A6: Tomato | B6: =TOMATO_REVENUE_PER_BED -> 8800 | C6: =SUMPRODUCT(MAX((M14:M33=1)*A14:A33)) -> 5 | D6: =SUMPRODUCT(MAX((N14:N33=1)*A14:A33)) -> 10 | E6: =TOMATO_BED_CAP -> 20 | F6: =TEMP_HOURLY_RATE -> 17.36 | G6: TEMP_HOURLY_RATE | H6: =SUMPRODUCT(MAX((R14:R33=1)*A14:A33)) -> 10 | I6: =SUMPRODUCT(MAX((V14:V33=1)*A14:A33)) -> 10 | J6: =SUMPRODUCT(--(U15:U33<U14:U32)) -> 1
A7: Carrot | B7: =CARROT_REVENUE_PER_BED -> 2094 | C7: =SUMPRODUCT(MAX((M39:M58=1)*A39:A58)) -> 10 | D7: =SUMPRODUCT(MAX((N39:N58=1)*A39:A58)) -> 20 | E7: =CARROT_BED_CAP -> 20 | F7: =PERMANENT_HOURLY_RATE -> 34.72 | G7: PERMANENT_HOURLY_RATE | H7: =SUMPRODUCT(MAX((R39:R58=1)*A39:A58)) -> 10 | I7: =SUMPRODUCT(MAX((V39:V58=1)*A39:A58)) -> 20 | J7: =SUMPRODUCT(--(U40:U58<U39:U57)) -> 2
A8: Mesclun | B8: =MESCLUN_REVENUE_PER_BED -> 2700 | C8: =SUMPRODUCT(MAX((M64:M93=1)*A64:A93)) -> 6 | D8: =SUMPRODUCT(MAX((N64:N93=1)*A64:A93)) -> 30 | E8: =MESCLUN_BED_CAP -> 30 | F8: =PERMANENT_HOURLY_RATE -> 34.72 | G8: PERMANENT_HOURLY_RATE | H8: =SUMPRODUCT(MAX((R64:R93=1)*A64:A93)) -> 6 | I8: =SUMPRODUCT(MAX((V64:V93=1)*A64:A93)) -> 30 | J8: =SUMPRODUCT(--(U65:U93<U64:U92)) -> 2
A11: Tomato schedule | C11: LABOR_HOURS(q) = q × TOMATO_HRS_PER_WEEK_PER_BED × SEASON_WEEKS × (1 + TOMATO_DIM_RTRN_PCT)^q
A12: q (beds) | B12: Labor hours | C12: Labor $ @ permanent rate | D12: Labor $ @ temp rate | E12: Fertilizer $ | F12: Marginal labor hours | G12: Marginal labor $ @ permanent | H12: Marginal labor $ @ temp | I12: Marginal fertilizer $ | J12: Marginal total cost @ permanent | K12: Marginal total cost @ temp | L12: Price P (revenue/bed) | M12: P ≥ MC @ permanent (1/0) | N12: P ≥ MC @ temp (1/0) | O12: Labor $ @ MC_RATE | P12: Marginal labor $ @ MC_RATE | Q12: Marginal total cost @ MC_RATE (spec) | R12: P ≥ MC @ MC_RATE (1/0) | S12: Labor $, permanent hours first (info) | T12: Marginal labor $, permanent hours first | U12: Marginal total cost, permanent hours first | V12: P ≥ MC, permanent hours first (1/0)
A13: =ROW()-ROW($A$13) -> 0 | B13: =A13*TOMATO_HRS_PER_WEEK_PER_BED*SEASON_WEEKS*(1+TOMATO_DIM_RTRN_PCT)^A13 -> 0 | C13: =B13*PERMANENT_HOURLY_RATE -> 0 | D13: =B13*TEMP_HOURLY_RATE -> 0 | E13: =A13*TOMATO_FERTILIZER_PER_BED -> 0 | F13: — | G13: — | H13: — | I13: — | J13: — | K13: — | L13: =TOMATO_REVENUE_PER_BED -> 8800 | M13: — | N13: — | O13: =B13*TOMATO_MC_RATE -> 0 | P13: — | Q13: — | R13: — | S13: =MIN(B13,PERMANENT_FIELD_LABOR_HOURS)*PERMANENT_HOURLY_RATE+MAX(0,B13-PERMANENT_FIELD_LABOR_HOURS)*TEMP_HOURLY_RATE -> 0 | T13: — | U13: — | V13: —
A14: =ROW()-ROW($A$13) -> 1 | B14: =A14*TOMATO_HRS_PER_WEEK_PER_BED*SEASON_WEEKS*(1+TOMATO_DIM_RTRN_PCT)^A14 -> 99 | C14: =B14*PERMANENT_HOURLY_RATE -> 3437.28 | D14: =B14*TEMP_HOURLY_RATE -> 1718.64 | E14: =A14*TOMATO_FERTILIZER_PER_BED -> 880 | F14: =B14-B13 -> 99 | G14: =C14-C13 -> 3437.28 | H14: =D14-D13 -> 1718.64 | I14: =E14-E13 -> 880 | J14: =G14+I14 -> 4317.28 | K14: =H14+I14 -> 2598.64 | L14: =TOMATO_REVENUE_PER_BED -> 8800 | M14: =IF(L14>=J14,1,0) -> 1 | N14: =IF(L14>=K14,1,0) -> 1 | O14: =B14*TOMATO_MC_RATE -> 1718.64 | P14: =O14-O13 -> 1718.64 | Q14: =P14+I14 -> 2598.64 | R14: =IF(L14>=Q14,1,0) -> 1 | S14: =MIN(B14,PERMANENT_FIELD_LABOR_HOURS)*PERMANENT_HOURLY_RATE+MAX(0,B14-PERMANENT_FIELD_LABOR_HOURS)*TEMP_HOURLY_RATE -> 3437.28 | T14: =S14-S13 -> 3437.28 | U14: =T14+I14 -> 4317.28 | V14: =IF(L14>=U14,1,0) -> 1
A15: =ROW()-ROW($A$13) -> 2 | B15: =A15*TOMATO_HRS_PER_WEEK_PER_BED*SEASON_WEEKS*(1+TOMATO_DIM_RTRN_PCT)^A15 -> 217.8 | C15: =B15*PERMANENT_HOURLY_RATE -> 7562.016 | D15: =B15*TEMP_HOURLY_RATE -> 3781.008 | E15: =A15*TOMATO_FERTILIZER_PER_BED -> 1760 | F15: =B15-B14 -> 118.8 | G15: =C15-C14 -> 4124.736 | H15: =D15-D14 -> 2062.368 | I15: =E15-E14 -> 880 | J15: =G15+I15 -> 5004.736 | K15: =H15+I15 -> 2942.368 | L15: =TOMATO_REVENUE_PER_BED -> 8800 | M15: =IF(L15>=J15,1,0) -> 1 | N15: =IF(L15>=K15,1,0) -> 1 | O15: =B15*TOMATO_MC_RATE -> 3781.008 | P15: =O15-O14 -> 2062.368 | Q15: =P15+I15 -> 2942.368 | R15: =IF(L15>=Q15,1,0) -> 1 | S15: =MIN(B15,PERMANENT_FIELD_LABOR_HOURS)*PERMANENT_HOURLY_RATE+MAX(0,B15-PERMANENT_FIELD_LABOR_HOURS)*TEMP_HOURLY_RATE -> 7562.016 | T15: =S15-S14 -> 4124.736 | U15: =T15+I15 -> 5004.736 | V15: =IF(L15>=U15,1,0) -> 1
A16: =ROW()-ROW($A$13) -> 3 | B16: =A16*TOMATO_HRS_PER_WEEK_PER_BED*SEASON_WEEKS*(1+TOMATO_DIM_RTRN_PCT)^A16 -> 359.37 | C16: =B16*PERMANENT_HOURLY_RATE -> 12477.326 | D16: =B16*TEMP_HOURLY_RATE -> 6238.6632 | E16: =A16*TOMATO_FERTILIZER_PER_BED -> 2640 | F16: =B16-B15 -> 141.57 | G16: =C16-C15 -> 4915.3104 | H16: =D16-D15 -> 2457.6552 | I16: =E16-E15 -> 880 | J16: =G16+I16 -> 5795.3104 | K16: =H16+I16 -> 3337.6552 | L16: =TOMATO_REVENUE_PER_BED -> 8800 | M16: =IF(L16>=J16,1,0) -> 1 | N16: =IF(L16>=K16,1,0) -> 1 | O16: =B16*TOMATO_MC_RATE -> 6238.6632 | P16: =O16-O15 -> 2457.6552 | Q16: =P16+I16 -> 3337.6552 | R16: =IF(L16>=Q16,1,0) -> 1 | S16: =MIN(B16,PERMANENT_FIELD_LABOR_HOURS)*PERMANENT_HOURLY_RATE+MAX(0,B16-PERMANENT_FIELD_LABOR_HOURS)*TEMP_HOURLY_RATE -> 12477.326 | T16: =S16-S15 -> 4915.3104 | U16: =T16+I16 -> 5795.3104 | V16: =IF(L16>=U16,1,0) -> 1
A17: =ROW()-ROW($A$13) -> 4 | B17: =A17*TOMATO_HRS_PER_WEEK_PER_BED*SEASON_WEEKS*(1+TOMATO_DIM_RTRN_PCT)^A17 -> 527.076 | C17: =B17*PERMANENT_HOURLY_RATE -> 18300.079 | D17: =B17*TEMP_HOURLY_RATE -> 9150.0394 | E17: =A17*TOMATO_FERTILIZER_PER_BED -> 3520 | F17: =B17-B16 -> 167.706 | G17: =C17-C16 -> 5822.7523 | H17: =D17-D16 -> 2911.3762 | I17: =E17-E16 -> 880 | J17: =G17+I17 -> 6702.7523 | K17: =H17+I17 -> 3791.3762 | L17: =TOMATO_REVENUE_PER_BED -> 8800 | M17: =IF(L17>=J17,1,0) -> 1 | N17: =IF(L17>=K17,1,0) -> 1 | O17: =B17*TOMATO_MC_RATE -> 9150.0394 | P17: =O17-O16 -> 2911.3762 | Q17: =P17+I17 -> 3791.3762 | R17: =IF(L17>=Q17,1,0) -> 1 | S17: =MIN(B17,PERMANENT_FIELD_LABOR_HOURS)*PERMANENT_HOURLY_RATE+MAX(0,B17-PERMANENT_FIELD_LABOR_HOURS)*TEMP_HOURLY_RATE -> 18300.079 | T17: =S17-S16 -> 5822.7523 | U17: =T17+I17 -> 6702.7523 | V17: =IF(L17>=U17,1,0) -> 1
A18: =ROW()-ROW($A$13) -> 5 | B18: =A18*TOMATO_HRS_PER_WEEK_PER_BED*SEASON_WEEKS*(1+TOMATO_DIM_RTRN_PCT)^A18 -> 724.7295 | C18: =B18*PERMANENT_HOURLY_RATE -> 25162.608 | D18: =B18*TEMP_HOURLY_RATE -> 12581.304 | E18: =A18*TOMATO_FERTILIZER_PER_BED -> 4400 | F18: =B18-B17 -> 197.6535 | G18: =C18-C17 -> 6862.5295 | H18: =D18-D17 -> 3431.2648 | I18: =E18-E17 -> 880 | J18: =G18+I18 -> 7742.5295 | K18: =H18+I18 -> 4311.2648 | L18: =TOMATO_REVENUE_PER_BED -> 8800 | M18: =IF(L18>=J18,1,0) -> 1 | N18: =IF(L18>=K18,1,0) -> 1 | O18: =B18*TOMATO_MC_RATE -> 12581.304 | P18: =O18-O17 -> 3431.2648 | Q18: =P18+I18 -> 4311.2648 | R18: =IF(L18>=Q18,1,0) -> 1 | S18: =MIN(B18,PERMANENT_FIELD_LABOR_HOURS)*PERMANENT_HOURLY_RATE+MAX(0,B18-PERMANENT_FIELD_LABOR_HOURS)*TEMP_HOURLY_RATE -> 25080.504 | T18: =S18-S17 -> 6780.4254 | U18: =T18+I18 -> 7660.4254 | V18: =IF(L18>=U18,1,0) -> 1
A19: =ROW()-ROW($A$13) -> 6 | B19: =A19*TOMATO_HRS_PER_WEEK_PER_BED*SEASON_WEEKS*(1+TOMATO_DIM_RTRN_PCT)^A19 -> 956.64294 | C19: =B19*PERMANENT_HOURLY_RATE -> 33214.643 | D19: =B19*TEMP_HOURLY_RATE -> 16607.321 | E19: =A19*TOMATO_FERTILIZER_PER_BED -> 5280 | F19: =B19-B18 -> 231.91344 | G19: =C19-C18 -> 8052.0346 | H19: =D19-D18 -> 4026.0173 | I19: =E19-E18 -> 880 | J19: =G19+I19 -> 8932.0346 | K19: =H19+I19 -> 4906.0173 | L19: =TOMATO_REVENUE_PER_BED -> 8800 | M19: =IF(L19>=J19,1,0) -> 0 | N19: =IF(L19>=K19,1,0) -> 1 | O19: =B19*TOMATO_MC_RATE -> 16607.321 | P19: =O19-O18 -> 4026.0173 | Q19: =P19+I19 -> 4906.0173 | R19: =IF(L19>=Q19,1,0) -> 1 | S19: =MIN(B19,PERMANENT_FIELD_LABOR_HOURS)*PERMANENT_HOURLY_RATE+MAX(0,B19-PERMANENT_FIELD_LABOR_HOURS)*TEMP_HOURLY_RATE -> 29106.521 | T19: =S19-S18 -> 4026.0173 | U19: =T19+I19 -> 4906.0173 | V19: =IF(L19>=U19,1,0) -> 1
A20: =ROW()-ROW($A$13) -> 7 | B20: =A20*TOMATO_HRS_PER_WEEK_PER_BED*SEASON_WEEKS*(1+TOMATO_DIM_RTRN_PCT)^A20 -> 1227.6918 | C20: =B20*PERMANENT_HOURLY_RATE -> 42625.458 | D20: =B20*TEMP_HOURLY_RATE -> 21312.729 | E20: =A20*TOMATO_FERTILIZER_PER_BED -> 6160 | F20: =B20-B19 -> 271.04883 | G20: =C20-C19 -> 9410.8155 | H20: =D20-D19 -> 4705.4077 | I20: =E20-E19 -> 880 | J20: =G20+I20 -> 10290.815 | K20: =H20+I20 -> 5585.4077 | L20: =TOMATO_REVENUE_PER_BED -> 8800 | M20: =IF(L20>=J20,1,0) -> 0 | N20: =IF(L20>=K20,1,0) -> 1 | O20: =B20*TOMATO_MC_RATE -> 21312.729 | P20: =O20-O19 -> 4705.4077 | Q20: =P20+I20 -> 5585.4077 | R20: =IF(L20>=Q20,1,0) -> 1 | S20: =MIN(B20,PERMANENT_FIELD_LABOR_HOURS)*PERMANENT_HOURLY_RATE+MAX(0,B20-PERMANENT_FIELD_LABOR_HOURS)*TEMP_HOURLY_RATE -> 33811.929 | T20: =S20-S19 -> 4705.4077 | U20: =T20+I20 -> 5585.4077 | V20: =IF(L20>=U20,1,0) -> 1
A21: =ROW()-ROW($A$13) -> 8 | B21: =A21*TOMATO_HRS_PER_WEEK_PER_BED*SEASON_WEEKS*(1+TOMATO_DIM_RTRN_PCT)^A21 -> 1543.3839 | C21: =B21*PERMANENT_HOURLY_RATE -> 53586.291 | D21: =B21*TEMP_HOURLY_RATE -> 26793.145 | E21: =A21*TOMATO_FERTILIZER_PER_BED -> 7040 | F21: =B21-B20 -> 315.69217 | G21: =C21-C20 -> 10960.832 | H21: =D21-D20 -> 5480.4161 | I21: =E21-E20 -> 880 | J21: =G21+I21 -> 11840.832 | K21: =H21+I21 -> 6360.4161 | L21: =TOMATO_REVENUE_PER_BED -> 8800 | M21: =IF(L21>=J21,1,0) -> 0 | N21: =IF(L21>=K21,1,0) -> 1 | O21: =B21*TOMATO_MC_RATE -> 26793.145 | P21: =O21-O20 -> 5480.4161 | Q21: =P21+I21 -> 6360.4161 | R21: =IF(L21>=Q21,1,0) -> 1 | S21: =MIN(B21,PERMANENT_FIELD_LABOR_HOURS)*PERMANENT_HOURLY_RATE+MAX(0,B21-PERMANENT_FIELD_LABOR_HOURS)*TEMP_HOURLY_RATE -> 39292.345 | T21: =S21-S20 -> 5480.4161 | U21: =T21+I21 -> 6360.4161 | V21: =IF(L21>=U21,1,0) -> 1
A22: =ROW()-ROW($A$13) -> 9 | B22: =A22*TOMATO_HRS_PER_WEEK_PER_BED*SEASON_WEEKS*(1+TOMATO_DIM_RTRN_PCT)^A22 -> 1909.9376 | C22: =B22*PERMANENT_HOURLY_RATE -> 66313.035 | D22: =B22*TEMP_HOURLY_RATE -> 33156.517 | E22: =A22*TOMATO_FERTILIZER_PER_BED -> 7920 | F22: =B22-B21 -> 366.55369 | G22: =C22-C21 -> 12726.744 | H22: =D22-D21 -> 6363.372 | I22: =E22-E21 -> 880 | J22: =G22+I22 -> 13606.744 | K22: =H22+I22 -> 7243.372 | L22: =TOMATO_REVENUE_PER_BED -> 8800 | M22: =IF(L22>=J22,1,0) -> 0 | N22: =IF(L22>=K22,1,0) -> 1 | O22: =B22*TOMATO_MC_RATE -> 33156.517 | P22: =O22-O21 -> 6363.372 | Q22: =P22+I22 -> 7243.372 | R22: =IF(L22>=Q22,1,0) -> 1 | S22: =MIN(B22,PERMANENT_FIELD_LABOR_HOURS)*PERMANENT_HOURLY_RATE+MAX(0,B22-PERMANENT_FIELD_LABOR_HOURS)*TEMP_HOURLY_RATE -> 45655.717 | T22: =S22-S21 -> 6363.372 | U22: =T22+I22 -> 7243.372 | V22: =IF(L22>=U22,1,0) -> 1
A23: =ROW()-ROW($A$13) -> 10 | B23: =A23*TOMATO_HRS_PER_WEEK_PER_BED*SEASON_WEEKS*(1+TOMATO_DIM_RTRN_PCT)^A23 -> 2334.3682 | C23: =B23*PERMANENT_HOURLY_RATE -> 81049.264 | D23: =B23*TEMP_HOURLY_RATE -> 40524.632 | E23: =A23*TOMATO_FERTILIZER_PER_BED -> 8800 | F23: =B23-B22 -> 424.43058 | G23: =C23-C22 -> 14736.23 | H23: =D23-D22 -> 7368.1149 | I23: =E23-E22 -> 880 | J23: =G23+I23 -> 15616.23 | K23: =H23+I23 -> 8248.1149 | L23: =TOMATO_REVENUE_PER_BED -> 8800 | M23: =IF(L23>=J23,1,0) -> 0 | N23: =IF(L23>=K23,1,0) -> 1 | O23: =B23*TOMATO_MC_RATE -> 40524.632 | P23: =O23-O22 -> 7368.1149 | Q23: =P23+I23 -> 8248.1149 | R23: =IF(L23>=Q23,1,0) -> 1 | S23: =MIN(B23,PERMANENT_FIELD_LABOR_HOURS)*PERMANENT_HOURLY_RATE+MAX(0,B23-PERMANENT_FIELD_LABOR_HOURS)*TEMP_HOURLY_RATE -> 53023.832 | T23: =S23-S22 -> 7368.1149 | U23: =T23+I23 -> 8248.1149 | V23: =IF(L23>=U23,1,0) -> 1
A24: =ROW()-ROW($A$13) -> 11 | B24: =A24*TOMATO_HRS_PER_WEEK_PER_BED*SEASON_WEEKS*(1+TOMATO_DIM_RTRN_PCT)^A24 -> 2824.5855 | C24: =B24*PERMANENT_HOURLY_RATE -> 98069.61 | D24: =B24*TEMP_HOURLY_RATE -> 49034.805 | E24: =A24*TOMATO_FERTILIZER_PER_BED -> 9680 | F24: =B24-B23 -> 490.21732 | G24: =C24-C23 -> 17020.346 | H24: =D24-D23 -> 8510.1728 | I24: =E24-E23 -> 880 | J24: =G24+I24 -> 17900.346 | K24: =H24+I24 -> 9390.1728 | L24: =TOMATO_REVENUE_PER_BED -> 8800 | M24: =IF(L24>=J24,1,0) -> 0 | N24: =IF(L24>=K24,1,0) -> 0 | O24: =B24*TOMATO_MC_RATE -> 49034.805 | P24: =O24-O23 -> 8510.1728 | Q24: =P24+I24 -> 9390.1728 | R24: =IF(L24>=Q24,1,0) -> 0 | S24: =MIN(B24,PERMANENT_FIELD_LABOR_HOURS)*PERMANENT_HOURLY_RATE+MAX(0,B24-PERMANENT_FIELD_LABOR_HOURS)*TEMP_HOURLY_RATE -> 61534.005 | T24: =S24-S23 -> 8510.1728 | U24: =T24+I24 -> 9390.1728 | V24: =IF(L24>=U24,1,0) -> 0
A25: =ROW()-ROW($A$13) -> 12 | B25: =A25*TOMATO_HRS_PER_WEEK_PER_BED*SEASON_WEEKS*(1+TOMATO_DIM_RTRN_PCT)^A25 -> 3389.5026 | C25: =B25*PERMANENT_HOURLY_RATE -> 117683.53 | D25: =B25*TEMP_HOURLY_RATE -> 58841.766 | E25: =A25*TOMATO_FERTILIZER_PER_BED -> 10560 | F25: =B25-B24 -> 564.91711 | G25: =C25-C24 -> 19613.922 | H25: =D25-D24 -> 9806.961 | I25: =E25-E24 -> 880 | J25: =G25+I25 -> 20493.922 | K25: =H25+I25 -> 10686.961 | L25: =TOMATO_REVENUE_PER_BED -> 8800 | M25: =IF(L25>=J25,1,0) -> 0 | N25: =IF(L25>=K25,1,0) -> 0 | O25: =B25*TOMATO_MC_RATE -> 58841.766 | P25: =O25-O24 -> 9806.961 | Q25: =P25+I25 -> 10686.961 | R25: =IF(L25>=Q25,1,0) -> 0 | S25: =MIN(B25,PERMANENT_FIELD_LABOR_HOURS)*PERMANENT_HOURLY_RATE+MAX(0,B25-PERMANENT_FIELD_LABOR_HOURS)*TEMP_HOURLY_RATE -> 71340.966 | T25: =S25-S24 -> 9806.961 | U25: =T25+I25 -> 10686.961 | V25: =IF(L25>=U25,1,0) -> 0
... A33: =ROW()-ROW($A$13) -> 20 | B33: =A33*TOMATO_HRS_PER_WEEK_PER_BED*SEASON_WEEKS*(1+TOMATO_DIM_RTRN_PCT)^A33 -> 12109.5 | C33: =B33*PERMANENT_HOURLY_RATE -> 420441.84 | D33: =B33*TEMP_HOURLY_RATE -> 210220.92 | E33: =A33*TOMATO_FERTILIZER_PER_BED -> 17600 | F33: =B33-B32 -> 1651.2954 | G33: =C33-C32 -> 57332.978 | H33: =D33-D32 -> 28666.489 | I33: =E33-E32 -> 880 | J33: =G33+I33 -> 58212.978 | K33: =H33+I33 -> 29546.489 | L33: =TOMATO_REVENUE_PER_BED -> 8800 | M33: =IF(L33>=J33,1,0) -> 0 | N33: =IF(L33>=K33,1,0) -> 0 | O33: =B33*TOMATO_MC_RATE -> 210220.92 | P33: =O33-O32 -> 28666.489 | Q33: =P33+I33 -> 29546.489 | R33: =IF(L33>=Q33,1,0) -> 0 | S33: =MIN(B33,PERMANENT_FIELD_LABOR_HOURS)*PERMANENT_HOURLY_RATE+MAX(0,B33-PERMANENT_FIELD_LABOR_HOURS)*TEMP_HOURLY_RATE -> 222720.12 | T33: =S33-S32 -> 28666.489 | U33: =T33+I33 -> 29546.489 | V33: =IF(L33>=U33,1,0) -> 0
A36: Carrot schedule | C36: LABOR_HOURS(q) = q × CARROT_HRS_PER_WEEK_PER_BED × SEASON_WEEKS × (1 + CARROT_DIM_RTRN_PCT)^q
A37: q (beds) | B37: Labor hours | C37: Labor $ @ permanent rate | D37: Labor $ @ temp rate | E37: Fertilizer $ | F37: Marginal labor hours | G37: Marginal labor $ @ permanent | H37: Marginal labor $ @ temp | I37: Marginal fertilizer $ | J37: Marginal total cost @ permanent | K37: Marginal total cost @ temp | L37: Price P (revenue/bed) | M37: P ≥ MC @ permanent (1/0) | N37: P ≥ MC @ temp (1/0) | O37: Labor $ @ MC_RATE | P37: Marginal labor $ @ MC_RATE | Q37: Marginal total cost @ MC_RATE (spec) | R37: P ≥ MC @ MC_RATE (1/0) | S37: Labor $, permanent hours first (info) | T37: Marginal labor $, permanent hours first | U37: Marginal total cost, permanent hours first | V37: P ≥ MC, permanent hours first (1/0)
A38: =ROW()-ROW($A$38) -> 0 | B38: =A38*CARROT_HRS_PER_WEEK_PER_BED*SEASON_WEEKS*(1+CARROT_DIM_RTRN_PCT)^A38 -> 0 | C38: =B38*PERMANENT_HOURLY_RATE -> 0 | D38: =B38*TEMP_HOURLY_RATE -> 0 | E38: =A38*CARROT_FERTILIZER_PER_BED -> 0 | F38: — | G38: — | H38: — | I38: — | J38: — | K38: — | L38: =CARROT_REVENUE_PER_BED -> 2094 | M38: — | N38: — | O38: =B38*CARROT_MC_RATE -> 0 | P38: — | Q38: — | R38: — | S38: =MIN(B38,PERMANENT_FIELD_LABOR_HOURS)*PERMANENT_HOURLY_RATE+MAX(0,B38-PERMANENT_FIELD_LABOR_HOURS)*TEMP_HOURLY_RATE -> 0 | T38: — | U38: — | V38: —
A39: =ROW()-ROW($A$38) -> 1 | B39: =A39*CARROT_HRS_PER_WEEK_PER_BED*SEASON_WEEKS*(1+CARROT_DIM_RTRN_PCT)^A39 -> 30.7377 | C39: =B39*PERMANENT_HOURLY_RATE -> 1067.2129 | D39: =B39*TEMP_HOURLY_RATE -> 533.60647 | E39: =A39*CARROT_FERTILIZER_PER_BED -> 440 | F39: =B39-B38 -> 30.7377 | G39: =C39-C38 -> 1067.2129 | H39: =D39-D38 -> 533.60647 | I39: =E39-E38 -> 440 | J39: =G39+I39 -> 1507.2129 | K39: =H39+I39 -> 973.60647 | L39: =CARROT_REVENUE_PER_BED -> 2094 | M39: =IF(L39>=J39,1,0) -> 1 | N39: =IF(L39>=K39,1,0) -> 1 | O39: =B39*CARROT_MC_RATE -> 1067.2129 | P39: =O39-O38 -> 1067.2129 | Q39: =P39+I39 -> 1507.2129 | R39: =IF(L39>=Q39,1,0) -> 1 | S39: =MIN(B39,PERMANENT_FIELD_LABOR_HOURS)*PERMANENT_HOURLY_RATE+MAX(0,B39-PERMANENT_FIELD_LABOR_HOURS)*TEMP_HOURLY_RATE -> 1067.2129 | T39: =S39-S38 -> 1067.2129 | U39: =T39+I39 -> 1507.2129 | V39: =IF(L39>=U39,1,0) -> 1
A40: =ROW()-ROW($A$38) -> 2 | B40: =A40*CARROT_HRS_PER_WEEK_PER_BED*SEASON_WEEKS*(1+CARROT_DIM_RTRN_PCT)^A40 -> 63.012285 | C40: =B40*PERMANENT_HOURLY_RATE -> 2187.7865 | D40: =B40*TEMP_HOURLY_RATE -> 1093.8933 | E40: =A40*CARROT_FERTILIZER_PER_BED -> 880 | F40: =B40-B39 -> 32.274585 | G40: =C40-C39 -> 1120.5736 | H40: =D40-D39 -> 560.2868 | I40: =E40-E39 -> 440 | J40: =G40+I40 -> 1560.5736 | K40: =H40+I40 -> 1000.2868 | L40: =CARROT_REVENUE_PER_BED -> 2094 | M40: =IF(L40>=J40,1,0) -> 1 | N40: =IF(L40>=K40,1,0) -> 1 | O40: =B40*CARROT_MC_RATE -> 2187.7865 | P40: =O40-O39 -> 1120.5736 | Q40: =P40+I40 -> 1560.5736 | R40: =IF(L40>=Q40,1,0) -> 1 | S40: =MIN(B40,PERMANENT_FIELD_LABOR_HOURS)*PERMANENT_HOURLY_RATE+MAX(0,B40-PERMANENT_FIELD_LABOR_HOURS)*TEMP_HOURLY_RATE -> 2187.7865 | T40: =S40-S39 -> 1120.5736 | U40: =T40+I40 -> 1560.5736 | V40: =IF(L40>=U40,1,0) -> 1
A41: =ROW()-ROW($A$38) -> 3 | B41: =A41*CARROT_HRS_PER_WEEK_PER_BED*SEASON_WEEKS*(1+CARROT_DIM_RTRN_PCT)^A41 -> 96.881388 | C41: =B41*PERMANENT_HOURLY_RATE -> 3363.7218 | D41: =B41*TEMP_HOURLY_RATE -> 1681.8609 | E41: =A41*CARROT_FERTILIZER_PER_BED -> 1320 | F41: =B41-B40 -> 33.869103 | G41: =C41-C40 -> 1175.9353 | H41: =D41-D40 -> 587.96763 | I41: =E41-E40 -> 440 | J41: =G41+I41 -> 1615.9353 | K41: =H41+I41 -> 1027.9676 | L41: =CARROT_REVENUE_PER_BED -> 2094 | M41: =IF(L41>=J41,1,0) -> 1 | N41: =IF(L41>=K41,1,0) -> 1 | O41: =B41*CARROT_MC_RATE -> 3363.7218 | P41: =O41-O40 -> 1175.9353 | Q41: =P41+I41 -> 1615.9353 | R41: =IF(L41>=Q41,1,0) -> 1 | S41: =MIN(B41,PERMANENT_FIELD_LABOR_HOURS)*PERMANENT_HOURLY_RATE+MAX(0,B41-PERMANENT_FIELD_LABOR_HOURS)*TEMP_HOURLY_RATE -> 3363.7218 | T41: =S41-S40 -> 1175.9353 | U41: =T41+I41 -> 1615.9353 | V41: =IF(L41>=U41,1,0) -> 1
A42: =ROW()-ROW($A$38) -> 4 | B42: =A42*CARROT_HRS_PER_WEEK_PER_BED*SEASON_WEEKS*(1+CARROT_DIM_RTRN_PCT)^A42 -> 132.40456 | C42: =B42*PERMANENT_HOURLY_RATE -> 4597.0865 | D42: =B42*TEMP_HOURLY_RATE -> 2298.5432 | E42: =A42*CARROT_FERTILIZER_PER_BED -> 1760 | F42: =B42-B41 -> 35.523176 | G42: =C42-C41 -> 1233.3647 | H42: =D42-D41 -> 616.68233 | I42: =E42-E41 -> 440 | J42: =G42+I42 -> 1673.3647 | K42: =H42+I42 -> 1056.6823 | L42: =CARROT_REVENUE_PER_BED -> 2094 | M42: =IF(L42>=J42,1,0) -> 1 | N42: =IF(L42>=K42,1,0) -> 1 | O42: =B42*CARROT_MC_RATE -> 4597.0865 | P42: =O42-O41 -> 1233.3647 | Q42: =P42+I42 -> 1673.3647 | R42: =IF(L42>=Q42,1,0) -> 1 | S42: =MIN(B42,PERMANENT_FIELD_LABOR_HOURS)*PERMANENT_HOURLY_RATE+MAX(0,B42-PERMANENT_FIELD_LABOR_HOURS)*TEMP_HOURLY_RATE -> 4597.0865 | T42: =S42-S41 -> 1233.3647 | U42: =T42+I42 -> 1673.3647 | V42: =IF(L42>=U42,1,0) -> 1
A43: =ROW()-ROW($A$38) -> 5 | B43: =A43*CARROT_HRS_PER_WEEK_PER_BED*SEASON_WEEKS*(1+CARROT_DIM_RTRN_PCT)^A43 -> 169.64335 | C43: =B43*PERMANENT_HOURLY_RATE -> 5890.017 | D43: =B43*TEMP_HOURLY_RATE -> 2945.0085 | E43: =A43*CARROT_FERTILIZER_PER_BED -> 2200 | F43: =B43-B42 -> 37.238784 | G43: =C43-C42 -> 1292.9306 | H43: =D43-D42 -> 646.46528 | I43: =E43-E42 -> 440 | J43: =G43+I43 -> 1732.9306 | K43: =H43+I43 -> 1086.4653 | L43: =CARROT_REVENUE_PER_BED -> 2094 | M43: =IF(L43>=J43,1,0) -> 1 | N43: =IF(L43>=K43,1,0) -> 1 | O43: =B43*CARROT_MC_RATE -> 5890.017 | P43: =O43-O42 -> 1292.9306 | Q43: =P43+I43 -> 1732.9306 | R43: =IF(L43>=Q43,1,0) -> 1 | S43: =MIN(B43,PERMANENT_FIELD_LABOR_HOURS)*PERMANENT_HOURLY_RATE+MAX(0,B43-PERMANENT_FIELD_LABOR_HOURS)*TEMP_HOURLY_RATE -> 5890.017 | T43: =S43-S42 -> 1292.9306 | U43: =T43+I43 -> 1732.9306 | V43: =IF(L43>=U43,1,0) -> 1
A44: =ROW()-ROW($A$38) -> 6 | B44: =A44*CARROT_HRS_PER_WEEK_PER_BED*SEASON_WEEKS*(1+CARROT_DIM_RTRN_PCT)^A44 -> 208.66132 | C44: =B44*PERMANENT_HOURLY_RATE -> 7244.7209 | D44: =B44*TEMP_HOURLY_RATE -> 3622.3605 | E44: =A44*CARROT_FERTILIZER_PER_BED -> 2640 | F44: =B44-B43 -> 39.01797 | G44: =C44-C43 -> 1354.7039 | H44: =D44-D43 -> 677.35196 | I44: =E44-E43 -> 440 | J44: =G44+I44 -> 1794.7039 | K44: =H44+I44 -> 1117.352 | L44: =CARROT_REVENUE_PER_BED -> 2094 | M44: =IF(L44>=J44,1,0) -> 1 | N44: =IF(L44>=K44,1,0) -> 1 | O44: =B44*CARROT_MC_RATE -> 7244.7209 | P44: =O44-O43 -> 1354.7039 | Q44: =P44+I44 -> 1794.7039 | R44: =IF(L44>=Q44,1,0) -> 1 | S44: =MIN(B44,PERMANENT_FIELD_LABOR_HOURS)*PERMANENT_HOURLY_RATE+MAX(0,B44-PERMANENT_FIELD_LABOR_HOURS)*TEMP_HOURLY_RATE -> 7244.7209 | T44: =S44-S43 -> 1354.7039 | U44: =T44+I44 -> 1794.7039 | V44: =IF(L44>=U44,1,0) -> 1
A45: =ROW()-ROW($A$38) -> 7 | B45: =A45*CARROT_HRS_PER_WEEK_PER_BED*SEASON_WEEKS*(1+CARROT_DIM_RTRN_PCT)^A45 -> 249.52416 | C45: =B45*PERMANENT_HOURLY_RATE -> 8663.4788 | D45: =B45*TEMP_HOURLY_RATE -> 4331.7394 | E45: =A45*CARROT_FERTILIZER_PER_BED -> 3080 | F45: =B45-B44 -> 40.862841 | G45: =C45-C44 -> 1418.7579 | H45: =D45-D44 -> 709.37893 | I45: =E45-E44 -> 440 | J45: =G45+I45 -> 1858.7579 | K45: =H45+I45 -> 1149.3789 | L45: =CARROT_REVENUE_PER_BED -> 2094 | M45: =IF(L45>=J45,1,0) -> 1 | N45: =IF(L45>=K45,1,0) -> 1 | O45: =B45*CARROT_MC_RATE -> 8663.4788 | P45: =O45-O44 -> 1418.7579 | Q45: =P45+I45 -> 1858.7579 | R45: =IF(L45>=Q45,1,0) -> 1 | S45: =MIN(B45,PERMANENT_FIELD_LABOR_HOURS)*PERMANENT_HOURLY_RATE+MAX(0,B45-PERMANENT_FIELD_LABOR_HOURS)*TEMP_HOURLY_RATE -> 8663.4788 | T45: =S45-S44 -> 1418.7579 | U45: =T45+I45 -> 1858.7579 | V45: =IF(L45>=U45,1,0) -> 1
A46: =ROW()-ROW($A$38) -> 8 | B46: =A46*CARROT_HRS_PER_WEEK_PER_BED*SEASON_WEEKS*(1+CARROT_DIM_RTRN_PCT)^A46 -> 292.29973 | C46: =B46*PERMANENT_HOURLY_RATE -> 10148.647 | D46: =B46*TEMP_HOURLY_RATE -> 5074.3233 | E46: =A46*CARROT_FERTILIZER_PER_BED -> 3520 | F46: =B46-B45 -> 42.77557 | G46: =C46-C45 -> 1485.1678 | H46: =D46-D45 -> 742.5839 | I46: =E46-E45 -> 440 | J46: =G46+I46 -> 1925.1678 | K46: =H46+I46 -> 1182.5839 | L46: =CARROT_REVENUE_PER_BED -> 2094 | M46: =IF(L46>=J46,1,0) -> 1 | N46: =IF(L46>=K46,1,0) -> 1 | O46: =B46*CARROT_MC_RATE -> 10148.647 | P46: =O46-O45 -> 1485.1678 | Q46: =P46+I46 -> 1925.1678 | R46: =IF(L46>=Q46,1,0) -> 1 | S46: =MIN(B46,PERMANENT_FIELD_LABOR_HOURS)*PERMANENT_HOURLY_RATE+MAX(0,B46-PERMANENT_FIELD_LABOR_HOURS)*TEMP_HOURLY_RATE -> 10148.647 | T46: =S46-S45 -> 1485.1678 | U46: =T46+I46 -> 1925.1678 | V46: =IF(L46>=U46,1,0) -> 1
A47: =ROW()-ROW($A$38) -> 9 | B47: =A47*CARROT_HRS_PER_WEEK_PER_BED*SEASON_WEEKS*(1+CARROT_DIM_RTRN_PCT)^A47 -> 337.05812 | C47: =B47*PERMANENT_HOURLY_RATE -> 11702.658 | D47: =B47*TEMP_HOURLY_RATE -> 5851.329 | E47: =A47*CARROT_FERTILIZER_PER_BED -> 3960 | F47: =B47-B46 -> 44.758396 | G47: =C47-C46 -> 1554.0115 | H47: =D47-D46 -> 777.00575 | I47: =E47-E46 -> 440 | J47: =G47+I47 -> 1994.0115 | K47: =H47+I47 -> 1217.0058 | L47: =CARROT_REVENUE_PER_BED -> 2094 | M47: =IF(L47>=J47,1,0) -> 1 | N47: =IF(L47>=K47,1,0) -> 1 | O47: =B47*CARROT_MC_RATE -> 11702.658 | P47: =O47-O46 -> 1554.0115 | Q47: =P47+I47 -> 1994.0115 | R47: =IF(L47>=Q47,1,0) -> 1 | S47: =MIN(B47,PERMANENT_FIELD_LABOR_HOURS)*PERMANENT_HOURLY_RATE+MAX(0,B47-PERMANENT_FIELD_LABOR_HOURS)*TEMP_HOURLY_RATE -> 11702.658 | T47: =S47-S46 -> 1554.0115 | U47: =T47+I47 -> 1994.0115 | V47: =IF(L47>=U47,1,0) -> 1
A48: =ROW()-ROW($A$38) -> 10 | B48: =A48*CARROT_HRS_PER_WEEK_PER_BED*SEASON_WEEKS*(1+CARROT_DIM_RTRN_PCT)^A48 -> 383.87175 | C48: =B48*PERMANENT_HOURLY_RATE -> 13328.027 | D48: =B48*TEMP_HOURLY_RATE -> 6664.0136 | E48: =A48*CARROT_FERTILIZER_PER_BED -> 4400 | F48: =B48-B47 -> 46.813628 | G48: =C48-C47 -> 1625.3692 | H48: =D48-D47 -> 812.68459 | I48: =E48-E47 -> 440 | J48: =G48+I48 -> 2065.3692 | K48: =H48+I48 -> 1252.6846 | L48: =CARROT_REVENUE_PER_BED -> 2094 | M48: =IF(L48>=J48,1,0) -> 1 | N48: =IF(L48>=K48,1,0) -> 1 | O48: =B48*CARROT_MC_RATE -> 13328.027 | P48: =O48-O47 -> 1625.3692 | Q48: =P48+I48 -> 2065.3692 | R48: =IF(L48>=Q48,1,0) -> 1 | S48: =MIN(B48,PERMANENT_FIELD_LABOR_HOURS)*PERMANENT_HOURLY_RATE+MAX(0,B48-PERMANENT_FIELD_LABOR_HOURS)*TEMP_HOURLY_RATE -> 13328.027 | T48: =S48-S47 -> 1625.3692 | U48: =T48+I48 -> 2065.3692 | V48: =IF(L48>=U48,1,0) -> 1
A49: =ROW()-ROW($A$38) -> 11 | B49: =A49*CARROT_HRS_PER_WEEK_PER_BED*SEASON_WEEKS*(1+CARROT_DIM_RTRN_PCT)^A49 -> 432.8154 | C49: =B49*PERMANENT_HOURLY_RATE -> 15027.351 | D49: =B49*TEMP_HOURLY_RATE -> 7513.6754 | E49: =A49*CARROT_FERTILIZER_PER_BED -> 4840 | F49: =B49-B48 -> 48.943649 | G49: =C49-C48 -> 1699.3235 | H49: =D49-D48 -> 849.66174 | I49: =E49-E48 -> 440 | J49: =G49+I49 -> 2139.3235 | K49: =H49+I49 -> 1289.6617 | L49: =CARROT_REVENUE_PER_BED -> 2094 | M49: =IF(L49>=J49,1,0) -> 0 | N49: =IF(L49>=K49,1,0) -> 1 | O49: =B49*CARROT_MC_RATE -> 15027.351 | P49: =O49-O48 -> 1699.3235 | Q49: =P49+I49 -> 2139.3235 | R49: =IF(L49>=Q49,1,0) -> 0 | S49: =MIN(B49,PERMANENT_FIELD_LABOR_HOURS)*PERMANENT_HOURLY_RATE+MAX(0,B49-PERMANENT_FIELD_LABOR_HOURS)*TEMP_HOURLY_RATE -> 15027.351 | T49: =S49-S48 -> 1699.3235 | U49: =T49+I49 -> 2139.3235 | V49: =IF(L49>=U49,1,0) -> 0
A50: =ROW()-ROW($A$38) -> 12 | B50: =A50*CARROT_HRS_PER_WEEK_PER_BED*SEASON_WEEKS*(1+CARROT_DIM_RTRN_PCT)^A50 -> 483.96631 | C50: =B50*PERMANENT_HOURLY_RATE -> 16803.31 | D50: =B50*TEMP_HOURLY_RATE -> 8401.6552 | E50: =A50*CARROT_FERTILIZER_PER_BED -> 5280 | F50: =B50-B49 -> 51.150911 | G50: =C50-C49 -> 1775.9596 | H50: =D50-D49 -> 887.97982 | I50: =E50-E49 -> 440 | J50: =G50+I50 -> 2215.9596 | K50: =H50+I50 -> 1327.9798 | L50: =CARROT_REVENUE_PER_BED -> 2094 | M50: =IF(L50>=J50,1,0) -> 0 | N50: =IF(L50>=K50,1,0) -> 1 | O50: =B50*CARROT_MC_RATE -> 16803.31 | P50: =O50-O49 -> 1775.9596 | Q50: =P50+I50 -> 2215.9596 | R50: =IF(L50>=Q50,1,0) -> 0 | S50: =MIN(B50,PERMANENT_FIELD_LABOR_HOURS)*PERMANENT_HOURLY_RATE+MAX(0,B50-PERMANENT_FIELD_LABOR_HOURS)*TEMP_HOURLY_RATE -> 16803.31 | T50: =S50-S49 -> 1775.9596 | U50: =T50+I50 -> 2215.9596 | V50: =IF(L50>=U50,1,0) -> 0
... A58: =ROW()-ROW($A$38) -> 20 | B58: =A58*CARROT_HRS_PER_WEEK_PER_BED*SEASON_WEEKS*(1+CARROT_DIM_RTRN_PCT)^A58 -> 982.7766 | C58: =B58*PERMANENT_HOURLY_RATE -> 34122.003 | D58: =B58*TEMP_HOURLY_RATE -> 17061.002 | E58: =A58*CARROT_FERTILIZER_PER_BED -> 8800 | F58: =B58-B57 -> 71.910483 | G58: =C58-C57 -> 2496.732 | H58: =D58-D57 -> 1248.366 | I58: =E58-E57 -> 440 | J58: =G58+I58 -> 2936.732 | K58: =H58+I58 -> 1688.366 | L58: =CARROT_REVENUE_PER_BED -> 2094 | M58: =IF(L58>=J58,1,0) -> 0 | N58: =IF(L58>=K58,1,0) -> 1 | O58: =B58*CARROT_MC_RATE -> 34122.003 | P58: =O58-O57 -> 2496.732 | Q58: =P58+I58 -> 2936.732 | R58: =IF(L58>=Q58,1,0) -> 0 | S58: =MIN(B58,PERMANENT_FIELD_LABOR_HOURS)*PERMANENT_HOURLY_RATE+MAX(0,B58-PERMANENT_FIELD_LABOR_HOURS)*TEMP_HOURLY_RATE -> 29560.202 | T58: =S58-S57 -> 1248.366 | U58: =T58+I58 -> 1688.366 | V58: =IF(L58>=U58,1,0) -> 1
A61: Mesclun schedule | C61: LABOR_HOURS(q) = q × MESCLUN_HRS_PER_WEEK_PER_BED × SEASON_WEEKS × (1 + MESCLUN_DIM_RTRN_PCT)^q
A62: q (beds) | B62: Labor hours | C62: Labor $ @ permanent rate | D62: Labor $ @ temp rate | E62: Fertilizer $ | F62: Marginal labor hours | G62: Marginal labor $ @ permanent | H62: Marginal labor $ @ temp | I62: Marginal fertilizer $ | J62: Marginal total cost @ permanent | K62: Marginal total cost @ temp | L62: Price P (revenue/bed) | M62: P ≥ MC @ permanent (1/0) | N62: P ≥ MC @ temp (1/0) | O62: Labor $ @ MC_RATE | P62: Marginal labor $ @ MC_RATE | Q62: Marginal total cost @ MC_RATE (spec) | R62: P ≥ MC @ MC_RATE (1/0) | S62: Labor $, permanent hours first (info) | T62: Marginal labor $, permanent hours first | U62: Marginal total cost, permanent hours first | V62: P ≥ MC, permanent hours first (1/0)
A63: =ROW()-ROW($A$63) -> 0 | B63: =A63*MESCLUN_HRS_PER_WEEK_PER_BED*SEASON_WEEKS*(1+MESCLUN_DIM_RTRN_PCT)^A63 -> 0 | C63: =B63*PERMANENT_HOURLY_RATE -> 0 | D63: =B63*TEMP_HOURLY_RATE -> 0 | E63: =A63*MESCLUN_FERTILIZER_PER_BED -> 0 | F63: — | G63: — | H63: — | I63: — | J63: — | K63: — | L63: =MESCLUN_REVENUE_PER_BED -> 2700 | M63: — | N63: — | O63: =B63*MESCLUN_MC_RATE -> 0 | P63: — | Q63: — | R63: — | S63: =MIN(B63,PERMANENT_FIELD_LABOR_HOURS)*PERMANENT_HOURLY_RATE+MAX(0,B63-PERMANENT_FIELD_LABOR_HOURS)*TEMP_HOURLY_RATE -> 0 | T63: — | U63: — | V63: —
A64: =ROW()-ROW($A$63) -> 1 | B64: =A64*MESCLUN_HRS_PER_WEEK_PER_BED*SEASON_WEEKS*(1+MESCLUN_DIM_RTRN_PCT)^A64 -> 45.5625 | C64: =B64*PERMANENT_HOURLY_RATE -> 1581.93 | D64: =B64*TEMP_HOURLY_RATE -> 790.965 | E64: =A64*MESCLUN_FERTILIZER_PER_BED -> 880 | F64: =B64-B63 -> 45.5625 | G64: =C64-C63 -> 1581.93 | H64: =D64-D63 -> 790.965 | I64: =E64-E63 -> 880 | J64: =G64+I64 -> 2461.93 | K64: =H64+I64 -> 1670.965 | L64: =MESCLUN_REVENUE_PER_BED -> 2700 | M64: =IF(L64>=J64,1,0) -> 1 | N64: =IF(L64>=K64,1,0) -> 1 | O64: =B64*MESCLUN_MC_RATE -> 1581.93 | P64: =O64-O63 -> 1581.93 | Q64: =P64+I64 -> 2461.93 | R64: =IF(L64>=Q64,1,0) -> 1 | S64: =MIN(B64,PERMANENT_FIELD_LABOR_HOURS)*PERMANENT_HOURLY_RATE+MAX(0,B64-PERMANENT_FIELD_LABOR_HOURS)*TEMP_HOURLY_RATE -> 1581.93 | T64: =S64-S63 -> 1581.93 | U64: =T64+I64 -> 2461.93 | V64: =IF(L64>=U64,1,0) -> 1
A65: =ROW()-ROW($A$63) -> 2 | B65: =A65*MESCLUN_HRS_PER_WEEK_PER_BED*SEASON_WEEKS*(1+MESCLUN_DIM_RTRN_PCT)^A65 -> 92.264062 | C65: =B65*PERMANENT_HOURLY_RATE -> 3203.4082 | D65: =B65*TEMP_HOURLY_RATE -> 1601.7041 | E65: =A65*MESCLUN_FERTILIZER_PER_BED -> 1760 | F65: =B65-B64 -> 46.701563 | G65: =C65-C64 -> 1621.4782 | H65: =D65-D64 -> 810.73912 | I65: =E65-E64 -> 880 | J65: =G65+I65 -> 2501.4783 | K65: =H65+I65 -> 1690.7391 | L65: =MESCLUN_REVENUE_PER_BED -> 2700 | M65: =IF(L65>=J65,1,0) -> 1 | N65: =IF(L65>=K65,1,0) -> 1 | O65: =B65*MESCLUN_MC_RATE -> 3203.4082 | P65: =O65-O64 -> 1621.4782 | Q65: =P65+I65 -> 2501.4783 | R65: =IF(L65>=Q65,1,0) -> 1 | S65: =MIN(B65,PERMANENT_FIELD_LABOR_HOURS)*PERMANENT_HOURLY_RATE+MAX(0,B65-PERMANENT_FIELD_LABOR_HOURS)*TEMP_HOURLY_RATE -> 3203.4082 | T65: =S65-S64 -> 1621.4782 | U65: =T65+I65 -> 2501.4783 | V65: =IF(L65>=U65,1,0) -> 1
A66: =ROW()-ROW($A$63) -> 3 | B66: =A66*MESCLUN_HRS_PER_WEEK_PER_BED*SEASON_WEEKS*(1+MESCLUN_DIM_RTRN_PCT)^A66 -> 140.12604 | C66: =B66*PERMANENT_HOURLY_RATE -> 4865.1763 | D66: =B66*TEMP_HOURLY_RATE -> 2432.5881 | E66: =A66*MESCLUN_FERTILIZER_PER_BED -> 2640 | F66: =B66-B65 -> 47.861982 | G66: =C66-C65 -> 1661.768 | H66: =D66-D65 -> 830.88401 | I66: =E66-E65 -> 880 | J66: =G66+I66 -> 2541.768 | K66: =H66+I66 -> 1710.884 | L66: =MESCLUN_REVENUE_PER_BED -> 2700 | M66: =IF(L66>=J66,1,0) -> 1 | N66: =IF(L66>=K66,1,0) -> 1 | O66: =B66*MESCLUN_MC_RATE -> 4865.1763 | P66: =O66-O65 -> 1661.768 | Q66: =P66+I66 -> 2541.768 | R66: =IF(L66>=Q66,1,0) -> 1 | S66: =MIN(B66,PERMANENT_FIELD_LABOR_HOURS)*PERMANENT_HOURLY_RATE+MAX(0,B66-PERMANENT_FIELD_LABOR_HOURS)*TEMP_HOURLY_RATE -> 4865.1763 | T66: =S66-S65 -> 1661.768 | U66: =T66+I66 -> 2541.768 | V66: =IF(L66>=U66,1,0) -> 1
A67: =ROW()-ROW($A$63) -> 4 | B67: =A67*MESCLUN_HRS_PER_WEEK_PER_BED*SEASON_WEEKS*(1+MESCLUN_DIM_RTRN_PCT)^A67 -> 189.17016 | C67: =B67*PERMANENT_HOURLY_RATE -> 6567.988 | D67: =B67*TEMP_HOURLY_RATE -> 3283.994 | E67: =A67*MESCLUN_FERTILIZER_PER_BED -> 3520 | F67: =B67-B66 -> 49.044116 | G67: =C67-C66 -> 1702.8117 | H67: =D67-D66 -> 851.40585 | I67: =E67-E66 -> 880 | J67: =G67+I67 -> 2582.8117 | K67: =H67+I67 -> 1731.4058 | L67: =MESCLUN_REVENUE_PER_BED -> 2700 | M67: =IF(L67>=J67,1,0) -> 1 | N67: =IF(L67>=K67,1,0) -> 1 | O67: =B67*MESCLUN_MC_RATE -> 6567.988 | P67: =O67-O66 -> 1702.8117 | Q67: =P67+I67 -> 2582.8117 | R67: =IF(L67>=Q67,1,0) -> 1 | S67: =MIN(B67,PERMANENT_FIELD_LABOR_HOURS)*PERMANENT_HOURLY_RATE+MAX(0,B67-PERMANENT_FIELD_LABOR_HOURS)*TEMP_HOURLY_RATE -> 6567.988 | T67: =S67-S66 -> 1702.8117 | U67: =T67+I67 -> 2582.8117 | V67: =IF(L67>=U67,1,0) -> 1
A68: =ROW()-ROW($A$63) -> 5 | B68: =A68*MESCLUN_HRS_PER_WEEK_PER_BED*SEASON_WEEKS*(1+MESCLUN_DIM_RTRN_PCT)^A68 -> 239.41848 | C68: =B68*PERMANENT_HOURLY_RATE -> 8312.6098 | D68: =B68*TEMP_HOURLY_RATE -> 4156.3049 | E68: =A68*MESCLUN_FERTILIZER_PER_BED -> 4400 | F68: =B68-B67 -> 50.248324 | G68: =C68-C67 -> 1744.6218 | H68: =D68-D67 -> 872.3109 | I68: =E68-E67 -> 880 | J68: =G68+I68 -> 2624.6218 | K68: =H68+I68 -> 1752.3109 | L68: =MESCLUN_REVENUE_PER_BED -> 2700 | M68: =IF(L68>=J68,1,0) -> 1 | N68: =IF(L68>=K68,1,0) -> 1 | O68: =B68*MESCLUN_MC_RATE -> 8312.6098 | P68: =O68-O67 -> 1744.6218 | Q68: =P68+I68 -> 2624.6218 | R68: =IF(L68>=Q68,1,0) -> 1 | S68: =MIN(B68,PERMANENT_FIELD_LABOR_HOURS)*PERMANENT_HOURLY_RATE+MAX(0,B68-PERMANENT_FIELD_LABOR_HOURS)*TEMP_HOURLY_RATE -> 8312.6098 | T68: =S68-S67 -> 1744.6218 | U68: =T68+I68 -> 2624.6218 | V68: =IF(L68>=U68,1,0) -> 1
A69: =ROW()-ROW($A$63) -> 6 | B69: =A69*MESCLUN_HRS_PER_WEEK_PER_BED*SEASON_WEEKS*(1+MESCLUN_DIM_RTRN_PCT)^A69 -> 290.89346 | C69: =B69*PERMANENT_HOURLY_RATE -> 10099.821 | D69: =B69*TEMP_HOURLY_RATE -> 5049.9104 | E69: =A69*MESCLUN_FERTILIZER_PER_BED -> 5280 | F69: =B69-B68 -> 51.474974 | G69: =C69-C68 -> 1787.2111 | H69: =D69-D68 -> 893.60555 | I69: =E69-E68 -> 880 | J69: =G69+I69 -> 2667.2111 | K69: =H69+I69 -> 1773.6056 | L69: =MESCLUN_REVENUE_PER_BED -> 2700 | M69: =IF(L69>=J69,1,0) -> 1 | N69: =IF(L69>=K69,1,0) -> 1 | O69: =B69*MESCLUN_MC_RATE -> 10099.821 | P69: =O69-O68 -> 1787.2111 | Q69: =P69+I69 -> 2667.2111 | R69: =IF(L69>=Q69,1,0) -> 1 | S69: =MIN(B69,PERMANENT_FIELD_LABOR_HOURS)*PERMANENT_HOURLY_RATE+MAX(0,B69-PERMANENT_FIELD_LABOR_HOURS)*TEMP_HOURLY_RATE -> 10099.821 | T69: =S69-S68 -> 1787.2111 | U69: =T69+I69 -> 2667.2111 | V69: =IF(L69>=U69,1,0) -> 1
A70: =ROW()-ROW($A$63) -> 7 | B70: =A70*MESCLUN_HRS_PER_WEEK_PER_BED*SEASON_WEEKS*(1+MESCLUN_DIM_RTRN_PCT)^A70 -> 343.6179 | C70: =B70*PERMANENT_HOURLY_RATE -> 11930.413 | D70: =B70*TEMP_HOURLY_RATE -> 5965.2067 | E70: =A70*MESCLUN_FERTILIZER_PER_BED -> 6160 | F70: =B70-B69 -> 52.724439 | G70: =C70-C69 -> 1830.5925 | H70: =D70-D69 -> 915.29627 | I70: =E70-E69 -> 880 | J70: =G70+I70 -> 2710.5925 | K70: =H70+I70 -> 1795.2963 | L70: =MESCLUN_REVENUE_PER_BED -> 2700 | M70: =IF(L70>=J70,1,0) -> 0 | N70: =IF(L70>=K70,1,0) -> 1 | O70: =B70*MESCLUN_MC_RATE -> 11930.413 | P70: =O70-O69 -> 1830.5925 | Q70: =P70+I70 -> 2710.5925 | R70: =IF(L70>=Q70,1,0) -> 0 | S70: =MIN(B70,PERMANENT_FIELD_LABOR_HOURS)*PERMANENT_HOURLY_RATE+MAX(0,B70-PERMANENT_FIELD_LABOR_HOURS)*TEMP_HOURLY_RATE -> 11930.413 | T70: =S70-S69 -> 1830.5925 | U70: =T70+I70 -> 2710.5925 | V70: =IF(L70>=U70,1,0) -> 0
A71: =ROW()-ROW($A$63) -> 8 | B71: =A71*MESCLUN_HRS_PER_WEEK_PER_BED*SEASON_WEEKS*(1+MESCLUN_DIM_RTRN_PCT)^A71 -> 397.615 | C71: =B71*PERMANENT_HOURLY_RATE -> 13805.193 | D71: =B71*TEMP_HOURLY_RATE -> 6902.5963 | E71: =A71*MESCLUN_FERTILIZER_PER_BED -> 7040 | F71: =B71-B70 -> 53.997098 | G71: =C71-C70 -> 1874.7793 | H71: =D71-D70 -> 937.38963 | I71: =E71-E70 -> 880 | J71: =G71+I71 -> 2754.7793 | K71: =H71+I71 -> 1817.3896 | L71: =MESCLUN_REVENUE_PER_BED -> 2700 | M71: =IF(L71>=J71,1,0) -> 0 | N71: =IF(L71>=K71,1,0) -> 1 | O71: =B71*MESCLUN_MC_RATE -> 13805.193 | P71: =O71-O70 -> 1874.7793 | Q71: =P71+I71 -> 2754.7793 | R71: =IF(L71>=Q71,1,0) -> 0 | S71: =MIN(B71,PERMANENT_FIELD_LABOR_HOURS)*PERMANENT_HOURLY_RATE+MAX(0,B71-PERMANENT_FIELD_LABOR_HOURS)*TEMP_HOURLY_RATE -> 13805.193 | T71: =S71-S70 -> 1874.7793 | U71: =T71+I71 -> 2754.7793 | V71: =IF(L71>=U71,1,0) -> 0
A72: =ROW()-ROW($A$63) -> 9 | B72: =A72*MESCLUN_HRS_PER_WEEK_PER_BED*SEASON_WEEKS*(1+MESCLUN_DIM_RTRN_PCT)^A72 -> 452.90833 | C72: =B72*PERMANENT_HOURLY_RATE -> 15724.977 | D72: =B72*TEMP_HOURLY_RATE -> 7862.4886 | E72: =A72*MESCLUN_FERTILIZER_PER_BED -> 7920 | F72: =B72-B71 -> 55.293335 | G72: =C72-C71 -> 1919.7846 | H72: =D72-D71 -> 959.8923 | I72: =E72-E71 -> 880 | J72: =G72+I72 -> 2799.7846 | K72: =H72+I72 -> 1839.8923 | L72: =MESCLUN_REVENUE_PER_BED -> 2700 | M72: =IF(L72>=J72,1,0) -> 0 | N72: =IF(L72>=K72,1,0) -> 1 | O72: =B72*MESCLUN_MC_RATE -> 15724.977 | P72: =O72-O71 -> 1919.7846 | Q72: =P72+I72 -> 2799.7846 | R72: =IF(L72>=Q72,1,0) -> 0 | S72: =MIN(B72,PERMANENT_FIELD_LABOR_HOURS)*PERMANENT_HOURLY_RATE+MAX(0,B72-PERMANENT_FIELD_LABOR_HOURS)*TEMP_HOURLY_RATE -> 15724.977 | T72: =S72-S71 -> 1919.7846 | U72: =T72+I72 -> 2799.7846 | V72: =IF(L72>=U72,1,0) -> 0
A73: =ROW()-ROW($A$63) -> 10 | B73: =A73*MESCLUN_HRS_PER_WEEK_PER_BED*SEASON_WEEKS*(1+MESCLUN_DIM_RTRN_PCT)^A73 -> 509.52187 | C73: =B73*PERMANENT_HOURLY_RATE -> 17690.599 | D73: =B73*TEMP_HOURLY_RATE -> 8845.2997 | E73: =A73*MESCLUN_FERTILIZER_PER_BED -> 8800 | F73: =B73-B72 -> 56.613541 | G73: =C73-C72 -> 1965.6222 | H73: =D73-D72 -> 982.81108 | I73: =E73-E72 -> 880 | J73: =G73+I73 -> 2845.6222 | K73: =H73+I73 -> 1862.8111 | L73: =MESCLUN_REVENUE_PER_BED -> 2700 | M73: =IF(L73>=J73,1,0) -> 0 | N73: =IF(L73>=K73,1,0) -> 1 | O73: =B73*MESCLUN_MC_RATE -> 17690.599 | P73: =O73-O72 -> 1965.6222 | Q73: =P73+I73 -> 2845.6222 | R73: =IF(L73>=Q73,1,0) -> 0 | S73: =MIN(B73,PERMANENT_FIELD_LABOR_HOURS)*PERMANENT_HOURLY_RATE+MAX(0,B73-PERMANENT_FIELD_LABOR_HOURS)*TEMP_HOURLY_RATE -> 17690.599 | T73: =S73-S72 -> 1965.6222 | U73: =T73+I73 -> 2845.6222 | V73: =IF(L73>=U73,1,0) -> 0
A74: =ROW()-ROW($A$63) -> 11 | B74: =A74*MESCLUN_HRS_PER_WEEK_PER_BED*SEASON_WEEKS*(1+MESCLUN_DIM_RTRN_PCT)^A74 -> 567.47999 | C74: =B74*PERMANENT_HOURLY_RATE -> 19702.905 | D74: =B74*TEMP_HOURLY_RATE -> 9851.4526 | E74: =A74*MESCLUN_FERTILIZER_PER_BED -> 9680 | F74: =B74-B73 -> 57.958113 | G74: =C74-C73 -> 2012.3057 | H74: =D74-D73 -> 1006.1528 | I74: =E74-E73 -> 880 | J74: =G74+I74 -> 2892.3057 | K74: =H74+I74 -> 1886.1528 | L74: =MESCLUN_REVENUE_PER_BED -> 2700 | M74: =IF(L74>=J74,1,0) -> 0 | N74: =IF(L74>=K74,1,0) -> 1 | O74: =B74*MESCLUN_MC_RATE -> 19702.905 | P74: =O74-O73 -> 2012.3057 | Q74: =P74+I74 -> 2892.3057 | R74: =IF(L74>=Q74,1,0) -> 0 | S74: =MIN(B74,PERMANENT_FIELD_LABOR_HOURS)*PERMANENT_HOURLY_RATE+MAX(0,B74-PERMANENT_FIELD_LABOR_HOURS)*TEMP_HOURLY_RATE -> 19702.905 | T74: =S74-S73 -> 2012.3057 | U74: =T74+I74 -> 2892.3057 | V74: =IF(L74>=U74,1,0) -> 0
A75: =ROW()-ROW($A$63) -> 12 | B75: =A75*MESCLUN_HRS_PER_WEEK_PER_BED*SEASON_WEEKS*(1+MESCLUN_DIM_RTRN_PCT)^A75 -> 626.80744 | C75: =B75*PERMANENT_HOURLY_RATE -> 21762.754 | D75: =B75*TEMP_HOURLY_RATE -> 10881.377 | E75: =A75*MESCLUN_FERTILIZER_PER_BED -> 10560 | F75: =B75-B74 -> 59.327453 | G75: =C75-C74 -> 2059.8492 | H75: =D75-D74 -> 1029.9246 | I75: =E75-E74 -> 880 | J75: =G75+I75 -> 2939.8492 | K75: =H75+I75 -> 1909.9246 | L75: =MESCLUN_REVENUE_PER_BED -> 2700 | M75: =IF(L75>=J75,1,0) -> 0 | N75: =IF(L75>=K75,1,0) -> 1 | O75: =B75*MESCLUN_MC_RATE -> 21762.754 | P75: =O75-O74 -> 2059.8492 | Q75: =P75+I75 -> 2939.8492 | R75: =IF(L75>=Q75,1,0) -> 0 | S75: =MIN(B75,PERMANENT_FIELD_LABOR_HOURS)*PERMANENT_HOURLY_RATE+MAX(0,B75-PERMANENT_FIELD_LABOR_HOURS)*TEMP_HOURLY_RATE -> 21762.754 | T75: =S75-S74 -> 2059.8492 | U75: =T75+I75 -> 2939.8492 | V75: =IF(L75>=U75,1,0) -> 0
... A93: =ROW()-ROW($A$63) -> 30 | B93: =A93*MESCLUN_HRS_PER_WEEK_PER_BED*SEASON_WEEKS*(1+MESCLUN_DIM_RTRN_PCT)^A93 -> 1959.678 | C93: =B93*PERMANENT_HOURLY_RATE -> 68040.021 | D93: =B93*TEMP_HOURLY_RATE -> 34020.011 | E93: =A93*MESCLUN_FERTILIZER_PER_BED -> 26400 | F93: =B93-B92 -> 88.709705 | G93: =C93-C92 -> 3080.001 | H93: =D93-D92 -> 1540.0005 | I93: =E93-E92 -> 880 | J93: =G93+I93 -> 3960.001 | K93: =H93+I93 -> 2420.0005 | L93: =MESCLUN_REVENUE_PER_BED -> 2700 | M93: =IF(L93>=J93,1,0) -> 0 | N93: =IF(L93>=K93,1,0) -> 1 | O93: =B93*MESCLUN_MC_RATE -> 68040.021 | P93: =O93-O92 -> 3080.001 | Q93: =P93+I93 -> 3960.001 | R93: =IF(L93>=Q93,1,0) -> 0 | S93: =MIN(B93,PERMANENT_FIELD_LABOR_HOURS)*PERMANENT_HOURLY_RATE+MAX(0,B93-PERMANENT_FIELD_LABOR_HOURS)*TEMP_HOURLY_RATE -> 46519.211 | T93: =S93-S92 -> 1540.0005 | U93: =T93+I93 -> 2420.0005 | V93: =IF(L93>=U93,1,0) -> 1

Sheet Optimization
A1: Optimization - decision cells, objective, constraints, Solver setup
A2: Orange cells are the Solver changing cells. Green cells are constraint checks. Gold cells are the recommendation.
A4: Decision cells (Solver changing cells: integer, non-negative)
A5: Crop | B5: Named range | C5: Beds | D5: Unit | E5: Note
A6: Tomato | B6: TOMATO_BEDS | C6: 10 | D6: beds | E6: Solver writes this value. Checks (V1 and O5) confirm it equals the exhaustive-enumeration optimum.
A7: Carrot | B7: CARROT_BEDS | C7: 20 | D7: beds | E7: Solver writes this value. Checks (V1 and O5) confirm it equals the exhaustive-enumeration optimum.
A8: Mesclun | B8: MESCLUN_BEDS | C8: 30 | D8: beds | E8: Solver writes this value. Checks (V1 and O5) confirm it equals the exhaustive-enumeration optimum.
A10: Objective (Solver: Set Objective, Max)
A11: Seasonal profit | B11: OBJECTIVE_SEASONAL_PROFIT | C11: =SEASONAL_PROFIT -> 42775.155 | D11: $ | E11: SEASONAL_PROFIT = TOTAL_REVENUE − TOTAL_FERTILIZER − TOTAL_LABOR_COST − FIXED_SEASON_COST (Cost Structure sheet)
A13: Constraints (green = constraint-check cells)
A14: Constraint | B14: Left-hand side | C14: Relation | D14: Right-hand side | E14: Slack | F14: Check | G14: Binding?
A15: TOMATO_BEDS ≤ TOMATO_BED_CAP | B15: =TOMATO_BEDS -> 10 | C15: ≤ | D15: =TOMATO_BED_CAP -> 20 | E15: =D15-B15 -> 10 | F15: =IF(B15<=D15+0.000000001,"OK","VIOLATED") -> OK | G15: =IF(ABS(E15)<0.000000001,"Binding","Not binding") -> Not binding
A16: CARROT_BEDS ≤ CARROT_BED_CAP | B16: =CARROT_BEDS -> 20 | C16: ≤ | D16: =CARROT_BED_CAP -> 20 | E16: =D16-B16 -> 0 | F16: =IF(B16<=D16+0.000000001,"OK","VIOLATED") -> OK | G16: =IF(ABS(E16)<0.000000001,"Binding","Not binding") -> Binding
A17: MESCLUN_BEDS ≤ MESCLUN_BED_CAP | B17: =MESCLUN_BEDS -> 30 | C17: ≤ | D17: =MESCLUN_BED_CAP -> 30 | E17: =D17-B17 -> 0 | F17: =IF(B17<=D17+0.000000001,"OK","VIOLATED") -> OK | G17: =IF(ABS(E17)<0.000000001,"Binding","Not binding") -> Binding
A18: TOTAL_BEDS_USED ≤ TOTAL_BEDS_AVAILABLE | B18: =TOTAL_BEDS_USED -> 60 | C18: ≤ | D18: =TOTAL_BEDS_AVAILABLE -> 64 | E18: =D18-B18 -> 4 | F18: =IF(B18<=D18+0.000000001,"OK","VIOLATED") -> OK | G18: =IF(ABS(E18)<0.000000001,"Binding","Not binding") -> Not binding
A19: TEMP_HOURS_USED ≤ TEMP_HOURS_CAP | B19: =TEMP_HOURS_USED -> 4556.8228 | C19: ≤ | D19: =TEMP_HOURS_CAP -> 5760 | E19: =D19-B19 -> 1203.1772 | F19: =IF(B19<=D19+0.000000001,"OK","VIOLATED") -> OK | G19: =IF(ABS(E19)<0.000000001,"Binding","Not binding") -> Not binding
A20: TOTAL_LABOR_HOURS ≤ TOTAL_LABOR_HOURS_CAP | B20: =TOTAL_LABOR_HOURS -> 5276.8228 | C20: ≤ | D20: =TOTAL_LABOR_HOURS_CAP -> 6480 | E20: =D20-B20 -> 1203.1772 | F20: =IF(B20<=D20+0.000000001,"OK","VIOLATED") -> OK | G20: =IF(ABS(E20)<0.000000001,"Binding","Not binding") -> Not binding
A21: TOMATO_BEDS integer | B21: =TOMATO_BEDS -> 10 | C21: int | D21: integer | E21: — | F21: =IF(B21=INT(B21),"OK","VIOLATED") -> OK | G21: —
A22: CARROT_BEDS integer | B22: =CARROT_BEDS -> 20 | C22: int | D22: integer | E22: — | F22: =IF(B22=INT(B22),"OK","VIOLATED") -> OK | G22: —
A23: MESCLUN_BEDS integer | B23: =MESCLUN_BEDS -> 30 | C23: int | D23: integer | E23: — | F23: =IF(B23=INT(B23),"OK","VIOLATED") -> OK | G23: —
A24: TOMATO_BEDS ≥ 0 | B24: =TOMATO_BEDS -> 10 | C24: ≥ | D24: 0 | E24: =B24-D24 -> 10 | F24: =IF(B24>=D24,"OK","VIOLATED") -> OK | G24: =IF(ABS(E24)<0.000000001,"Binding","Not binding") -> Not binding
A25: CARROT_BEDS ≥ 0 | B25: =CARROT_BEDS -> 20 | C25: ≥ | D25: 0 | E25: =B25-D25 -> 20 | F25: =IF(B25>=D25,"OK","VIOLATED") -> OK | G25: =IF(ABS(E25)<0.000000001,"Binding","Not binding") -> Not binding
A26: MESCLUN_BEDS ≥ 0 | B26: =MESCLUN_BEDS -> 30 | C26: ≥ | D26: 0 | E26: =B26-D26 -> 30 | F26: =IF(B26>=D26,"OK","VIOLATED") -> OK | G26: =IF(ABS(E26)<0.000000001,"Binding","Not binding") -> Not binding
A28: Marginal analysis at the current mix: what happens if one bed is added or removed (labor priced at the farm-level permanent-first allocation)
A29: Crop | B29: Current beds | C29: Labor hours of next bed | D29: Labor cost of next bed | E29: Fertilizer of next bed | F29: Revenue of next bed (P) | G29: Profit change: +1 bed | H29: +1 bed feasible? | I29: Labor hours of last bed | J29: Profit change: −1 bed | K29: What limits this crop
A30: Tomato | B30: =TOMATO_BEDS -> 10 | C30: =((TOMATO_BEDS+1)*TOMATO_HRS_PER_WEEK_PER_BED*SEASON_WEEKS*(1+TOMATO_DIM_RTRN_PCT)^(TOMATO_BEDS+1))-TOMATO_LABOR_HRS -> 490.21732 | D30: =(MIN(TOTAL_LABOR_HOURS+C30,PERMANENT_FIELD_LABOR_HOURS)*PERMANENT_HOURLY_RATE+MAX(0,TOTAL_LABOR_HOURS+C30-PERMANENT_FIELD_LABOR_HOURS)*TEMP_HOURLY_RATE)-TOTAL_LABOR_COST -> 8510.1728 | E30: =TOMATO_FERTILIZER_PER_BED -> 880 | F30: =TOMATO_REVENUE_PER_BED -> 8800 | G30: =F30-E30-D30 -> -590.17276 | H30: =AND(TOMATO_BEDS+1<=TOMATO_BED_CAP,TOTAL_BEDS_USED+1<=TOTAL_BEDS_AVAILABLE,TOTAL_LABOR_HOURS+C30<=TOTAL_LABOR_HOURS_CAP,MAX(0,TOTAL_LABOR_HOURS+C30-PERMANENT_FIELD_LABOR_HOURS)<=TEMP_HOURS_CAP) -> TRUE | I30: =IF(TOMATO_BEDS=0,0,TOMATO_LABOR_HRS-((TOMATO_BEDS-1)*TOMATO_HRS_PER_WEEK_PER_BED*SEASON_WEEKS*(1+TOMATO_DIM_RTRN_PCT)^(TOMATO_BEDS-1))) -> 424.43058 | J30: =IF(TOMATO_BEDS=0,"n/a",-(F30-E30)+(TOTAL_LABOR_COST-(MIN(TOTAL_LABOR_HOURS-I30,PERMANENT_FIELD_LABOR_HOURS)*PERMANENT_HOURLY_RATE+MAX(0,TOTAL_LABOR_HOURS-I30-PERMANENT_FIELD_LABOR_HOURS)*TEMP_HOURLY_RATE))) -> -551.88506 | K30: =IF(TOMATO_BEDS>=TOMATO_BED_CAP,"BINDING: tomato bed cap ("&TOMATO_BED_CAP&" beds). One more bed would change profit by "&TEXT(G30,"$#,##0;-$#,##0")&", so the cap limits profit.",IF(NOT(H30),"BINDING: a farm-level bed or labor limit blocks the next tomato bed.",IF(G30<=0,"Not constraint-limited: stops on marginal cost. Bed "&(TOMATO_BEDS+1)&" would add "&TEXT(C30,"#,##0")&" labor hours and change profit by "&TEXT(G30,"$#,##0;-$#,##0")&".","NOT OPTIMAL: one more tomato bed would raise profit by "&TEXT(G30,"$#,##0")&"."))) -> Not constraint-limited: stops on marginal cost. Bed 11 would add 490 labor hours and change profit by -$590.
A31: Carrot | B31: =CARROT_BEDS -> 20 | C31: =((CARROT_BEDS+1)*CARROT_HRS_PER_WEEK_PER_BED*SEASON_WEEKS*(1+CARROT_DIM_RTRN_PCT)^(CARROT_BEDS+1))-CARROT_LABOR_HRS -> 74.936715 | D31: =(MIN(TOTAL_LABOR_HOURS+C31,PERMANENT_FIELD_LABOR_HOURS)*PERMANENT_HOURLY_RATE+MAX(0,TOTAL_LABOR_HOURS+C31-PERMANENT_FIELD_LABOR_HOURS)*TEMP_HOURLY_RATE)-TOTAL_LABOR_COST -> 1300.9014 | E31: =CARROT_FERTILIZER_PER_BED -> 440 | F31: =CARROT_REVENUE_PER_BED -> 2094 | G31: =F31-E31-D31 -> 353.09862 | H31: =AND(CARROT_BEDS+1<=CARROT_BED_CAP,TOTAL_BEDS_USED+1<=TOTAL_BEDS_AVAILABLE,TOTAL_LABOR_HOURS+C31<=TOTAL_LABOR_HOURS_CAP,MAX(0,TOTAL_LABOR_HOURS+C31-PERMANENT_FIELD_LABOR_HOURS)<=TEMP_HOURS_CAP) -> FALSE | I31: =IF(CARROT_BEDS=0,0,CARROT_LABOR_HRS-((CARROT_BEDS-1)*CARROT_HRS_PER_WEEK_PER_BED*SEASON_WEEKS*(1+CARROT_DIM_RTRN_PCT)^(CARROT_BEDS-1))) -> 71.910483 | J31: =IF(CARROT_BEDS=0,"n/a",-(F31-E31)+(TOTAL_LABOR_COST-(MIN(TOTAL_LABOR_HOURS-I31,PERMANENT_FIELD_LABOR_HOURS)*PERMANENT_HOURLY_RATE+MAX(0,TOTAL_LABOR_HOURS-I31-PERMANENT_FIELD_LABOR_HOURS)*TEMP_HOURLY_RATE))) -> -405.63402 | K31: =IF(CARROT_BEDS>=CARROT_BED_CAP,"BINDING: carrot bed cap ("&CARROT_BED_CAP&" beds). One more bed would change profit by "&TEXT(G31,"$#,##0;-$#,##0")&", so the cap limits profit.",IF(NOT(H31),"BINDING: a farm-level bed or labor limit blocks the next carrot bed.",IF(G31<=0,"Not constraint-limited: stops on marginal cost. Bed "&(CARROT_BEDS+1)&" would add "&TEXT(C31,"#,##0")&" labor hours and change profit by "&TEXT(G31,"$#,##0;-$#,##0")&".","NOT OPTIMAL: one more carrot bed would raise profit by "&TEXT(G31,"$#,##0")&"."))) -> BINDING: carrot bed cap (20 beds). One more bed would change profit by $353, so the cap limits profit.
A32: Mesclun | B32: =MESCLUN_BEDS -> 30 | C32: =((MESCLUN_BEDS+1)*MESCLUN_HRS_PER_WEEK_PER_BED*SEASON_WEEKS*(1+MESCLUN_DIM_RTRN_PCT)^(MESCLUN_BEDS+1))-MESCLUN_LABOR_HRS -> 90.635109 | D32: =(MIN(TOTAL_LABOR_HOURS+C32,PERMANENT_FIELD_LABOR_HOURS)*PERMANENT_HOURLY_RATE+MAX(0,TOTAL_LABOR_HOURS+C32-PERMANENT_FIELD_LABOR_HOURS)*TEMP_HOURLY_RATE)-TOTAL_LABOR_COST -> 1573.4255 | E32: =MESCLUN_FERTILIZER_PER_BED -> 880 | F32: =MESCLUN_REVENUE_PER_BED -> 2700 | G32: =F32-E32-D32 -> 246.5745 | H32: =AND(MESCLUN_BEDS+1<=MESCLUN_BED_CAP,TOTAL_BEDS_USED+1<=TOTAL_BEDS_AVAILABLE,TOTAL_LABOR_HOURS+C32<=TOTAL_LABOR_HOURS_CAP,MAX(0,TOTAL_LABOR_HOURS+C32-PERMANENT_FIELD_LABOR_HOURS)<=TEMP_HOURS_CAP) -> FALSE | I32: =IF(MESCLUN_BEDS=0,0,MESCLUN_LABOR_HRS-((MESCLUN_BEDS-1)*MESCLUN_HRS_PER_WEEK_PER_BED*SEASON_WEEKS*(1+MESCLUN_DIM_RTRN_PCT)^(MESCLUN_BEDS-1))) -> 88.709705 | J32: =IF(MESCLUN_BEDS=0,"n/a",-(F32-E32)+(TOTAL_LABOR_COST-(MIN(TOTAL_LABOR_HOURS-I32,PERMANENT_FIELD_LABOR_HOURS)*PERMANENT_HOURLY_RATE+MAX(0,TOTAL_LABOR_HOURS-I32-PERMANENT_FIELD_LABOR_HOURS)*TEMP_HOURLY_RATE))) -> -279.99952 | K32: =IF(MESCLUN_BEDS>=MESCLUN_BED_CAP,"BINDING: mesclun bed cap ("&MESCLUN_BED_CAP&" beds). One more bed would change profit by "&TEXT(G32,"$#,##0;-$#,##0")&", so the cap limits profit.",IF(NOT(H32),"BINDING: a farm-level bed or labor limit blocks the next mesclun bed.",IF(G32<=0,"Not constraint-limited: stops on marginal cost. Bed "&(MESCLUN_BEDS+1)&" would add "&TEXT(C32,"#,##0")&" labor hours and change profit by "&TEXT(G32,"$#,##0;-$#,##0")&".","NOT OPTIMAL: one more mesclun bed would raise profit by "&TEXT(G32,"$#,##0")&"."))) -> BINDING: mesclun bed cap (30 beds). One more bed would change profit by $247, so the cap limits profit.
A34: Farm-level constraints at the current mix
A35: Constraint | B35: Used | C35: Available | D35: Unused | E35: Statement
A36: Beds (64-bed farm) | B36: =TOTAL_BEDS_USED -> 60 | C36: =TOTAL_BEDS_AVAILABLE -> 64 | D36: =UNUSED_BEDS -> 4 | E36: =IF(D36<=0.000000001,"BINDING: all beds are used; extra beds must displace existing ones (opportunity cost).","Not binding: "&TEXT(D36,"#,##0")&" beds unused, so this limit has no opportunity cost at the current mix.") -> Not binding: 4 beds unused, so this limit has no opportunity cost at the current mix.
A37: Total labor hours | B37: =TOTAL_LABOR_HOURS -> 5276.8228 | C37: =TOTAL_LABOR_HOURS_CAP -> 6480 | D37: =UNUSED_LABOR_HOURS -> 1203.1772 | E37: =IF(D37<=0.000000001,"BINDING: all labor hours are used; extra beds must displace existing ones (opportunity cost).","Not binding: "&TEXT(D37,"#,##0.0")&" labor hours unused, so this limit has no opportunity cost at the current mix.") -> Not binding: 1,203.2 labor hours unused, so this limit has no opportunity cost at the current mix.
A38: Temporary labor hours | B38: =TEMP_HOURS_USED -> 4556.8228 | C38: =TEMP_HOURS_CAP -> 5760 | D38: =TEMP_HOURS_CAP-TEMP_HOURS_USED -> 1203.1772 | E38: =IF(D38<=0.000000001,"BINDING: all temporary hours are used; extra beds must displace existing ones (opportunity cost).","Not binding: "&TEXT(D38,"#,##0.0")&" temporary hours unused, so this limit has no opportunity cost at the current mix.") -> Not binding: 1,203.2 temporary hours unused, so this limit has no opportunity cost at the current mix.
A39: Permanent labor hours | B39: =PERMANENT_HOURS_USED -> 720 | C39: =PERMANENT_FIELD_LABOR_HOURS -> 720 | D39: =PERMANENT_FIELD_LABOR_HOURS-PERMANENT_HOURS_USED -> 0 | E39: =IF(D39<=0.000000001,"Fully used (permanent hours are allocated first). Further hours are bought at the temporary rate of "&TEXT(TEMP_HOURLY_RATE,"$0.00")&"/hr, which is the marginal labor rate.","Not fully used: "&TEXT(D39,"#,##0.0")&" permanent hours spare.") -> Fully used (permanent hours are allocated first). Further hours are bought at the temporary rate of $17.36/hr, which is the marginal labor rate.
A42: Optimized solution (RECOMMENDATION)
A43: Item | B43: Decision cells (Solver) | C43: Exhaustive enumeration | D43: Match?
A44: Tomato beds | B44: =TOMATO_BEDS -> 10 | C44: =ENUM_BEST_TOMATO -> 10 | D44: =IF(ABS(B44-C44)<0.005,"PASS","FAIL") -> PASS
A45: Carrot beds | B45: =CARROT_BEDS -> 20 | C45: =ENUM_BEST_CARROT -> 20 | D45: =IF(ABS(B45-C45)<0.005,"PASS","FAIL") -> PASS
A46: Mesclun beds | B46: =MESCLUN_BEDS -> 30 | C46: =ENUM_BEST_MESCLUN -> 30 | D46: =IF(ABS(B46-C46)<0.005,"PASS","FAIL") -> PASS
A47: Seasonal profit | B47: =SEASONAL_PROFIT -> 42775.155 | C47: =ENUM_BEST_PROFIT -> 42775.155 | D47: =IF(ABS(B47-C47)<0.005,"PASS","FAIL") -> PASS
A48: Recommendation | B48: ="Plant "&TOMATO_BEDS&" tomato, "&CARROT_BEDS&" carrot and "&MESCLUN_BEDS&" mesclun beds ("&TOTAL_BEDS_USED&" of "&TOTAL_BEDS_AVAILABLE&" beds) for a seasonal profit of "&TEXT(SEASONAL_PROFIT,"$#,##0")&"." -> Plant 10 tomato, 20 carrot and 30 mesclun beds (60 of 64 beds) for a seasonal profit of $42,775.
A51: Solver settings (Data › Solver). Pre-loaded in this sheet's hidden Solver names; enter manually if the dialog is blank.
A52: Set Objective | B52: OBJECTIVE_SEASONAL_PROFIT (Optimization!$C$11)
A53: To | B53: Max
A54: By Changing Variable Cells | B54: TOMATO_BEDS, CARROT_BEDS, MESCLUN_BEDS (Optimization!$C$6:$C$8)
A55: Subject to | B55: TOMATO_BEDS ≤ TOMATO_BED_CAP; CARROT_BEDS ≤ CARROT_BED_CAP; MESCLUN_BEDS ≤ MESCLUN_BED_CAP
B56: TOTAL_BEDS_USED ≤ TOTAL_BEDS_AVAILABLE; TEMP_HOURS_USED ≤ TEMP_HOURS_CAP; TOTAL_LABOR_HOURS ≤ TOTAL_LABOR_HOURS_CAP
B57: Optimization!$C$6:$C$8 = integer
A58: Make Unconstrained Variables Non-Negative | B58: Checked
A59: Solving Method | B59: GRG Nonlinear
A60: Options › All Methods | B60: Integer Optimality (%) = 0; Ignore Integer Constraints = unchecked
A61: Options › GRG Nonlinear | B61: Use Multistart = checked (recommended: labor cost is concave in hours, so a single GRG start can stop at a local optimum)
A62: Cross-check | B62: The Enumeration sheet evaluates every integer mix; the Checks sheet fails if the Solver result differs from it.

Sheet Enumeration
A1: Exhaustive integer enumeration - every (tomato, carrot, mesclun) mix
A2: Rows = tomato × carrot pairs; columns = mesclun beds. Each cell is SEASONAL_PROFIT for that mix, or blank if it breaks a constraint. Solver-independent proof of the global optimum.
A4: Mesclun beds m → | F4: =COLUMN()-COLUMN($F$4) -> 0 | G4: =COLUMN()-COLUMN($F$4) -> 1 | H4: =COLUMN()-COLUMN($F$4) -> 2 | I4: =COLUMN()-COLUMN($F$4) -> 3 | J4: =COLUMN()-COLUMN($F$4) -> 4 | K4: =COLUMN()-COLUMN($F$4) -> 5 | L4: =COLUMN()-COLUMN($F$4) -> 6 | M4: =COLUMN()-COLUMN($F$4) -> 7 | ... AJ4: =COLUMN()-COLUMN($F$4) -> 30
A5: Mesclun labor hours LABOR_HOURS(m) | F5: =INDEX(MESCLUN_SCHED_LABOR_HRS,F$4+1) -> 0 | G5: =INDEX(MESCLUN_SCHED_LABOR_HRS,G$4+1) -> 45.5625 | H5: =INDEX(MESCLUN_SCHED_LABOR_HRS,H$4+1) -> 92.264062 | I5: =INDEX(MESCLUN_SCHED_LABOR_HRS,I$4+1) -> 140.12604 | J5: =INDEX(MESCLUN_SCHED_LABOR_HRS,J$4+1) -> 189.17016 | K5: =INDEX(MESCLUN_SCHED_LABOR_HRS,K$4+1) -> 239.41848 | L5: =INDEX(MESCLUN_SCHED_LABOR_HRS,L$4+1) -> 290.89346 | M5: =INDEX(MESCLUN_SCHED_LABOR_HRS,M$4+1) -> 343.6179 | ... AJ5: =INDEX(MESCLUN_SCHED_LABOR_HRS,AJ$4+1) -> 1959.678
A6: Mesclun net revenue m × (revenue − fertilizer) | F6: =F$4*(MESCLUN_REVENUE_PER_BED-MESCLUN_FERTILIZER_PER_BED) -> 0 | G6: =G$4*(MESCLUN_REVENUE_PER_BED-MESCLUN_FERTILIZER_PER_BED) -> 1820 | H6: =H$4*(MESCLUN_REVENUE_PER_BED-MESCLUN_FERTILIZER_PER_BED) -> 3640 | I6: =I$4*(MESCLUN_REVENUE_PER_BED-MESCLUN_FERTILIZER_PER_BED) -> 5460 | J6: =J$4*(MESCLUN_REVENUE_PER_BED-MESCLUN_FERTILIZER_PER_BED) -> 7280 | K6: =K$4*(MESCLUN_REVENUE_PER_BED-MESCLUN_FERTILIZER_PER_BED) -> 9100 | L6: =L$4*(MESCLUN_REVENUE_PER_BED-MESCLUN_FERTILIZER_PER_BED) -> 10920 | M6: =M$4*(MESCLUN_REVENUE_PER_BED-MESCLUN_FERTILIZER_PER_BED) -> 12740 | ... AJ6: =AJ$4*(MESCLUN_REVENUE_PER_BED-MESCLUN_FERTILIZER_PER_BED) -> 54600
A7: Tomato beds t | B7: Carrot beds c | C7: Net revenue of t, c | D7: Labor hours of t, c | E7: Best profit in row | AL7: Enumeration result
A8: =INT((ROW()-ROW($A$8))/(20+1)) -> 0 | B8: =MOD(ROW()-ROW($A$8),20+1) -> 0 | C8: =A8*(TOMATO_REVENUE_PER_BED-TOMATO_FERTILIZER_PER_BED)+B8*(CARROT_REVENUE_PER_BED-CARROT_FERTILIZER_PER_BED) -> 0 | D8: =INDEX(TOMATO_SCHED_LABOR_HRS,A8+1)+INDEX(CARROT_SCHED_LABOR_HRS,B8+1) -> 0 | E8: =IF(COUNT(F8:AJ8)=0,"",MAX(F8:AJ8)) -> -11919.211 | F8: =IF(OR($A8>TOMATO_BED_CAP,$B8>CARROT_BED_CAP,F$4>MESCLUN_BED_CAP,$A8+$B8+F$4>TOTAL_BEDS_AVAILABLE,($D8+F$5)>TOTAL_LABOR_HOURS_CAP,MAX(0,($D8+F$5)-PERMANENT_FIELD_LABOR_HOURS)>TEMP_HOURS_CAP),"",$C8+F$6-MIN(($D8+F$5),PERMANENT_FIELD_LABOR_HOURS)*PERMANENT_HOURLY_RATE-MAX(0,($D8+F$5)-PERMANENT_FIELD_LABOR_HOURS)*TEMP_HOURLY_RATE-FIXED_SEASON_COST) -> -20000 | G8: =IF(OR($A8>TOMATO_BED_CAP,$B8>CARROT_BED_CAP,G$4>MESCLUN_BED_CAP,$A8+$B8+G$4>TOTAL_BEDS_AVAILABLE,($D8+G$5)>TOTAL_LABOR_HOURS_CAP,MAX(0,($D8+G$5)-PERMANENT_FIELD_LABOR_HOURS)>TEMP_HOURS_CAP),"",$C8+G$6-MIN(($D8+G$5),PERMANENT_FIELD_LABOR_HOURS)*PERMANENT_HOURLY_RATE-MAX(0,($D8+G$5)-PERMANENT_FIELD_LABOR_HOURS)*TEMP_HOURLY_RATE-FIXED_SEASON_COST) -> -19761.93 | H8: =IF(OR($A8>TOMATO_BED_CAP,$B8>CARROT_BED_CAP,H$4>MESCLUN_BED_CAP,$A8+$B8+H$4>TOTAL_BEDS_AVAILABLE,($D8+H$5)>TOTAL_LABOR_HOURS_CAP,MAX(0,($D8+H$5)-PERMANENT_FIELD_LABOR_HOURS)>TEMP_HOURS_CAP),"",$C8+H$6-MIN(($D8+H$5),PERMANENT_FIELD_LABOR_HOURS)*PERMANENT_HOURLY_RATE-MAX(0,($D8+H$5)-PERMANENT_FIELD_LABOR_HOURS)*TEMP_HOURLY_RATE-FIXED_SEASON_COST) -> -19563.408 | I8: =IF(OR($A8>TOMATO_BED_CAP,$B8>CARROT_BED_CAP,I$4>MESCLUN_BED_CAP,$A8+$B8+I$4>TOTAL_BEDS_AVAILABLE,($D8+I$5)>TOTAL_LABOR_HOURS_CAP,MAX(0,($D8+I$5)-PERMANENT_FIELD_LABOR_HOURS)>TEMP_HOURS_CAP),"",$C8+I$6-MIN(($D8+I$5),PERMANENT_FIELD_LABOR_HOURS)*PERMANENT_HOURLY_RATE-MAX(0,($D8+I$5)-PERMANENT_FIELD_LABOR_HOURS)*TEMP_HOURLY_RATE-FIXED_SEASON_COST) -> -19405.176 | J8: =IF(OR($A8>TOMATO_BED_CAP,$B8>CARROT_BED_CAP,J$4>MESCLUN_BED_CAP,$A8+$B8+J$4>TOTAL_BEDS_AVAILABLE,($D8+J$5)>TOTAL_LABOR_HOURS_CAP,MAX(0,($D8+J$5)-PERMANENT_FIELD_LABOR_HOURS)>TEMP_HOURS_CAP),"",$C8+J$6-MIN(($D8+J$5),PERMANENT_FIELD_LABOR_HOURS)*PERMANENT_HOURLY_RATE-MAX(0,($D8+J$5)-PERMANENT_FIELD_LABOR_HOURS)*TEMP_HOURLY_RATE-FIXED_SEASON_COST) -> -19287.988 | K8: =IF(OR($A8>TOMATO_BED_CAP,$B8>CARROT_BED_CAP,K$4>MESCLUN_BED_CAP,$A8+$B8+K$4>TOTAL_BEDS_AVAILABLE,($D8+K$5)>TOTAL_LABOR_HOURS_CAP,MAX(0,($D8+K$5)-PERMANENT_FIELD_LABOR_HOURS)>TEMP_HOURS_CAP),"",$C8+K$6-MIN(($D8+K$5),PERMANENT_FIELD_LABOR_HOURS)*PERMANENT_HOURLY_RATE-MAX(0,($D8+K$5)-PERMANENT_FIELD_LABOR_HOURS)*TEMP_HOURLY_RATE-FIXED_SEASON_COST) -> -19212.61 | L8: =IF(OR($A8>TOMATO_BED_CAP,$B8>CARROT_BED_CAP,L$4>MESCLUN_BED_CAP,$A8+$B8+L$4>TOTAL_BEDS_AVAILABLE,($D8+L$5)>TOTAL_LABOR_HOURS_CAP,MAX(0,($D8+L$5)-PERMANENT_FIELD_LABOR_HOURS)>TEMP_HOURS_CAP),"",$C8+L$6-MIN(($D8+L$5),PERMANENT_FIELD_LABOR_HOURS)*PERMANENT_HOURLY_RATE-MAX(0,($D8+L$5)-PERMANENT_FIELD_LABOR_HOURS)*TEMP_HOURLY_RATE-FIXED_SEASON_COST) -> -19179.821 | M8: =IF(OR($A8>TOMATO_BED_CAP,$B8>CARROT_BED_CAP,M$4>MESCLUN_BED_CAP,$A8+$B8+M$4>TOTAL_BEDS_AVAILABLE,($D8+M$5)>TOTAL_LABOR_HOURS_CAP,MAX(0,($D8+M$5)-PERMANENT_FIELD_LABOR_HOURS)>TEMP_HOURS_CAP),"",$C8+M$6-MIN(($D8+M$5),PERMANENT_FIELD_LABOR_HOURS)*PERMANENT_HOURLY_RATE-MAX(0,($D8+M$5)-PERMANENT_FIELD_LABOR_HOURS)*TEMP_HOURLY_RATE-FIXED_SEASON_COST) -> -19190.413 | ... AJ8: =IF(OR($A8>TOMATO_BED_CAP,$B8>CARROT_BED_CAP,AJ$4>MESCLUN_BED_CAP,$A8+$B8+AJ$4>TOTAL_BEDS_AVAILABLE,($D8+AJ$5)>TOTAL_LABOR_HOURS_CAP,MAX(0,($D8+AJ$5)-PERMANENT_FIELD_LABOR_HOURS)>TEMP_HOURS_CAP),"",$C8+AJ$6-MIN(($D8+AJ$5),PERMANENT_FIELD_LABOR_HOURS)*PERMANENT_HOURLY_RATE-MAX(0,($D8+AJ$5)-PERMANENT_FIELD_LABOR_HOURS)*TEMP_HOURLY_RATE-FIXED_SEASON_COST) -> -11919.211 | AL8: Best feasible profit | AM8: =MAX(ENUM_ROW_BEST) -> 42775.155
A9: =INT((ROW()-ROW($A$8))/(20+1)) -> 0 | B9: =MOD(ROW()-ROW($A$8),20+1) -> 1 | C9: =A9*(TOMATO_REVENUE_PER_BED-TOMATO_FERTILIZER_PER_BED)+B9*(CARROT_REVENUE_PER_BED-CARROT_FERTILIZER_PER_BED) -> 1654 | D9: =INDEX(TOMATO_SCHED_LABOR_HRS,A9+1)+INDEX(CARROT_SCHED_LABOR_HRS,B9+1) -> 30.7377 | E9: =IF(COUNT(F9:AJ9)=0,"",MAX(F9:AJ9)) -> -10798.817 | F9: =IF(OR($A9>TOMATO_BED_CAP,$B9>CARROT_BED_CAP,F$4>MESCLUN_BED_CAP,$A9+$B9+F$4>TOTAL_BEDS_AVAILABLE,($D9+F$5)>TOTAL_LABOR_HOURS_CAP,MAX(0,($D9+F$5)-PERMANENT_FIELD_LABOR_HOURS)>TEMP_HOURS_CAP),"",$C9+F$6-MIN(($D9+F$5),PERMANENT_FIELD_LABOR_HOURS)*PERMANENT_HOURLY_RATE-MAX(0,($D9+F$5)-PERMANENT_FIELD_LABOR_HOURS)*TEMP_HOURLY_RATE-FIXED_SEASON_COST) -> -19413.213 | G9: =IF(OR($A9>TOMATO_BED_CAP,$B9>CARROT_BED_CAP,G$4>MESCLUN_BED_CAP,$A9+$B9+G$4>TOTAL_BEDS_AVAILABLE,($D9+G$5)>TOTAL_LABOR_HOURS_CAP,MAX(0,($D9+G$5)-PERMANENT_FIELD_LABOR_HOURS)>TEMP_HOURS_CAP),"",$C9+G$6-MIN(($D9+G$5),PERMANENT_FIELD_LABOR_HOURS)*PERMANENT_HOURLY_RATE-MAX(0,($D9+G$5)-PERMANENT_FIELD_LABOR_HOURS)*TEMP_HOURLY_RATE-FIXED_SEASON_COST) -> -19175.143 | H9: =IF(OR($A9>TOMATO_BED_CAP,$B9>CARROT_BED_CAP,H$4>MESCLUN_BED_CAP,$A9+$B9+H$4>TOTAL_BEDS_AVAILABLE,($D9+H$5)>TOTAL_LABOR_HOURS_CAP,MAX(0,($D9+H$5)-PERMANENT_FIELD_LABOR_HOURS)>TEMP_HOURS_CAP),"",$C9+H$6-MIN(($D9+H$5),PERMANENT_FIELD_LABOR_HOURS)*PERMANENT_HOURLY_RATE-MAX(0,($D9+H$5)-PERMANENT_FIELD_LABOR_HOURS)*TEMP_HOURLY_RATE-FIXED_SEASON_COST) -> -18976.621 | I9: =IF(OR($A9>TOMATO_BED_CAP,$B9>CARROT_BED_CAP,I$4>MESCLUN_BED_CAP,$A9+$B9+I$4>TOTAL_BEDS_AVAILABLE,($D9+I$5)>TOTAL_LABOR_HOURS_CAP,MAX(0,($D9+I$5)-PERMANENT_FIELD_LABOR_HOURS)>TEMP_HOURS_CAP),"",$C9+I$6-MIN(($D9+I$5),PERMANENT_FIELD_LABOR_HOURS)*PERMANENT_HOURLY_RATE-MAX(0,($D9+I$5)-PERMANENT_FIELD_LABOR_HOURS)*TEMP_HOURLY_RATE-FIXED_SEASON_COST) -> -18818.389 | J9: =IF(OR($A9>TOMATO_BED_CAP,$B9>CARROT_BED_CAP,J$4>MESCLUN_BED_CAP,$A9+$B9+J$4>TOTAL_BEDS_AVAILABLE,($D9+J$5)>TOTAL_LABOR_HOURS_CAP,MAX(0,($D9+J$5)-PERMANENT_FIELD_LABOR_HOURS)>TEMP_HOURS_CAP),"",$C9+J$6-MIN(($D9+J$5),PERMANENT_FIELD_LABOR_HOURS)*PERMANENT_HOURLY_RATE-MAX(0,($D9+J$5)-PERMANENT_FIELD_LABOR_HOURS)*TEMP_HOURLY_RATE-FIXED_SEASON_COST) -> -18701.201 | K9: =IF(OR($A9>TOMATO_BED_CAP,$B9>CARROT_BED_CAP,K$4>MESCLUN_BED_CAP,$A9+$B9+K$4>TOTAL_BEDS_AVAILABLE,($D9+K$5)>TOTAL_LABOR_HOURS_CAP,MAX(0,($D9+K$5)-PERMANENT_FIELD_LABOR_HOURS)>TEMP_HOURS_CAP),"",$C9+K$6-MIN(($D9+K$5),PERMANENT_FIELD_LABOR_HOURS)*PERMANENT_HOURLY_RATE-MAX(0,($D9+K$5)-PERMANENT_FIELD_LABOR_HOURS)*TEMP_HOURLY_RATE-FIXED_SEASON_COST) -> -18625.823 | L9: =IF(OR($A9>TOMATO_BED_CAP,$B9>CARROT_BED_CAP,L$4>MESCLUN_BED_CAP,$A9+$B9+L$4>TOTAL_BEDS_AVAILABLE,($D9+L$5)>TOTAL_LABOR_HOURS_CAP,MAX(0,($D9+L$5)-PERMANENT_FIELD_LABOR_HOURS)>TEMP_HOURS_CAP),"",$C9+L$6-MIN(($D9+L$5),PERMANENT_FIELD_LABOR_HOURS)*PERMANENT_HOURLY_RATE-MAX(0,($D9+L$5)-PERMANENT_FIELD_LABOR_HOURS)*TEMP_HOURLY_RATE-FIXED_SEASON_COST) -> -18593.034 | M9: =IF(OR($A9>TOMATO_BED_CAP,$B9>CARROT_BED_CAP,M$4>MESCLUN_BED_CAP,$A9+$B9+M$4>TOTAL_BEDS_AVAILABLE,($D9+M$5)>TOTAL_LABOR_HOURS_CAP,MAX(0,($D9+M$5)-PERMANENT_FIELD_LABOR_HOURS)>TEMP_HOURS_CAP),"",$C9+M$6-MIN(($D9+M$5),PERMANENT_FIELD_LABOR_HOURS)*PERMANENT_HOURLY_RATE-MAX(0,($D9+M$5)-PERMANENT_FIELD_LABOR_HOURS)*TEMP_HOURLY_RATE-FIXED_SEASON_COST) -> -18603.626 | ... AJ9: =IF(OR($A9>TOMATO_BED_CAP,$B9>CARROT_BED_CAP,AJ$4>MESCLUN_BED_CAP,$A9+$B9+AJ$4>TOTAL_BEDS_AVAILABLE,($D9+AJ$5)>TOTAL_LABOR_HOURS_CAP,MAX(0,($D9+AJ$5)-PERMANENT_FIELD_LABOR_HOURS)>TEMP_HOURS_CAP),"",$C9+AJ$6-MIN(($D9+AJ$5),PERMANENT_FIELD_LABOR_HOURS)*PERMANENT_HOURLY_RATE-MAX(0,($D9+AJ$5)-PERMANENT_FIELD_LABOR_HOURS)*TEMP_HOURLY_RATE-FIXED_SEASON_COST) -> -10798.817 | AL9: Row of best mix | AM9: =MATCH(ENUM_BEST_PROFIT,ENUM_ROW_BEST,0) -> 231
A10: =INT((ROW()-ROW($A$8))/(20+1)) -> 0 | B10: =MOD(ROW()-ROW($A$8),20+1) -> 2 | C10: =A10*(TOMATO_REVENUE_PER_BED-TOMATO_FERTILIZER_PER_BED)+B10*(CARROT_REVENUE_PER_BED-CARROT_FERTILIZER_PER_BED) -> 3308 | D10: =INDEX(TOMATO_SCHED_LABOR_HRS,A10+1)+INDEX(CARROT_SCHED_LABOR_HRS,B10+1) -> 63.012285 | E10: =IF(COUNT(F10:AJ10)=0,"",MAX(F10:AJ10)) -> -9705.104 | F10: =IF(OR($A10>TOMATO_BED_CAP,$B10>CARROT_BED_CAP,F$4>MESCLUN_BED_CAP,$A10+$B10+F$4>TOTAL_BEDS_AVAILABLE,($D10+F$5)>TOTAL_LABOR_HOURS_CAP,MAX(0,($D10+F$5)-PERMANENT_FIELD_LABOR_HOURS)>TEMP_HOURS_CAP),"",$C10+F$6-MIN(($D10+F$5),PERMANENT_FIELD_LABOR_HOURS)*PERMANENT_HOURLY_RATE-MAX(0,($D10+F$5)-PERMANENT_FIELD_LABOR_HOURS)*TEMP_HOURLY_RATE-FIXED_SEASON_COST) -> -18879.787 | G10: =IF(OR($A10>TOMATO_BED_CAP,$B10>CARROT_BED_CAP,G$4>MESCLUN_BED_CAP,$A10+$B10+G$4>TOTAL_BEDS_AVAILABLE,($D10+G$5)>TOTAL_LABOR_HOURS_CAP,MAX(0,($D10+G$5)-PERMANENT_FIELD_LABOR_HOURS)>TEMP_HOURS_CAP),"",$C10+G$6-MIN(($D10+G$5),PERMANENT_FIELD_LABOR_HOURS)*PERMANENT_HOURLY_RATE-MAX(0,($D10+G$5)-PERMANENT_FIELD_LABOR_HOURS)*TEMP_HOURLY_RATE-FIXED_SEASON_COST) -> -18641.717 | H10: =IF(OR($A10>TOMATO_BED_CAP,$B10>CARROT_BED_CAP,H$4>MESCLUN_BED_CAP,$A10+$B10+H$4>TOTAL_BEDS_AVAILABLE,($D10+H$5)>TOTAL_LABOR_HOURS_CAP,MAX(0,($D10+H$5)-PERMANENT_FIELD_LABOR_HOURS)>TEMP_HOURS_CAP),"",$C10+H$6-MIN(($D10+H$5),PERMANENT_FIELD_LABOR_HOURS)*PERMANENT_HOURLY_RATE-MAX(0,($D10+H$5)-PERMANENT_FIELD_LABOR_HOURS)*TEMP_HOURLY_RATE-FIXED_SEASON_COST) -> -18443.195 | I10: =IF(OR($A10>TOMATO_BED_CAP,$B10>CARROT_BED_CAP,I$4>MESCLUN_BED_CAP,$A10+$B10+I$4>TOTAL_BEDS_AVAILABLE,($D10+I$5)>TOTAL_LABOR_HOURS_CAP,MAX(0,($D10+I$5)-PERMANENT_FIELD_LABOR_HOURS)>TEMP_HOURS_CAP),"",$C10+I$6-MIN(($D10+I$5),PERMANENT_FIELD_LABOR_HOURS)*PERMANENT_HOURLY_RATE-MAX(0,($D10+I$5)-PERMANENT_FIELD_LABOR_HOURS)*TEMP_HOURLY_RATE-FIXED_SEASON_COST) -> -18284.963 | J10: =IF(OR($A10>TOMATO_BED_CAP,$B10>CARROT_BED_CAP,J$4>MESCLUN_BED_CAP,$A10+$B10+J$4>TOTAL_BEDS_AVAILABLE,($D10+J$5)>TOTAL_LABOR_HOURS_CAP,MAX(0,($D10+J$5)-PERMANENT_FIELD_LABOR_HOURS)>TEMP_HOURS_CAP),"",$C10+J$6-MIN(($D10+J$5),PERMANENT_FIELD_LABOR_HOURS)*PERMANENT_HOURLY_RATE-MAX(0,($D10+J$5)-PERMANENT_FIELD_LABOR_HOURS)*TEMP_HOURLY_RATE-FIXED_SEASON_COST) -> -18167.775 | K10: =IF(OR($A10>TOMATO_BED_CAP,$B10>CARROT_BED_CAP,K$4>MESCLUN_BED_CAP,$A10+$B10+K$4>TOTAL_BEDS_AVAILABLE,($D10+K$5)>TOTAL_LABOR_HOURS_CAP,MAX(0,($D10+K$5)-PERMANENT_FIELD_LABOR_HOURS)>TEMP_HOURS_CAP),"",$C10+K$6-MIN(($D10+K$5),PERMANENT_FIELD_LABOR_HOURS)*PERMANENT_HOURLY_RATE-MAX(0,($D10+K$5)-PERMANENT_FIELD_LABOR_HOURS)*TEMP_HOURLY_RATE-FIXED_SEASON_COST) -> -18092.396 | L10: =IF(OR($A10>TOMATO_BED_CAP,$B10>CARROT_BED_CAP,L$4>MESCLUN_BED_CAP,$A10+$B10+L$4>TOTAL_BEDS_AVAILABLE,($D10+L$5)>TOTAL_LABOR_HOURS_CAP,MAX(0,($D10+L$5)-PERMANENT_FIELD_LABOR_HOURS)>TEMP_HOURS_CAP),"",$C10+L$6-MIN(($D10+L$5),PERMANENT_FIELD_LABOR_HOURS)*PERMANENT_HOURLY_RATE-MAX(0,($D10+L$5)-PERMANENT_FIELD_LABOR_HOURS)*TEMP_HOURLY_RATE-FIXED_SEASON_COST) -> -18059.607 | M10: =IF(OR($A10>TOMATO_BED_CAP,$B10>CARROT_BED_CAP,M$4>MESCLUN_BED_CAP,$A10+$B10+M$4>TOTAL_BEDS_AVAILABLE,($D10+M$5)>TOTAL_LABOR_HOURS_CAP,MAX(0,($D10+M$5)-PERMANENT_FIELD_LABOR_HOURS)>TEMP_HOURS_CAP),"",$C10+M$6-MIN(($D10+M$5),PERMANENT_FIELD_LABOR_HOURS)*PERMANENT_HOURLY_RATE-MAX(0,($D10+M$5)-PERMANENT_FIELD_LABOR_HOURS)*TEMP_HOURLY_RATE-FIXED_SEASON_COST) -> -18070.2 | ... AJ10: =IF(OR($A10>TOMATO_BED_CAP,$B10>CARROT_BED_CAP,AJ$4>MESCLUN_BED_CAP,$A10+$B10+AJ$4>TOTAL_BEDS_AVAILABLE,($D10+AJ$5)>TOTAL_LABOR_HOURS_CAP,MAX(0,($D10+AJ$5)-PERMANENT_FIELD_LABOR_HOURS)>TEMP_HOURS_CAP),"",$C10+AJ$6-MIN(($D10+AJ$5),PERMANENT_FIELD_LABOR_HOURS)*PERMANENT_HOURLY_RATE-MAX(0,($D10+AJ$5)-PERMANENT_FIELD_LABOR_HOURS)*TEMP_HOURLY_RATE-FIXED_SEASON_COST) -> -9705.104 | AL10: Best tomato beds | AM10: =INDEX(ENUM_T,ENUM_BEST_ROW) -> 10
A11: =INT((ROW()-ROW($A$8))/(20+1)) -> 0 | B11: =MOD(ROW()-ROW($A$8),20+1) -> 3 | C11: =A11*(TOMATO_REVENUE_PER_BED-TOMATO_FERTILIZER_PER_BED)+B11*(CARROT_REVENUE_PER_BED-CARROT_FERTILIZER_PER_BED) -> 4962 | D11: =INDEX(TOMATO_SCHED_LABOR_HRS,A11+1)+INDEX(CARROT_SCHED_LABOR_HRS,B11+1) -> 96.881388 | E11: =IF(COUNT(F11:AJ11)=0,"",MAX(F11:AJ11)) -> -8639.0716 | F11: =IF(OR($A11>TOMATO_BED_CAP,$B11>CARROT_BED_CAP,F$4>MESCLUN_BED_CAP,$A11+$B11+F$4>TOTAL_BEDS_AVAILABLE,($D11+F$5)>TOTAL_LABOR_HOURS_CAP,MAX(0,($D11+F$5)-PERMANENT_FIELD_LABOR_HOURS)>TEMP_HOURS_CAP),"",$C11+F$6-MIN(($D11+F$5),PERMANENT_FIELD_LABOR_HOURS)*PERMANENT_HOURLY_RATE-MAX(0,($D11+F$5)-PERMANENT_FIELD_LABOR_HOURS)*TEMP_HOURLY_RATE-FIXED_SEASON_COST) -> -18401.722 | G11: =IF(OR($A11>TOMATO_BED_CAP,$B11>CARROT_BED_CAP,G$4>MESCLUN_BED_CAP,$A11+$B11+G$4>TOTAL_BEDS_AVAILABLE,($D11+G$5)>TOTAL_LABOR_HOURS_CAP,MAX(0,($D11+G$5)-PERMANENT_FIELD_LABOR_HOURS)>TEMP_HOURS_CAP),"",$C11+G$6-MIN(($D11+G$5),PERMANENT_FIELD_LABOR_HOURS)*PERMANENT_HOURLY_RATE-MAX(0,($D11+G$5)-PERMANENT_FIELD_LABOR_HOURS)*TEMP_HOURLY_RATE-FIXED_SEASON_COST) -> -18163.652 | H11: =IF(OR($A11>TOMATO_BED_CAP,$B11>CARROT_BED_CAP,H$4>MESCLUN_BED_CAP,$A11+$B11+H$4>TOTAL_BEDS_AVAILABLE,($D11+H$5)>TOTAL_LABOR_HOURS_CAP,MAX(0,($D11+H$5)-PERMANENT_FIELD_LABOR_HOURS)>TEMP_HOURS_CAP),"",$C11+H$6-MIN(($D11+H$5),PERMANENT_FIELD_LABOR_HOURS)*PERMANENT_HOURLY_RATE-MAX(0,($D11+H$5)-PERMANENT_FIELD_LABOR_HOURS)*TEMP_HOURLY_RATE-FIXED_SEASON_COST) -> -17965.13 | I11: =IF(OR($A11>TOMATO_BED_CAP,$B11>CARROT_BED_CAP,I$4>MESCLUN_BED_CAP,$A11+$B11+I$4>TOTAL_BEDS_AVAILABLE,($D11+I$5)>TOTAL_LABOR_HOURS_CAP,MAX(0,($D11+I$5)-PERMANENT_FIELD_LABOR_HOURS)>TEMP_HOURS_CAP),"",$C11+I$6-MIN(($D11+I$5),PERMANENT_FIELD_LABOR_HOURS)*PERMANENT_HOURLY_RATE-MAX(0,($D11+I$5)-PERMANENT_FIELD_LABOR_HOURS)*TEMP_HOURLY_RATE-FIXED_SEASON_COST) -> -17806.898 | J11: =IF(OR($A11>TOMATO_BED_CAP,$B11>CARROT_BED_CAP,J$4>MESCLUN_BED_CAP,$A11+$B11+J$4>TOTAL_BEDS_AVAILABLE,($D11+J$5)>TOTAL_LABOR_HOURS_CAP,MAX(0,($D11+J$5)-PERMANENT_FIELD_LABOR_HOURS)>TEMP_HOURS_CAP),"",$C11+J$6-MIN(($D11+J$5),PERMANENT_FIELD_LABOR_HOURS)*PERMANENT_HOURLY_RATE-MAX(0,($D11+J$5)-PERMANENT_FIELD_LABOR_HOURS)*TEMP_HOURLY_RATE-FIXED_SEASON_COST) -> -17689.71 | K11: =IF(OR($A11>TOMATO_BED_CAP,$B11>CARROT_BED_CAP,K$4>MESCLUN_BED_CAP,$A11+$B11+K$4>TOTAL_BEDS_AVAILABLE,($D11+K$5)>TOTAL_LABOR_HOURS_CAP,MAX(0,($D11+K$5)-PERMANENT_FIELD_LABOR_HOURS)>TEMP_HOURS_CAP),"",$C11+K$6-MIN(($D11+K$5),PERMANENT_FIELD_LABOR_HOURS)*PERMANENT_HOURLY_RATE-MAX(0,($D11+K$5)-PERMANENT_FIELD_LABOR_HOURS)*TEMP_HOURLY_RATE-FIXED_SEASON_COST) -> -17614.332 | L11: =IF(OR($A11>TOMATO_BED_CAP,$B11>CARROT_BED_CAP,L$4>MESCLUN_BED_CAP,$A11+$B11+L$4>TOTAL_BEDS_AVAILABLE,($D11+L$5)>TOTAL_LABOR_HOURS_CAP,MAX(0,($D11+L$5)-PERMANENT_FIELD_LABOR_HOURS)>TEMP_HOURS_CAP),"",$C11+L$6-MIN(($D11+L$5),PERMANENT_FIELD_LABOR_HOURS)*PERMANENT_HOURLY_RATE-MAX(0,($D11+L$5)-PERMANENT_FIELD_LABOR_HOURS)*TEMP_HOURLY_RATE-FIXED_SEASON_COST) -> -17581.543 | M11: =IF(OR($A11>TOMATO_BED_CAP,$B11>CARROT_BED_CAP,M$4>MESCLUN_BED_CAP,$A11+$B11+M$4>TOTAL_BEDS_AVAILABLE,($D11+M$5)>TOTAL_LABOR_HOURS_CAP,MAX(0,($D11+M$5)-PERMANENT_FIELD_LABOR_HOURS)>TEMP_HOURS_CAP),"",$C11+M$6-MIN(($D11+M$5),PERMANENT_FIELD_LABOR_HOURS)*PERMANENT_HOURLY_RATE-MAX(0,($D11+M$5)-PERMANENT_FIELD_LABOR_HOURS)*TEMP_HOURLY_RATE-FIXED_SEASON_COST) -> -17592.135 | ... AJ11: =IF(OR($A11>TOMATO_BED_CAP,$B11>CARROT_BED_CAP,AJ$4>MESCLUN_BED_CAP,$A11+$B11+AJ$4>TOTAL_BEDS_AVAILABLE,($D11+AJ$5)>TOTAL_LABOR_HOURS_CAP,MAX(0,($D11+AJ$5)-PERMANENT_FIELD_LABOR_HOURS)>TEMP_HOURS_CAP),"",$C11+AJ$6-MIN(($D11+AJ$5),PERMANENT_FIELD_LABOR_HOURS)*PERMANENT_HOURLY_RATE-MAX(0,($D11+AJ$5)-PERMANENT_FIELD_LABOR_HOURS)*TEMP_HOURLY_RATE-FIXED_SEASON_COST) -> -8639.0716 | AL11: Best carrot beds | AM11: =INDEX(ENUM_C,ENUM_BEST_ROW) -> 20
A12: =INT((ROW()-ROW($A$8))/(20+1)) -> 0 | B12: =MOD(ROW()-ROW($A$8),20+1) -> 4 | C12: =A12*(TOMATO_REVENUE_PER_BED-TOMATO_FERTILIZER_PER_BED)+B12*(CARROT_REVENUE_PER_BED-CARROT_FERTILIZER_PER_BED) -> 6616 | D12: =INDEX(TOMATO_SCHED_LABOR_HRS,A12+1)+INDEX(CARROT_SCHED_LABOR_HRS,B12+1) -> 132.40456 | E12: =IF(COUNT(F12:AJ12)=0,"",MAX(F12:AJ12)) -> -7601.7539 | F12: =IF(OR($A12>TOMATO_BED_CAP,$B12>CARROT_BED_CAP,F$4>MESCLUN_BED_CAP,$A12+$B12+F$4>TOTAL_BEDS_AVAILABLE,($D12+F$5)>TOTAL_LABOR_HOURS_CAP,MAX(0,($D12+F$5)-PERMANENT_FIELD_LABOR_HOURS)>TEMP_HOURS_CAP),"",$C12+F$6-MIN(($D12+F$5),PERMANENT_FIELD_LABOR_HOURS)*PERMANENT_HOURLY_RATE-MAX(0,($D12+F$5)-PERMANENT_FIELD_LABOR_HOURS)*TEMP_HOURLY_RATE-FIXED_SEASON_COST) -> -17981.086 | G12: =IF(OR($A12>TOMATO_BED_CAP,$B12>CARROT_BED_CAP,G$4>MESCLUN_BED_CAP,$A12+$B12+G$4>TOTAL_BEDS_AVAILABLE,($D12+G$5)>TOTAL_LABOR_HOURS_CAP,MAX(0,($D12+G$5)-PERMANENT_FIELD_LABOR_HOURS)>TEMP_HOURS_CAP),"",$C12+G$6-MIN(($D12+G$5),PERMANENT_FIELD_LABOR_HOURS)*PERMANENT_HOURLY_RATE-MAX(0,($D12+G$5)-PERMANENT_FIELD_LABOR_HOURS)*TEMP_HOURLY_RATE-FIXED_SEASON_COST) -> -17743.016 | H12: =IF(OR($A12>TOMATO_BED_CAP,$B12>CARROT_BED_CAP,H$4>MESCLUN_BED_CAP,$A12+$B12+H$4>TOTAL_BEDS_AVAILABLE,($D12+H$5)>TOTAL_LABOR_HOURS_CAP,MAX(0,($D12+H$5)-PERMANENT_FIELD_LABOR_HOURS)>TEMP_HOURS_CAP),"",$C12+H$6-MIN(($D12+H$5),PERMANENT_FIELD_LABOR_HOURS)*PERMANENT_HOURLY_RATE-MAX(0,($D12+H$5)-PERMANENT_FIELD_LABOR_HOURS)*TEMP_HOURLY_RATE-FIXED_SEASON_COST) -> -17544.495 | I12: =IF(OR($A12>TOMATO_BED_CAP,$B12>CARROT_BED_CAP,I$4>MESCLUN_BED_CAP,$A12+$B12+I$4>TOTAL_BEDS_AVAILABLE,($D12+I$5)>TOTAL_LABOR_HOURS_CAP,MAX(0,($D12+I$5)-PERMANENT_FIELD_LABOR_HOURS)>TEMP_HOURS_CAP),"",$C12+I$6-MIN(($D12+I$5),PERMANENT_FIELD_LABOR_HOURS)*PERMANENT_HOURLY_RATE-MAX(0,($D12+I$5)-PERMANENT_FIELD_LABOR_HOURS)*TEMP_HOURLY_RATE-FIXED_SEASON_COST) -> -17386.263 | J12: =IF(OR($A12>TOMATO_BED_CAP,$B12>CARROT_BED_CAP,J$4>MESCLUN_BED_CAP,$A12+$B12+J$4>TOTAL_BEDS_AVAILABLE,($D12+J$5)>TOTAL_LABOR_HOURS_CAP,MAX(0,($D12+J$5)-PERMANENT_FIELD_LABOR_HOURS)>TEMP_HOURS_CAP),"",$C12+J$6-MIN(($D12+J$5),PERMANENT_FIELD_LABOR_HOURS)*PERMANENT_HOURLY_RATE-MAX(0,($D12+J$5)-PERMANENT_FIELD_LABOR_HOURS)*TEMP_HOURLY_RATE-FIXED_SEASON_COST) -> -17269.074 | K12: =IF(OR($A12>TOMATO_BED_CAP,$B12>CARROT_BED_CAP,K$4>MESCLUN_BED_CAP,$A12+$B12+K$4>TOTAL_BEDS_AVAILABLE,($D12+K$5)>TOTAL_LABOR_HOURS_CAP,MAX(0,($D12+K$5)-PERMANENT_FIELD_LABOR_HOURS)>TEMP_HOURS_CAP),"",$C12+K$6-MIN(($D12+K$5),PERMANENT_FIELD_LABOR_HOURS)*PERMANENT_HOURLY_RATE-MAX(0,($D12+K$5)-PERMANENT_FIELD_LABOR_HOURS)*TEMP_HOURLY_RATE-FIXED_SEASON_COST) -> -17193.696 | L12: =IF(OR($A12>TOMATO_BED_CAP,$B12>CARROT_BED_CAP,L$4>MESCLUN_BED_CAP,$A12+$B12+L$4>TOTAL_BEDS_AVAILABLE,($D12+L$5)>TOTAL_LABOR_HOURS_CAP,MAX(0,($D12+L$5)-PERMANENT_FIELD_LABOR_HOURS)>TEMP_HOURS_CAP),"",$C12+L$6-MIN(($D12+L$5),PERMANENT_FIELD_LABOR_HOURS)*PERMANENT_HOURLY_RATE-MAX(0,($D12+L$5)-PERMANENT_FIELD_LABOR_HOURS)*TEMP_HOURLY_RATE-FIXED_SEASON_COST) -> -17160.907 | M12: =IF(OR($A12>TOMATO_BED_CAP,$B12>CARROT_BED_CAP,M$4>MESCLUN_BED_CAP,$A12+$B12+M$4>TOTAL_BEDS_AVAILABLE,($D12+M$5)>TOTAL_LABOR_HOURS_CAP,MAX(0,($D12+M$5)-PERMANENT_FIELD_LABOR_HOURS)>TEMP_HOURS_CAP),"",$C12+M$6-MIN(($D12+M$5),PERMANENT_FIELD_LABOR_HOURS)*PERMANENT_HOURLY_RATE-MAX(0,($D12+M$5)-PERMANENT_FIELD_LABOR_HOURS)*TEMP_HOURLY_RATE-FIXED_SEASON_COST) -> -17171.5 | ... AJ12: =IF(OR($A12>TOMATO_BED_CAP,$B12>CARROT_BED_CAP,AJ$4>MESCLUN_BED_CAP,$A12+$B12+AJ$4>TOTAL_BEDS_AVAILABLE,($D12+AJ$5)>TOTAL_LABOR_HOURS_CAP,MAX(0,($D12+AJ$5)-PERMANENT_FIELD_LABOR_HOURS)>TEMP_HOURS_CAP),"",$C12+AJ$6-MIN(($D12+AJ$5),PERMANENT_FIELD_LABOR_HOURS)*PERMANENT_HOURLY_RATE-MAX(0,($D12+AJ$5)-PERMANENT_FIELD_LABOR_HOURS)*TEMP_HOURLY_RATE-FIXED_SEASON_COST) -> -7601.7539 | AL12: Best mesclun beds | AM12: =MATCH(ENUM_BEST_PROFIT,INDEX(ENUM_GRID,ENUM_BEST_ROW,0),0)-1 -> 30
A13: =INT((ROW()-ROW($A$8))/(20+1)) -> 0 | B13: =MOD(ROW()-ROW($A$8),20+1) -> 5 | C13: =A13*(TOMATO_REVENUE_PER_BED-TOMATO_FERTILIZER_PER_BED)+B13*(CARROT_REVENUE_PER_BED-CARROT_FERTILIZER_PER_BED) -> 8270 | D13: =INDEX(TOMATO_SCHED_LABOR_HRS,A13+1)+INDEX(CARROT_SCHED_LABOR_HRS,B13+1) -> 169.64335 | E13: =IF(COUNT(F13:AJ13)=0,"",MAX(F13:AJ13)) -> -6594.2192 | F13: =IF(OR($A13>TOMATO_BED_CAP,$B13>CARROT_BED_CAP,F$4>MESCLUN_BED_CAP,$A13+$B13+F$4>TOTAL_BEDS_AVAILABLE,($D13+F$5)>TOTAL_LABOR_HOURS_CAP,MAX(0,($D13+F$5)-PERMANENT_FIELD_LABOR_HOURS)>TEMP_HOURS_CAP),"",$C13+F$6-MIN(($D13+F$5),PERMANENT_FIELD_LABOR_HOURS)*PERMANENT_HOURLY_RATE-MAX(0,($D13+F$5)-PERMANENT_FIELD_LABOR_HOURS)*TEMP_HOURLY_RATE-FIXED_SEASON_COST) -> -17620.017 | G13: =IF(OR($A13>TOMATO_BED_CAP,$B13>CARROT_BED_CAP,G$4>MESCLUN_BED_CAP,$A13+$B13+G$4>TOTAL_BEDS_AVAILABLE,($D13+G$5)>TOTAL_LABOR_HOURS_CAP,MAX(0,($D13+G$5)-PERMANENT_FIELD_LABOR_HOURS)>TEMP_HOURS_CAP),"",$C13+G$6-MIN(($D13+G$5),PERMANENT_FIELD_LABOR_HOURS)*PERMANENT_HOURLY_RATE-MAX(0,($D13+G$5)-PERMANENT_FIELD_LABOR_HOURS)*TEMP_HOURLY_RATE-FIXED_SEASON_COST) -> -17381.947 | H13: =IF(OR($A13>TOMATO_BED_CAP,$B13>CARROT_BED_CAP,H$4>MESCLUN_BED_CAP,$A13+$B13+H$4>TOTAL_BEDS_AVAILABLE,($D13+H$5)>TOTAL_LABOR_HOURS_CAP,MAX(0,($D13+H$5)-PERMANENT_FIELD_LABOR_HOURS)>TEMP_HOURS_CAP),"",$C13+H$6-MIN(($D13+H$5),PERMANENT_FIELD_LABOR_HOURS)*PERMANENT_HOURLY_RATE-MAX(0,($D13+H$5)-PERMANENT_FIELD_LABOR_HOURS)*TEMP_HOURLY_RATE-FIXED_SEASON_COST) -> -17183.425 | I13: =IF(OR($A13>TOMATO_BED_CAP,$B13>CARROT_BED_CAP,I$4>MESCLUN_BED_CAP,$A13+$B13+I$4>TOTAL_BEDS_AVAILABLE,($D13+I$5)>TOTAL_LABOR_HOURS_CAP,MAX(0,($D13+I$5)-PERMANENT_FIELD_LABOR_HOURS)>TEMP_HOURS_CAP),"",$C13+I$6-MIN(($D13+I$5),PERMANENT_FIELD_LABOR_HOURS)*PERMANENT_HOURLY_RATE-MAX(0,($D13+I$5)-PERMANENT_FIELD_LABOR_HOURS)*TEMP_HOURLY_RATE-FIXED_SEASON_COST) -> -17025.193 | J13: =IF(OR($A13>TOMATO_BED_CAP,$B13>CARROT_BED_CAP,J$4>MESCLUN_BED_CAP,$A13+$B13+J$4>TOTAL_BEDS_AVAILABLE,($D13+J$5)>TOTAL_LABOR_HOURS_CAP,MAX(0,($D13+J$5)-PERMANENT_FIELD_LABOR_HOURS)>TEMP_HOURS_CAP),"",$C13+J$6-MIN(($D13+J$5),PERMANENT_FIELD_LABOR_HOURS)*PERMANENT_HOURLY_RATE-MAX(0,($D13+J$5)-PERMANENT_FIELD_LABOR_HOURS)*TEMP_HOURLY_RATE-FIXED_SEASON_COST) -> -16908.005 | K13: =IF(OR($A13>TOMATO_BED_CAP,$B13>CARROT_BED_CAP,K$4>MESCLUN_BED_CAP,$A13+$B13+K$4>TOTAL_BEDS_AVAILABLE,($D13+K$5)>TOTAL_LABOR_HOURS_CAP,MAX(0,($D13+K$5)-PERMANENT_FIELD_LABOR_HOURS)>TEMP_HOURS_CAP),"",$C13+K$6-MIN(($D13+K$5),PERMANENT_FIELD_LABOR_HOURS)*PERMANENT_HOURLY_RATE-MAX(0,($D13+K$5)-PERMANENT_FIELD_LABOR_HOURS)*TEMP_HOURLY_RATE-FIXED_SEASON_COST) -> -16832.627 | L13: =IF(OR($A13>TOMATO_BED_CAP,$B13>CARROT_BED_CAP,L$4>MESCLUN_BED_CAP,$A13+$B13+L$4>TOTAL_BEDS_AVAILABLE,($D13+L$5)>TOTAL_LABOR_HOURS_CAP,MAX(0,($D13+L$5)-PERMANENT_FIELD_LABOR_HOURS)>TEMP_HOURS_CAP),"",$C13+L$6-MIN(($D13+L$5),PERMANENT_FIELD_LABOR_HOURS)*PERMANENT_HOURLY_RATE-MAX(0,($D13+L$5)-PERMANENT_FIELD_LABOR_HOURS)*TEMP_HOURLY_RATE-FIXED_SEASON_COST) -> -16799.838 | M13: =IF(OR($A13>TOMATO_BED_CAP,$B13>CARROT_BED_CAP,M$4>MESCLUN_BED_CAP,$A13+$B13+M$4>TOTAL_BEDS_AVAILABLE,($D13+M$5)>TOTAL_LABOR_HOURS_CAP,MAX(0,($D13+M$5)-PERMANENT_FIELD_LABOR_HOURS)>TEMP_HOURS_CAP),"",$C13+M$6-MIN(($D13+M$5),PERMANENT_FIELD_LABOR_HOURS)*PERMANENT_HOURLY_RATE-MAX(0,($D13+M$5)-PERMANENT_FIELD_LABOR_HOURS)*TEMP_HOURLY_RATE-FIXED_SEASON_COST) -> -16810.43 | ... AJ13: =IF(OR($A13>TOMATO_BED_CAP,$B13>CARROT_BED_CAP,AJ$4>MESCLUN_BED_CAP,$A13+$B13+AJ$4>TOTAL_BEDS_AVAILABLE,($D13+AJ$5)>TOTAL_LABOR_HOURS_CAP,MAX(0,($D13+AJ$5)-PERMANENT_FIELD_LABOR_HOURS)>TEMP_HOURS_CAP),"",$C13+AJ$6-MIN(($D13+AJ$5),PERMANENT_FIELD_LABOR_HOURS)*PERMANENT_HOURLY_RATE-MAX(0,($D13+AJ$5)-PERMANENT_FIELD_LABOR_HOURS)*TEMP_HOURLY_RATE-FIXED_SEASON_COST) -> -6594.2192 | AL13: Mixes tied at best profit | AM13: =COUNTIF(ENUM_GRID,ENUM_BEST_PROFIT) -> 1
A14: =INT((ROW()-ROW($A$8))/(20+1)) -> 0 | B14: =MOD(ROW()-ROW($A$8),20+1) -> 6 | C14: =A14*(TOMATO_REVENUE_PER_BED-TOMATO_FERTILIZER_PER_BED)+B14*(CARROT_REVENUE_PER_BED-CARROT_FERTILIZER_PER_BED) -> 9924 | D14: =INDEX(TOMATO_SCHED_LABOR_HRS,A14+1)+INDEX(CARROT_SCHED_LABOR_HRS,B14+1) -> 208.66132 | E14: =IF(COUNT(F14:AJ14)=0,"",MAX(F14:AJ14)) -> -5617.5712 | F14: =IF(OR($A14>TOMATO_BED_CAP,$B14>CARROT_BED_CAP,F$4>MESCLUN_BED_CAP,$A14+$B14+F$4>TOTAL_BEDS_AVAILABLE,($D14+F$5)>TOTAL_LABOR_HOURS_CAP,MAX(0,($D14+F$5)-PERMANENT_FIELD_LABOR_HOURS)>TEMP_HOURS_CAP),"",$C14+F$6-MIN(($D14+F$5),PERMANENT_FIELD_LABOR_HOURS)*PERMANENT_HOURLY_RATE-MAX(0,($D14+F$5)-PERMANENT_FIELD_LABOR_HOURS)*TEMP_HOURLY_RATE-FIXED_SEASON_COST) -> -17320.721 | G14: =IF(OR($A14>TOMATO_BED_CAP,$B14>CARROT_BED_CAP,G$4>MESCLUN_BED_CAP,$A14+$B14+G$4>TOTAL_BEDS_AVAILABLE,($D14+G$5)>TOTAL_LABOR_HOURS_CAP,MAX(0,($D14+G$5)-PERMANENT_FIELD_LABOR_HOURS)>TEMP_HOURS_CAP),"",$C14+G$6-MIN(($D14+G$5),PERMANENT_FIELD_LABOR_HOURS)*PERMANENT_HOURLY_RATE-MAX(0,($D14+G$5)-PERMANENT_FIELD_LABOR_HOURS)*TEMP_HOURLY_RATE-FIXED_SEASON_COST) -> -17082.651 | H14: =IF(OR($A14>TOMATO_BED_CAP,$B14>CARROT_BED_CAP,H$4>MESCLUN_BED_CAP,$A14+$B14+H$4>TOTAL_BEDS_AVAILABLE,($D14+H$5)>TOTAL_LABOR_HOURS_CAP,MAX(0,($D14+H$5)-PERMANENT_FIELD_LABOR_HOURS)>TEMP_HOURS_CAP),"",$C14+H$6-MIN(($D14+H$5),PERMANENT_FIELD_LABOR_HOURS)*PERMANENT_HOURLY_RATE-MAX(0,($D14+H$5)-PERMANENT_FIELD_LABOR_HOURS)*TEMP_HOURLY_RATE-FIXED_SEASON_COST) -> -16884.129 | I14: =IF(OR($A14>TOMATO_BED_CAP,$B14>CARROT_BED_CAP,I$4>MESCLUN_BED_CAP,$A14+$B14+I$4>TOTAL_BEDS_AVAILABLE,($D14+I$5)>TOTAL_LABOR_HOURS_CAP,MAX(0,($D14+I$5)-PERMANENT_FIELD_LABOR_HOURS)>TEMP_HOURS_CAP),"",$C14+I$6-MIN(($D14+I$5),PERMANENT_FIELD_LABOR_HOURS)*PERMANENT_HOURLY_RATE-MAX(0,($D14+I$5)-PERMANENT_FIELD_LABOR_HOURS)*TEMP_HOURLY_RATE-FIXED_SEASON_COST) -> -16725.897 | J14: =IF(OR($A14>TOMATO_BED_CAP,$B14>CARROT_BED_CAP,J$4>MESCLUN_BED_CAP,$A14+$B14+J$4>TOTAL_BEDS_AVAILABLE,($D14+J$5)>TOTAL_LABOR_HOURS_CAP,MAX(0,($D14+J$5)-PERMANENT_FIELD_LABOR_HOURS)>TEMP_HOURS_CAP),"",$C14+J$6-MIN(($D14+J$5),PERMANENT_FIELD_LABOR_HOURS)*PERMANENT_HOURLY_RATE-MAX(0,($D14+J$5)-PERMANENT_FIELD_LABOR_HOURS)*TEMP_HOURLY_RATE-FIXED_SEASON_COST) -> -16608.709 | K14: =IF(OR($A14>TOMATO_BED_CAP,$B14>CARROT_BED_CAP,K$4>MESCLUN_BED_CAP,$A14+$B14+K$4>TOTAL_BEDS_AVAILABLE,($D14+K$5)>TOTAL_LABOR_HOURS_CAP,MAX(0,($D14+K$5)-PERMANENT_FIELD_LABOR_HOURS)>TEMP_HOURS_CAP),"",$C14+K$6-MIN(($D14+K$5),PERMANENT_FIELD_LABOR_HOURS)*PERMANENT_HOURLY_RATE-MAX(0,($D14+K$5)-PERMANENT_FIELD_LABOR_HOURS)*TEMP_HOURLY_RATE-FIXED_SEASON_COST) -> -16533.331 | L14: =IF(OR($A14>TOMATO_BED_CAP,$B14>CARROT_BED_CAP,L$4>MESCLUN_BED_CAP,$A14+$B14+L$4>TOTAL_BEDS_AVAILABLE,($D14+L$5)>TOTAL_LABOR_HOURS_CAP,MAX(0,($D14+L$5)-PERMANENT_FIELD_LABOR_HOURS)>TEMP_HOURS_CAP),"",$C14+L$6-MIN(($D14+L$5),PERMANENT_FIELD_LABOR_HOURS)*PERMANENT_HOURLY_RATE-MAX(0,($D14+L$5)-PERMANENT_FIELD_LABOR_HOURS)*TEMP_HOURLY_RATE-FIXED_SEASON_COST) -> -16500.542 | M14: =IF(OR($A14>TOMATO_BED_CAP,$B14>CARROT_BED_CAP,M$4>MESCLUN_BED_CAP,$A14+$B14+M$4>TOTAL_BEDS_AVAILABLE,($D14+M$5)>TOTAL_LABOR_HOURS_CAP,MAX(0,($D14+M$5)-PERMANENT_FIELD_LABOR_HOURS)>TEMP_HOURS_CAP),"",$C14+M$6-MIN(($D14+M$5),PERMANENT_FIELD_LABOR_HOURS)*PERMANENT_HOURLY_RATE-MAX(0,($D14+M$5)-PERMANENT_FIELD_LABOR_HOURS)*TEMP_HOURLY_RATE-FIXED_SEASON_COST) -> -16511.134 | ... AJ14: =IF(OR($A14>TOMATO_BED_CAP,$B14>CARROT_BED_CAP,AJ$4>MESCLUN_BED_CAP,$A14+$B14+AJ$4>TOTAL_BEDS_AVAILABLE,($D14+AJ$5)>TOTAL_LABOR_HOURS_CAP,MAX(0,($D14+AJ$5)-PERMANENT_FIELD_LABOR_HOURS)>TEMP_HOURS_CAP),"",$C14+AJ$6-MIN(($D14+AJ$5),PERMANENT_FIELD_LABOR_HOURS)*PERMANENT_HOURLY_RATE-MAX(0,($D14+AJ$5)-PERMANENT_FIELD_LABOR_HOURS)*TEMP_HOURLY_RATE-FIXED_SEASON_COST) -> -5617.5712 | AL14: Feasible mixes evaluated | AM14: =COUNT(ENUM_GRID) -> 9727
A15: =INT((ROW()-ROW($A$8))/(20+1)) -> 0 | B15: =MOD(ROW()-ROW($A$8),20+1) -> 7 | C15: =A15*(TOMATO_REVENUE_PER_BED-TOMATO_FERTILIZER_PER_BED)+B15*(CARROT_REVENUE_PER_BED-CARROT_FERTILIZER_PER_BED) -> 11578 | D15: =INDEX(TOMATO_SCHED_LABOR_HRS,A15+1)+INDEX(CARROT_SCHED_LABOR_HRS,B15+1) -> 249.52416 | E15: =IF(COUNT(F15:AJ15)=0,"",MAX(F15:AJ15)) -> -4672.9501 | F15: =IF(OR($A15>TOMATO_BED_CAP,$B15>CARROT_BED_CAP,F$4>MESCLUN_BED_CAP,$A15+$B15+F$4>TOTAL_BEDS_AVAILABLE,($D15+F$5)>TOTAL_LABOR_HOURS_CAP,MAX(0,($D15+F$5)-PERMANENT_FIELD_LABOR_HOURS)>TEMP_HOURS_CAP),"",$C15+F$6-MIN(($D15+F$5),PERMANENT_FIELD_LABOR_HOURS)*PERMANENT_HOURLY_RATE-MAX(0,($D15+F$5)-PERMANENT_FIELD_LABOR_HOURS)*TEMP_HOURLY_RATE-FIXED_SEASON_COST) -> -17085.479 | G15: =IF(OR($A15>TOMATO_BED_CAP,$B15>CARROT_BED_CAP,G$4>MESCLUN_BED_CAP,$A15+$B15+G$4>TOTAL_BEDS_AVAILABLE,($D15+G$5)>TOTAL_LABOR_HOURS_CAP,MAX(0,($D15+G$5)-PERMANENT_FIELD_LABOR_HOURS)>TEMP_HOURS_CAP),"",$C15+G$6-MIN(($D15+G$5),PERMANENT_FIELD_LABOR_HOURS)*PERMANENT_HOURLY_RATE-MAX(0,($D15+G$5)-PERMANENT_FIELD_LABOR_HOURS)*TEMP_HOURLY_RATE-FIXED_SEASON_COST) -> -16847.409 | H15: =IF(OR($A15>TOMATO_BED_CAP,$B15>CARROT_BED_CAP,H$4>MESCLUN_BED_CAP,$A15+$B15+H$4>TOTAL_BEDS_AVAILABLE,($D15+H$5)>TOTAL_LABOR_HOURS_CAP,MAX(0,($D15+H$5)-PERMANENT_FIELD_LABOR_HOURS)>TEMP_HOURS_CAP),"",$C15+H$6-MIN(($D15+H$5),PERMANENT_FIELD_LABOR_HOURS)*PERMANENT_HOURLY_RATE-MAX(0,($D15+H$5)-PERMANENT_FIELD_LABOR_HOURS)*TEMP_HOURLY_RATE-FIXED_SEASON_COST) -> -16648.887 | I15: =IF(OR($A15>TOMATO_BED_CAP,$B15>CARROT_BED_CAP,I$4>MESCLUN_BED_CAP,$A15+$B15+I$4>TOTAL_BEDS_AVAILABLE,($D15+I$5)>TOTAL_LABOR_HOURS_CAP,MAX(0,($D15+I$5)-PERMANENT_FIELD_LABOR_HOURS)>TEMP_HOURS_CAP),"",$C15+I$6-MIN(($D15+I$5),PERMANENT_FIELD_LABOR_HOURS)*PERMANENT_HOURLY_RATE-MAX(0,($D15+I$5)-PERMANENT_FIELD_LABOR_HOURS)*TEMP_HOURLY_RATE-FIXED_SEASON_COST) -> -16490.655 | J15: =IF(OR($A15>TOMATO_BED_CAP,$B15>CARROT_BED_CAP,J$4>MESCLUN_BED_CAP,$A15+$B15+J$4>TOTAL_BEDS_AVAILABLE,($D15+J$5)>TOTAL_LABOR_HOURS_CAP,MAX(0,($D15+J$5)-PERMANENT_FIELD_LABOR_HOURS)>TEMP_HOURS_CAP),"",$C15+J$6-MIN(($D15+J$5),PERMANENT_FIELD_LABOR_HOURS)*PERMANENT_HOURLY_RATE-MAX(0,($D15+J$5)-PERMANENT_FIELD_LABOR_HOURS)*TEMP_HOURLY_RATE-FIXED_SEASON_COST) -> -16373.467 | K15: =IF(OR($A15>TOMATO_BED_CAP,$B15>CARROT_BED_CAP,K$4>MESCLUN_BED_CAP,$A15+$B15+K$4>TOTAL_BEDS_AVAILABLE,($D15+K$5)>TOTAL_LABOR_HOURS_CAP,MAX(0,($D15+K$5)-PERMANENT_FIELD_LABOR_HOURS)>TEMP_HOURS_CAP),"",$C15+K$6-MIN(($D15+K$5),PERMANENT_FIELD_LABOR_HOURS)*PERMANENT_HOURLY_RATE-MAX(0,($D15+K$5)-PERMANENT_FIELD_LABOR_HOURS)*TEMP_HOURLY_RATE-FIXED_SEASON_COST) -> -16298.089 | L15: =IF(OR($A15>TOMATO_BED_CAP,$B15>CARROT_BED_CAP,L$4>MESCLUN_BED_CAP,$A15+$B15+L$4>TOTAL_BEDS_AVAILABLE,($D15+L$5)>TOTAL_LABOR_HOURS_CAP,MAX(0,($D15+L$5)-PERMANENT_FIELD_LABOR_HOURS)>TEMP_HOURS_CAP),"",$C15+L$6-MIN(($D15+L$5),PERMANENT_FIELD_LABOR_HOURS)*PERMANENT_HOURLY_RATE-MAX(0,($D15+L$5)-PERMANENT_FIELD_LABOR_HOURS)*TEMP_HOURLY_RATE-FIXED_SEASON_COST) -> -16265.3 | M15: =IF(OR($A15>TOMATO_BED_CAP,$B15>CARROT_BED_CAP,M$4>MESCLUN_BED_CAP,$A15+$B15+M$4>TOTAL_BEDS_AVAILABLE,($D15+M$5)>TOTAL_LABOR_HOURS_CAP,MAX(0,($D15+M$5)-PERMANENT_FIELD_LABOR_HOURS)>TEMP_HOURS_CAP),"",$C15+M$6-MIN(($D15+M$5),PERMANENT_FIELD_LABOR_HOURS)*PERMANENT_HOURLY_RATE-MAX(0,($D15+M$5)-PERMANENT_FIELD_LABOR_HOURS)*TEMP_HOURLY_RATE-FIXED_SEASON_COST) -> -16275.892 | ... AJ15: =IF(OR($A15>TOMATO_BED_CAP,$B15>CARROT_BED_CAP,AJ$4>MESCLUN_BED_CAP,$A15+$B15+AJ$4>TOTAL_BEDS_AVAILABLE,($D15+AJ$5)>TOTAL_LABOR_HOURS_CAP,MAX(0,($D15+AJ$5)-PERMANENT_FIELD_LABOR_HOURS)>TEMP_HOURS_CAP),"",$C15+AJ$6-MIN(($D15+AJ$5),PERMANENT_FIELD_LABOR_HOURS)*PERMANENT_HOURLY_RATE-MAX(0,($D15+AJ$5)-PERMANENT_FIELD_LABOR_HOURS)*TEMP_HOURLY_RATE-FIXED_SEASON_COST) -> -4672.9501 | AL15: Total mixes in grid | AM15: =ROWS(ENUM_GRID)*COLUMNS(ENUM_GRID) -> 13671
A16: =INT((ROW()-ROW($A$8))/(20+1)) -> 0 | B16: =MOD(ROW()-ROW($A$8),20+1) -> 8 | C16: =A16*(TOMATO_REVENUE_PER_BED-TOMATO_FERTILIZER_PER_BED)+B16*(CARROT_REVENUE_PER_BED-CARROT_FERTILIZER_PER_BED) -> 13232 | D16: =INDEX(TOMATO_SCHED_LABOR_HRS,A16+1)+INDEX(CARROT_SCHED_LABOR_HRS,B16+1) -> 292.29973 | E16: =IF(COUNT(F16:AJ16)=0,"",MAX(F16:AJ16)) -> -3761.534 | F16: =IF(OR($A16>TOMATO_BED_CAP,$B16>CARROT_BED_CAP,F$4>MESCLUN_BED_CAP,$A16+$B16+F$4>TOTAL_BEDS_AVAILABLE,($D16+F$5)>TOTAL_LABOR_HOURS_CAP,MAX(0,($D16+F$5)-PERMANENT_FIELD_LABOR_HOURS)>TEMP_HOURS_CAP),"",$C16+F$6-MIN(($D16+F$5),PERMANENT_FIELD_LABOR_HOURS)*PERMANENT_HOURLY_RATE-MAX(0,($D16+F$5)-PERMANENT_FIELD_LABOR_HOURS)*TEMP_HOURLY_RATE-FIXED_SEASON_COST) -> -16916.647 | G16: =IF(OR($A16>TOMATO_BED_CAP,$B16>CARROT_BED_CAP,G$4>MESCLUN_BED_CAP,$A16+$B16+G$4>TOTAL_BEDS_AVAILABLE,($D16+G$5)>TOTAL_LABOR_HOURS_CAP,MAX(0,($D16+G$5)-PERMANENT_FIELD_LABOR_HOURS)>TEMP_HOURS_CAP),"",$C16+G$6-MIN(($D16+G$5),PERMANENT_FIELD_LABOR_HOURS)*PERMANENT_HOURLY_RATE-MAX(0,($D16+G$5)-PERMANENT_FIELD_LABOR_HOURS)*TEMP_HOURLY_RATE-FIXED_SEASON_COST) -> -16678.577 | H16: =IF(OR($A16>TOMATO_BED_CAP,$B16>CARROT_BED_CAP,H$4>MESCLUN_BED_CAP,$A16+$B16+H$4>TOTAL_BEDS_AVAILABLE,($D16+H$5)>TOTAL_LABOR_HOURS_CAP,MAX(0,($D16+H$5)-PERMANENT_FIELD_LABOR_HOURS)>TEMP_HOURS_CAP),"",$C16+H$6-MIN(($D16+H$5),PERMANENT_FIELD_LABOR_HOURS)*PERMANENT_HOURLY_RATE-MAX(0,($D16+H$5)-PERMANENT_FIELD_LABOR_HOURS)*TEMP_HOURLY_RATE-FIXED_SEASON_COST) -> -16480.055 | I16: =IF(OR($A16>TOMATO_BED_CAP,$B16>CARROT_BED_CAP,I$4>MESCLUN_BED_CAP,$A16+$B16+I$4>TOTAL_BEDS_AVAILABLE,($D16+I$5)>TOTAL_LABOR_HOURS_CAP,MAX(0,($D16+I$5)-PERMANENT_FIELD_LABOR_HOURS)>TEMP_HOURS_CAP),"",$C16+I$6-MIN(($D16+I$5),PERMANENT_FIELD_LABOR_HOURS)*PERMANENT_HOURLY_RATE-MAX(0,($D16+I$5)-PERMANENT_FIELD_LABOR_HOURS)*TEMP_HOURLY_RATE-FIXED_SEASON_COST) -> -16321.823 | J16: =IF(OR($A16>TOMATO_BED_CAP,$B16>CARROT_BED_CAP,J$4>MESCLUN_BED_CAP,$A16+$B16+J$4>TOTAL_BEDS_AVAILABLE,($D16+J$5)>TOTAL_LABOR_HOURS_CAP,MAX(0,($D16+J$5)-PERMANENT_FIELD_LABOR_HOURS)>TEMP_HOURS_CAP),"",$C16+J$6-MIN(($D16+J$5),PERMANENT_FIELD_LABOR_HOURS)*PERMANENT_HOURLY_RATE-MAX(0,($D16+J$5)-PERMANENT_FIELD_LABOR_HOURS)*TEMP_HOURLY_RATE-FIXED_SEASON_COST) -> -16204.635 | K16: =IF(OR($A16>TOMATO_BED_CAP,$B16>CARROT_BED_CAP,K$4>MESCLUN_BED_CAP,$A16+$B16+K$4>TOTAL_BEDS_AVAILABLE,($D16+K$5)>TOTAL_LABOR_HOURS_CAP,MAX(0,($D16+K$5)-PERMANENT_FIELD_LABOR_HOURS)>TEMP_HOURS_CAP),"",$C16+K$6-MIN(($D16+K$5),PERMANENT_FIELD_LABOR_HOURS)*PERMANENT_HOURLY_RATE-MAX(0,($D16+K$5)-PERMANENT_FIELD_LABOR_HOURS)*TEMP_HOURLY_RATE-FIXED_SEASON_COST) -> -16129.256 | L16: =IF(OR($A16>TOMATO_BED_CAP,$B16>CARROT_BED_CAP,L$4>MESCLUN_BED_CAP,$A16+$B16+L$4>TOTAL_BEDS_AVAILABLE,($D16+L$5)>TOTAL_LABOR_HOURS_CAP,MAX(0,($D16+L$5)-PERMANENT_FIELD_LABOR_HOURS)>TEMP_HOURS_CAP),"",$C16+L$6-MIN(($D16+L$5),PERMANENT_FIELD_LABOR_HOURS)*PERMANENT_HOURLY_RATE-MAX(0,($D16+L$5)-PERMANENT_FIELD_LABOR_HOURS)*TEMP_HOURLY_RATE-FIXED_SEASON_COST) -> -16096.467 | M16: =IF(OR($A16>TOMATO_BED_CAP,$B16>CARROT_BED_CAP,M$4>MESCLUN_BED_CAP,$A16+$B16+M$4>TOTAL_BEDS_AVAILABLE,($D16+M$5)>TOTAL_LABOR_HOURS_CAP,MAX(0,($D16+M$5)-PERMANENT_FIELD_LABOR_HOURS)>TEMP_HOURS_CAP),"",$C16+M$6-MIN(($D16+M$5),PERMANENT_FIELD_LABOR_HOURS)*PERMANENT_HOURLY_RATE-MAX(0,($D16+M$5)-PERMANENT_FIELD_LABOR_HOURS)*TEMP_HOURLY_RATE-FIXED_SEASON_COST) -> -16107.06 | ... AJ16: =IF(OR($A16>TOMATO_BED_CAP,$B16>CARROT_BED_CAP,AJ$4>MESCLUN_BED_CAP,$A16+$B16+AJ$4>TOTAL_BEDS_AVAILABLE,($D16+AJ$5)>TOTAL_LABOR_HOURS_CAP,MAX(0,($D16+AJ$5)-PERMANENT_FIELD_LABOR_HOURS)>TEMP_HOURS_CAP),"",$C16+AJ$6-MIN(($D16+AJ$5),PERMANENT_FIELD_LABOR_HOURS)*PERMANENT_HOURLY_RATE-MAX(0,($D16+AJ$5)-PERMANENT_FIELD_LABOR_HOURS)*TEMP_HOURLY_RATE-FIXED_SEASON_COST) -> -3761.534
A17: =INT((ROW()-ROW($A$8))/(20+1)) -> 0 | B17: =MOD(ROW()-ROW($A$8),20+1) -> 9 | C17: =A17*(TOMATO_REVENUE_PER_BED-TOMATO_FERTILIZER_PER_BED)+B17*(CARROT_REVENUE_PER_BED-CARROT_FERTILIZER_PER_BED) -> 14886 | D17: =INDEX(TOMATO_SCHED_LABOR_HRS,A17+1)+INDEX(CARROT_SCHED_LABOR_HRS,B17+1) -> 337.05812 | E17: =IF(COUNT(F17:AJ17)=0,"",MAX(F17:AJ17)) -> -2884.5397 | F17: =IF(OR($A17>TOMATO_BED_CAP,$B17>CARROT_BED_CAP,F$4>MESCLUN_BED_CAP,$A17+$B17+F$4>TOTAL_BEDS_AVAILABLE,($D17+F$5)>TOTAL_LABOR_HOURS_CAP,MAX(0,($D17+F$5)-PERMANENT_FIELD_LABOR_HOURS)>TEMP_HOURS_CAP),"",$C17+F$6-MIN(($D17+F$5),PERMANENT_FIELD_LABOR_HOURS)*PERMANENT_HOURLY_RATE-MAX(0,($D17+F$5)-PERMANENT_FIELD_LABOR_HOURS)*TEMP_HOURLY_RATE-FIXED_SEASON_COST) -> -16816.658 | G17: =IF(OR($A17>TOMATO_BED_CAP,$B17>CARROT_BED_CAP,G$4>MESCLUN_BED_CAP,$A17+$B17+G$4>TOTAL_BEDS_AVAILABLE,($D17+G$5)>TOTAL_LABOR_HOURS_CAP,MAX(0,($D17+G$5)-PERMANENT_FIELD_LABOR_HOURS)>TEMP_HOURS_CAP),"",$C17+G$6-MIN(($D17+G$5),PERMANENT_FIELD_LABOR_HOURS)*PERMANENT_HOURLY_RATE-MAX(0,($D17+G$5)-PERMANENT_FIELD_LABOR_HOURS)*TEMP_HOURLY_RATE-FIXED_SEASON_COST) -> -16578.588 | H17: =IF(OR($A17>TOMATO_BED_CAP,$B17>CARROT_BED_CAP,H$4>MESCLUN_BED_CAP,$A17+$B17+H$4>TOTAL_BEDS_AVAILABLE,($D17+H$5)>TOTAL_LABOR_HOURS_CAP,MAX(0,($D17+H$5)-PERMANENT_FIELD_LABOR_HOURS)>TEMP_HOURS_CAP),"",$C17+H$6-MIN(($D17+H$5),PERMANENT_FIELD_LABOR_HOURS)*PERMANENT_HOURLY_RATE-MAX(0,($D17+H$5)-PERMANENT_FIELD_LABOR_HOURS)*TEMP_HOURLY_RATE-FIXED_SEASON_COST) -> -16380.066 | I17: =IF(OR($A17>TOMATO_BED_CAP,$B17>CARROT_BED_CAP,I$4>MESCLUN_BED_CAP,$A17+$B17+I$4>TOTAL_BEDS_AVAILABLE,($D17+I$5)>TOTAL_LABOR_HOURS_CAP,MAX(0,($D17+I$5)-PERMANENT_FIELD_LABOR_HOURS)>TEMP_HOURS_CAP),"",$C17+I$6-MIN(($D17+I$5),PERMANENT_FIELD_LABOR_HOURS)*PERMANENT_HOURLY_RATE-MAX(0,($D17+I$5)-PERMANENT_FIELD_LABOR_HOURS)*TEMP_HOURLY_RATE-FIXED_SEASON_COST) -> -16221.834 | J17: =IF(OR($A17>TOMATO_BED_CAP,$B17>CARROT_BED_CAP,J$4>MESCLUN_BED_CAP,$A17+$B17+J$4>TOTAL_BEDS_AVAILABLE,($D17+J$5)>TOTAL_LABOR_HOURS_CAP,MAX(0,($D17+J$5)-PERMANENT_FIELD_LABOR_HOURS)>TEMP_HOURS_CAP),"",$C17+J$6-MIN(($D17+J$5),PERMANENT_FIELD_LABOR_HOURS)*PERMANENT_HOURLY_RATE-MAX(0,($D17+J$5)-PERMANENT_FIELD_LABOR_HOURS)*TEMP_HOURLY_RATE-FIXED_SEASON_COST) -> -16104.646 | K17: =IF(OR($A17>TOMATO_BED_CAP,$B17>CARROT_BED_CAP,K$4>MESCLUN_BED_CAP,$A17+$B17+K$4>TOTAL_BEDS_AVAILABLE,($D17+K$5)>TOTAL_LABOR_HOURS_CAP,MAX(0,($D17+K$5)-PERMANENT_FIELD_LABOR_HOURS)>TEMP_HOURS_CAP),"",$C17+K$6-MIN(($D17+K$5),PERMANENT_FIELD_LABOR_HOURS)*PERMANENT_HOURLY_RATE-MAX(0,($D17+K$5)-PERMANENT_FIELD_LABOR_HOURS)*TEMP_HOURLY_RATE-FIXED_SEASON_COST) -> -16029.268 | L17: =IF(OR($A17>TOMATO_BED_CAP,$B17>CARROT_BED_CAP,L$4>MESCLUN_BED_CAP,$A17+$B17+L$4>TOTAL_BEDS_AVAILABLE,($D17+L$5)>TOTAL_LABOR_HOURS_CAP,MAX(0,($D17+L$5)-PERMANENT_FIELD_LABOR_HOURS)>TEMP_HOURS_CAP),"",$C17+L$6-MIN(($D17+L$5),PERMANENT_FIELD_LABOR_HOURS)*PERMANENT_HOURLY_RATE-MAX(0,($D17+L$5)-PERMANENT_FIELD_LABOR_HOURS)*TEMP_HOURLY_RATE-FIXED_SEASON_COST) -> -15996.479 | M17: =IF(OR($A17>TOMATO_BED_CAP,$B17>CARROT_BED_CAP,M$4>MESCLUN_BED_CAP,$A17+$B17+M$4>TOTAL_BEDS_AVAILABLE,($D17+M$5)>TOTAL_LABOR_HOURS_CAP,MAX(0,($D17+M$5)-PERMANENT_FIELD_LABOR_HOURS)>TEMP_HOURS_CAP),"",$C17+M$6-MIN(($D17+M$5),PERMANENT_FIELD_LABOR_HOURS)*PERMANENT_HOURLY_RATE-MAX(0,($D17+M$5)-PERMANENT_FIELD_LABOR_HOURS)*TEMP_HOURLY_RATE-FIXED_SEASON_COST) -> -16007.072 | ... AJ17: =IF(OR($A17>TOMATO_BED_CAP,$B17>CARROT_BED_CAP,AJ$4>MESCLUN_BED_CAP,$A17+$B17+AJ$4>TOTAL_BEDS_AVAILABLE,($D17+AJ$5)>TOTAL_LABOR_HOURS_CAP,MAX(0,($D17+AJ$5)-PERMANENT_FIELD_LABOR_HOURS)>TEMP_HOURS_CAP),"",$C17+AJ$6-MIN(($D17+AJ$5),PERMANENT_FIELD_LABOR_HOURS)*PERMANENT_HOURLY_RATE-MAX(0,($D17+AJ$5)-PERMANENT_FIELD_LABOR_HOURS)*TEMP_HOURLY_RATE-FIXED_SEASON_COST) -> -2884.5397
A18: =INT((ROW()-ROW($A$8))/(20+1)) -> 0 | B18: =MOD(ROW()-ROW($A$8),20+1) -> 10 | C18: =A18*(TOMATO_REVENUE_PER_BED-TOMATO_FERTILIZER_PER_BED)+B18*(CARROT_REVENUE_PER_BED-CARROT_FERTILIZER_PER_BED) -> 16540 | D18: =INDEX(TOMATO_SCHED_LABOR_HRS,A18+1)+INDEX(CARROT_SCHED_LABOR_HRS,B18+1) -> 383.87175 | E18: =IF(COUNT(F18:AJ18)=0,"",MAX(F18:AJ18)) -> -2043.2243 | F18: =IF(OR($A18>TOMATO_BED_CAP,$B18>CARROT_BED_CAP,F$4>MESCLUN_BED_CAP,$A18+$B18+F$4>TOTAL_BEDS_AVAILABLE,($D18+F$5)>TOTAL_LABOR_HOURS_CAP,MAX(0,($D18+F$5)-PERMANENT_FIELD_LABOR_HOURS)>TEMP_HOURS_CAP),"",$C18+F$6-MIN(($D18+F$5),PERMANENT_FIELD_LABOR_HOURS)*PERMANENT_HOURLY_RATE-MAX(0,($D18+F$5)-PERMANENT_FIELD_LABOR_HOURS)*TEMP_HOURLY_RATE-FIXED_SEASON_COST) -> -16788.027 | G18: =IF(OR($A18>TOMATO_BED_CAP,$B18>CARROT_BED_CAP,G$4>MESCLUN_BED_CAP,$A18+$B18+G$4>TOTAL_BEDS_AVAILABLE,($D18+G$5)>TOTAL_LABOR_HOURS_CAP,MAX(0,($D18+G$5)-PERMANENT_FIELD_LABOR_HOURS)>TEMP_HOURS_CAP),"",$C18+G$6-MIN(($D18+G$5),PERMANENT_FIELD_LABOR_HOURS)*PERMANENT_HOURLY_RATE-MAX(0,($D18+G$5)-PERMANENT_FIELD_LABOR_HOURS)*TEMP_HOURLY_RATE-FIXED_SEASON_COST) -> -16549.957 | H18: =IF(OR($A18>TOMATO_BED_CAP,$B18>CARROT_BED_CAP,H$4>MESCLUN_BED_CAP,$A18+$B18+H$4>TOTAL_BEDS_AVAILABLE,($D18+H$5)>TOTAL_LABOR_HOURS_CAP,MAX(0,($D18+H$5)-PERMANENT_FIELD_LABOR_HOURS)>TEMP_HOURS_CAP),"",$C18+H$6-MIN(($D18+H$5),PERMANENT_FIELD_LABOR_HOURS)*PERMANENT_HOURLY_RATE-MAX(0,($D18+H$5)-PERMANENT_FIELD_LABOR_HOURS)*TEMP_HOURLY_RATE-FIXED_SEASON_COST) -> -16351.436 | I18: =IF(OR($A18>TOMATO_BED_CAP,$B18>CARROT_BED_CAP,I$4>MESCLUN_BED_CAP,$A18+$B18+I$4>TOTAL_BEDS_AVAILABLE,($D18+I$5)>TOTAL_LABOR_HOURS_CAP,MAX(0,($D18+I$5)-PERMANENT_FIELD_LABOR_HOURS)>TEMP_HOURS_CAP),"",$C18+I$6-MIN(($D18+I$5),PERMANENT_FIELD_LABOR_HOURS)*PERMANENT_HOURLY_RATE-MAX(0,($D18+I$5)-PERMANENT_FIELD_LABOR_HOURS)*TEMP_HOURLY_RATE-FIXED_SEASON_COST) -> -16193.204 | J18: =IF(OR($A18>TOMATO_BED_CAP,$B18>CARROT_BED_CAP,J$4>MESCLUN_BED_CAP,$A18+$B18+J$4>TOTAL_BEDS_AVAILABLE,($D18+J$5)>TOTAL_LABOR_HOURS_CAP,MAX(0,($D18+J$5)-PERMANENT_FIELD_LABOR_HOURS)>TEMP_HOURS_CAP),"",$C18+J$6-MIN(($D18+J$5),PERMANENT_FIELD_LABOR_HOURS)*PERMANENT_HOURLY_RATE-MAX(0,($D18+J$5)-PERMANENT_FIELD_LABOR_HOURS)*TEMP_HOURLY_RATE-FIXED_SEASON_COST) -> -16076.015 | K18: =IF(OR($A18>TOMATO_BED_CAP,$B18>CARROT_BED_CAP,K$4>MESCLUN_BED_CAP,$A18+$B18+K$4>TOTAL_BEDS_AVAILABLE,($D18+K$5)>TOTAL_LABOR_HOURS_CAP,MAX(0,($D18+K$5)-PERMANENT_FIELD_LABOR_HOURS)>TEMP_HOURS_CAP),"",$C18+K$6-MIN(($D18+K$5),PERMANENT_FIELD_LABOR_HOURS)*PERMANENT_HOURLY_RATE-MAX(0,($D18+K$5)-PERMANENT_FIELD_LABOR_HOURS)*TEMP_HOURLY_RATE-FIXED_SEASON_COST) -> -16000.637 | L18: =IF(OR($A18>TOMATO_BED_CAP,$B18>CARROT_BED_CAP,L$4>MESCLUN_BED_CAP,$A18+$B18+L$4>TOTAL_BEDS_AVAILABLE,($D18+L$5)>TOTAL_LABOR_HOURS_CAP,MAX(0,($D18+L$5)-PERMANENT_FIELD_LABOR_HOURS)>TEMP_HOURS_CAP),"",$C18+L$6-MIN(($D18+L$5),PERMANENT_FIELD_LABOR_HOURS)*PERMANENT_HOURLY_RATE-MAX(0,($D18+L$5)-PERMANENT_FIELD_LABOR_HOURS)*TEMP_HOURLY_RATE-FIXED_SEASON_COST) -> -15967.848 | M18: =IF(OR($A18>TOMATO_BED_CAP,$B18>CARROT_BED_CAP,M$4>MESCLUN_BED_CAP,$A18+$B18+M$4>TOTAL_BEDS_AVAILABLE,($D18+M$5)>TOTAL_LABOR_HOURS_CAP,MAX(0,($D18+M$5)-PERMANENT_FIELD_LABOR_HOURS)>TEMP_HOURS_CAP),"",$C18+M$6-MIN(($D18+M$5),PERMANENT_FIELD_LABOR_HOURS)*PERMANENT_HOURLY_RATE-MAX(0,($D18+M$5)-PERMANENT_FIELD_LABOR_HOURS)*TEMP_HOURLY_RATE-FIXED_SEASON_COST) -> -15848.42 | ... AJ18: =IF(OR($A18>TOMATO_BED_CAP,$B18>CARROT_BED_CAP,AJ$4>MESCLUN_BED_CAP,$A18+$B18+AJ$4>TOTAL_BEDS_AVAILABLE,($D18+AJ$5)>TOTAL_LABOR_HOURS_CAP,MAX(0,($D18+AJ$5)-PERMANENT_FIELD_LABOR_HOURS)>TEMP_HOURS_CAP),"",$C18+AJ$6-MIN(($D18+AJ$5),PERMANENT_FIELD_LABOR_HOURS)*PERMANENT_HOURLY_RATE-MAX(0,($D18+AJ$5)-PERMANENT_FIELD_LABOR_HOURS)*TEMP_HOURLY_RATE-FIXED_SEASON_COST) -> -2043.2243
A19: =INT((ROW()-ROW($A$8))/(20+1)) -> 0 | B19: =MOD(ROW()-ROW($A$8),20+1) -> 11 | C19: =A19*(TOMATO_REVENUE_PER_BED-TOMATO_FERTILIZER_PER_BED)+B19*(CARROT_REVENUE_PER_BED-CARROT_FERTILIZER_PER_BED) -> 18194 | D19: =INDEX(TOMATO_SCHED_LABOR_HRS,A19+1)+INDEX(CARROT_SCHED_LABOR_HRS,B19+1) -> 432.8154 | E19: =IF(COUNT(F19:AJ19)=0,"",MAX(F19:AJ19)) -> -1238.8861 | F19: =IF(OR($A19>TOMATO_BED_CAP,$B19>CARROT_BED_CAP,F$4>MESCLUN_BED_CAP,$A19+$B19+F$4>TOTAL_BEDS_AVAILABLE,($D19+F$5)>TOTAL_LABOR_HOURS_CAP,MAX(0,($D19+F$5)-PERMANENT_FIELD_LABOR_HOURS)>TEMP_HOURS_CAP),"",$C19+F$6-MIN(($D19+F$5),PERMANENT_FIELD_LABOR_HOURS)*PERMANENT_HOURLY_RATE-MAX(0,($D19+F$5)-PERMANENT_FIELD_LABOR_HOURS)*TEMP_HOURLY_RATE-FIXED_SEASON_COST) -> -16833.351 | G19: =IF(OR($A19>TOMATO_BED_CAP,$B19>CARROT_BED_CAP,G$4>MESCLUN_BED_CAP,$A19+$B19+G$4>TOTAL_BEDS_AVAILABLE,($D19+G$5)>TOTAL_LABOR_HOURS_CAP,MAX(0,($D19+G$5)-PERMANENT_FIELD_LABOR_HOURS)>TEMP_HOURS_CAP),"",$C19+G$6-MIN(($D19+G$5),PERMANENT_FIELD_LABOR_HOURS)*PERMANENT_HOURLY_RATE-MAX(0,($D19+G$5)-PERMANENT_FIELD_LABOR_HOURS)*TEMP_HOURLY_RATE-FIXED_SEASON_COST) -> -16595.281 | H19: =IF(OR($A19>TOMATO_BED_CAP,$B19>CARROT_BED_CAP,H$4>MESCLUN_BED_CAP,$A19+$B19+H$4>TOTAL_BEDS_AVAILABLE,($D19+H$5)>TOTAL_LABOR_HOURS_CAP,MAX(0,($D19+H$5)-PERMANENT_FIELD_LABOR_HOURS)>TEMP_HOURS_CAP),"",$C19+H$6-MIN(($D19+H$5),PERMANENT_FIELD_LABOR_HOURS)*PERMANENT_HOURLY_RATE-MAX(0,($D19+H$5)-PERMANENT_FIELD_LABOR_HOURS)*TEMP_HOURLY_RATE-FIXED_SEASON_COST) -> -16396.759 | I19: =IF(OR($A19>TOMATO_BED_CAP,$B19>CARROT_BED_CAP,I$4>MESCLUN_BED_CAP,$A19+$B19+I$4>TOTAL_BEDS_AVAILABLE,($D19+I$5)>TOTAL_LABOR_HOURS_CAP,MAX(0,($D19+I$5)-PERMANENT_FIELD_LABOR_HOURS)>TEMP_HOURS_CAP),"",$C19+I$6-MIN(($D19+I$5),PERMANENT_FIELD_LABOR_HOURS)*PERMANENT_HOURLY_RATE-MAX(0,($D19+I$5)-PERMANENT_FIELD_LABOR_HOURS)*TEMP_HOURLY_RATE-FIXED_SEASON_COST) -> -16238.527 | J19: =IF(OR($A19>TOMATO_BED_CAP,$B19>CARROT_BED_CAP,J$4>MESCLUN_BED_CAP,$A19+$B19+J$4>TOTAL_BEDS_AVAILABLE,($D19+J$5)>TOTAL_LABOR_HOURS_CAP,MAX(0,($D19+J$5)-PERMANENT_FIELD_LABOR_HOURS)>TEMP_HOURS_CAP),"",$C19+J$6-MIN(($D19+J$5),PERMANENT_FIELD_LABOR_HOURS)*PERMANENT_HOURLY_RATE-MAX(0,($D19+J$5)-PERMANENT_FIELD_LABOR_HOURS)*TEMP_HOURLY_RATE-FIXED_SEASON_COST) -> -16121.339 | K19: =IF(OR($A19>TOMATO_BED_CAP,$B19>CARROT_BED_CAP,K$4>MESCLUN_BED_CAP,$A19+$B19+K$4>TOTAL_BEDS_AVAILABLE,($D19+K$5)>TOTAL_LABOR_HOURS_CAP,MAX(0,($D19+K$5)-PERMANENT_FIELD_LABOR_HOURS)>TEMP_HOURS_CAP),"",$C19+K$6-MIN(($D19+K$5),PERMANENT_FIELD_LABOR_HOURS)*PERMANENT_HOURLY_RATE-MAX(0,($D19+K$5)-PERMANENT_FIELD_LABOR_HOURS)*TEMP_HOURLY_RATE-FIXED_SEASON_COST) -> -16045.961 | L19: =IF(OR($A19>TOMATO_BED_CAP,$B19>CARROT_BED_CAP,L$4>MESCLUN_BED_CAP,$A19+$B19+L$4>TOTAL_BEDS_AVAILABLE,($D19+L$5)>TOTAL_LABOR_HOURS_CAP,MAX(0,($D19+L$5)-PERMANENT_FIELD_LABOR_HOURS)>TEMP_HOURS_CAP),"",$C19+L$6-MIN(($D19+L$5),PERMANENT_FIELD_LABOR_HOURS)*PERMANENT_HOURLY_RATE-MAX(0,($D19+L$5)-PERMANENT_FIELD_LABOR_HOURS)*TEMP_HOURLY_RATE-FIXED_SEASON_COST) -> -15948.786 | M19: =IF(OR($A19>TOMATO_BED_CAP,$B19>CARROT_BED_CAP,M$4>MESCLUN_BED_CAP,$A19+$B19+M$4>TOTAL_BEDS_AVAILABLE,($D19+M$5)>TOTAL_LABOR_HOURS_CAP,MAX(0,($D19+M$5)-PERMANENT_FIELD_LABOR_HOURS)>TEMP_HOURS_CAP),"",$C19+M$6-MIN(($D19+M$5),PERMANENT_FIELD_LABOR_HOURS)*PERMANENT_HOURLY_RATE-MAX(0,($D19+M$5)-PERMANENT_FIELD_LABOR_HOURS)*TEMP_HOURLY_RATE-FIXED_SEASON_COST) -> -15044.082 | ... AJ19: =IF(OR($A19>TOMATO_BED_CAP,$B19>CARROT_BED_CAP,AJ$4>MESCLUN_BED_CAP,$A19+$B19+AJ$4>TOTAL_BEDS_AVAILABLE,($D19+AJ$5)>TOTAL_LABOR_HOURS_CAP,MAX(0,($D19+AJ$5)-PERMANENT_FIELD_LABOR_HOURS)>TEMP_HOURS_CAP),"",$C19+AJ$6-MIN(($D19+AJ$5),PERMANENT_FIELD_LABOR_HOURS)*PERMANENT_HOURLY_RATE-MAX(0,($D19+AJ$5)-PERMANENT_FIELD_LABOR_HOURS)*TEMP_HOURLY_RATE-FIXED_SEASON_COST) -> -1238.8861
A20: =INT((ROW()-ROW($A$8))/(20+1)) -> 0 | B20: =MOD(ROW()-ROW($A$8),20+1) -> 12 | C20: =A20*(TOMATO_REVENUE_PER_BED-TOMATO_FERTILIZER_PER_BED)+B20*(CARROT_REVENUE_PER_BED-CARROT_FERTILIZER_PER_BED) -> 19848 | D20: =INDEX(TOMATO_SCHED_LABOR_HRS,A20+1)+INDEX(CARROT_SCHED_LABOR_HRS,B20+1) -> 483.96631 | E20: =IF(COUNT(F20:AJ20)=0,"",MAX(F20:AJ20)) -> -472.86589 | F20: =IF(OR($A20>TOMATO_BED_CAP,$B20>CARROT_BED_CAP,F$4>MESCLUN_BED_CAP,$A20+$B20+F$4>TOTAL_BEDS_AVAILABLE,($D20+F$5)>TOTAL_LABOR_HOURS_CAP,MAX(0,($D20+F$5)-PERMANENT_FIELD_LABOR_HOURS)>TEMP_HOURS_CAP),"",$C20+F$6-MIN(($D20+F$5),PERMANENT_FIELD_LABOR_HOURS)*PERMANENT_HOURLY_RATE-MAX(0,($D20+F$5)-PERMANENT_FIELD_LABOR_HOURS)*TEMP_HOURLY_RATE-FIXED_SEASON_COST) -> -16955.31 | G20: =IF(OR($A20>TOMATO_BED_CAP,$B20>CARROT_BED_CAP,G$4>MESCLUN_BED_CAP,$A20+$B20+G$4>TOTAL_BEDS_AVAILABLE,($D20+G$5)>TOTAL_LABOR_HOURS_CAP,MAX(0,($D20+G$5)-PERMANENT_FIELD_LABOR_HOURS)>TEMP_HOURS_CAP),"",$C20+G$6-MIN(($D20+G$5),PERMANENT_FIELD_LABOR_HOURS)*PERMANENT_HOURLY_RATE-MAX(0,($D20+G$5)-PERMANENT_FIELD_LABOR_HOURS)*TEMP_HOURLY_RATE-FIXED_SEASON_COST) -> -16717.24 | H20: =IF(OR($A20>TOMATO_BED_CAP,$B20>CARROT_BED_CAP,H$4>MESCLUN_BED_CAP,$A20+$B20+H$4>TOTAL_BEDS_AVAILABLE,($D20+H$5)>TOTAL_LABOR_HOURS_CAP,MAX(0,($D20+H$5)-PERMANENT_FIELD_LABOR_HOURS)>TEMP_HOURS_CAP),"",$C20+H$6-MIN(($D20+H$5),PERMANENT_FIELD_LABOR_HOURS)*PERMANENT_HOURLY_RATE-MAX(0,($D20+H$5)-PERMANENT_FIELD_LABOR_HOURS)*TEMP_HOURLY_RATE-FIXED_SEASON_COST) -> -16518.719 | I20: =IF(OR($A20>TOMATO_BED_CAP,$B20>CARROT_BED_CAP,I$4>MESCLUN_BED_CAP,$A20+$B20+I$4>TOTAL_BEDS_AVAILABLE,($D20+I$5)>TOTAL_LABOR_HOURS_CAP,MAX(0,($D20+I$5)-PERMANENT_FIELD_LABOR_HOURS)>TEMP_HOURS_CAP),"",$C20+I$6-MIN(($D20+I$5),PERMANENT_FIELD_LABOR_HOURS)*PERMANENT_HOURLY_RATE-MAX(0,($D20+I$5)-PERMANENT_FIELD_LABOR_HOURS)*TEMP_HOURLY_RATE-FIXED_SEASON_COST) -> -16360.487 | J20: =IF(OR($A20>TOMATO_BED_CAP,$B20>CARROT_BED_CAP,J$4>MESCLUN_BED_CAP,$A20+$B20+J$4>TOTAL_BEDS_AVAILABLE,($D20+J$5)>TOTAL_LABOR_HOURS_CAP,MAX(0,($D20+J$5)-PERMANENT_FIELD_LABOR_HOURS)>TEMP_HOURS_CAP),"",$C20+J$6-MIN(($D20+J$5),PERMANENT_FIELD_LABOR_HOURS)*PERMANENT_HOURLY_RATE-MAX(0,($D20+J$5)-PERMANENT_FIELD_LABOR_HOURS)*TEMP_HOURLY_RATE-FIXED_SEASON_COST) -> -16243.298 | K20: =IF(OR($A20>TOMATO_BED_CAP,$B20>CARROT_BED_CAP,K$4>MESCLUN_BED_CAP,$A20+$B20+K$4>TOTAL_BEDS_AVAILABLE,($D20+K$5)>TOTAL_LABOR_HOURS_CAP,MAX(0,($D20+K$5)-PERMANENT_FIELD_LABOR_HOURS)>TEMP_HOURS_CAP),"",$C20+K$6-MIN(($D20+K$5),PERMANENT_FIELD_LABOR_HOURS)*PERMANENT_HOURLY_RATE-MAX(0,($D20+K$5)-PERMANENT_FIELD_LABOR_HOURS)*TEMP_HOURLY_RATE-FIXED_SEASON_COST) -> -16109.16 | L20: =IF(OR($A20>TOMATO_BED_CAP,$B20>CARROT_BED_CAP,L$4>MESCLUN_BED_CAP,$A20+$B20+L$4>TOTAL_BEDS_AVAILABLE,($D20+L$5)>TOTAL_LABOR_HOURS_CAP,MAX(0,($D20+L$5)-PERMANENT_FIELD_LABOR_HOURS)>TEMP_HOURS_CAP),"",$C20+L$6-MIN(($D20+L$5),PERMANENT_FIELD_LABOR_HOURS)*PERMANENT_HOURLY_RATE-MAX(0,($D20+L$5)-PERMANENT_FIELD_LABOR_HOURS)*TEMP_HOURLY_RATE-FIXED_SEASON_COST) -> -15182.766 | M20: =IF(OR($A20>TOMATO_BED_CAP,$B20>CARROT_BED_CAP,M$4>MESCLUN_BED_CAP,$A20+$B20+M$4>TOTAL_BEDS_AVAILABLE,($D20+M$5)>TOTAL_LABOR_HOURS_CAP,MAX(0,($D20+M$5)-PERMANENT_FIELD_LABOR_HOURS)>TEMP_HOURS_CAP),"",$C20+M$6-MIN(($D20+M$5),PERMANENT_FIELD_LABOR_HOURS)*PERMANENT_HOURLY_RATE-MAX(0,($D20+M$5)-PERMANENT_FIELD_LABOR_HOURS)*TEMP_HOURLY_RATE-FIXED_SEASON_COST) -> -14278.062 | ... AJ20: =IF(OR($A20>TOMATO_BED_CAP,$B20>CARROT_BED_CAP,AJ$4>MESCLUN_BED_CAP,$A20+$B20+AJ$4>TOTAL_BEDS_AVAILABLE,($D20+AJ$5)>TOTAL_LABOR_HOURS_CAP,MAX(0,($D20+AJ$5)-PERMANENT_FIELD_LABOR_HOURS)>TEMP_HOURS_CAP),"",$C20+AJ$6-MIN(($D20+AJ$5),PERMANENT_FIELD_LABOR_HOURS)*PERMANENT_HOURLY_RATE-MAX(0,($D20+AJ$5)-PERMANENT_FIELD_LABOR_HOURS)*TEMP_HOURLY_RATE-FIXED_SEASON_COST) -> -472.86589
A21: =INT((ROW()-ROW($A$8))/(20+1)) -> 0 | B21: =MOD(ROW()-ROW($A$8),20+1) -> 13 | C21: =A21*(TOMATO_REVENUE_PER_BED-TOMATO_FERTILIZER_PER_BED)+B21*(CARROT_REVENUE_PER_BED-CARROT_FERTILIZER_PER_BED) -> 21502 | D21: =INDEX(TOMATO_SCHED_LABOR_HRS,A21+1)+INDEX(CARROT_SCHED_LABOR_HRS,B21+1) -> 537.40426 | E21: =IF(COUNT(F21:AJ21)=0,"",MAX(F21:AJ21)) -> 253.45135 | F21: =IF(OR($A21>TOMATO_BED_CAP,$B21>CARROT_BED_CAP,F$4>MESCLUN_BED_CAP,$A21+$B21+F$4>TOTAL_BEDS_AVAILABLE,($D21+F$5)>TOTAL_LABOR_HOURS_CAP,MAX(0,($D21+F$5)-PERMANENT_FIELD_LABOR_HOURS)>TEMP_HOURS_CAP),"",$C21+F$6-MIN(($D21+F$5),PERMANENT_FIELD_LABOR_HOURS)*PERMANENT_HOURLY_RATE-MAX(0,($D21+F$5)-PERMANENT_FIELD_LABOR_HOURS)*TEMP_HOURLY_RATE-FIXED_SEASON_COST) -> -17156.676 | G21: =IF(OR($A21>TOMATO_BED_CAP,$B21>CARROT_BED_CAP,G$4>MESCLUN_BED_CAP,$A21+$B21+G$4>TOTAL_BEDS_AVAILABLE,($D21+G$5)>TOTAL_LABOR_HOURS_CAP,MAX(0,($D21+G$5)-PERMANENT_FIELD_LABOR_HOURS)>TEMP_HOURS_CAP),"",$C21+G$6-MIN(($D21+G$5),PERMANENT_FIELD_LABOR_HOURS)*PERMANENT_HOURLY_RATE-MAX(0,($D21+G$5)-PERMANENT_FIELD_LABOR_HOURS)*TEMP_HOURLY_RATE-FIXED_SEASON_COST) -> -16918.606 | H21: =IF(OR($A21>TOMATO_BED_CAP,$B21>CARROT_BED_CAP,H$4>MESCLUN_BED_CAP,$A21+$B21+H$4>TOTAL_BEDS_AVAILABLE,($D21+H$5)>TOTAL_LABOR_HOURS_CAP,MAX(0,($D21+H$5)-PERMANENT_FIELD_LABOR_HOURS)>TEMP_HOURS_CAP),"",$C21+H$6-MIN(($D21+H$5),PERMANENT_FIELD_LABOR_HOURS)*PERMANENT_HOURLY_RATE-MAX(0,($D21+H$5)-PERMANENT_FIELD_LABOR_HOURS)*TEMP_HOURLY_RATE-FIXED_SEASON_COST) -> -16720.084 | I21: =IF(OR($A21>TOMATO_BED_CAP,$B21>CARROT_BED_CAP,I$4>MESCLUN_BED_CAP,$A21+$B21+I$4>TOTAL_BEDS_AVAILABLE,($D21+I$5)>TOTAL_LABOR_HOURS_CAP,MAX(0,($D21+I$5)-PERMANENT_FIELD_LABOR_HOURS)>TEMP_HOURS_CAP),"",$C21+I$6-MIN(($D21+I$5),PERMANENT_FIELD_LABOR_HOURS)*PERMANENT_HOURLY_RATE-MAX(0,($D21+I$5)-PERMANENT_FIELD_LABOR_HOURS)*TEMP_HOURLY_RATE-FIXED_SEASON_COST) -> -16561.852 | J21: =IF(OR($A21>TOMATO_BED_CAP,$B21>CARROT_BED_CAP,J$4>MESCLUN_BED_CAP,$A21+$B21+J$4>TOTAL_BEDS_AVAILABLE,($D21+J$5)>TOTAL_LABOR_HOURS_CAP,MAX(0,($D21+J$5)-PERMANENT_FIELD_LABOR_HOURS)>TEMP_HOURS_CAP),"",$C21+J$6-MIN(($D21+J$5),PERMANENT_FIELD_LABOR_HOURS)*PERMANENT_HOURLY_RATE-MAX(0,($D21+J$5)-PERMANENT_FIELD_LABOR_HOURS)*TEMP_HOURLY_RATE-FIXED_SEASON_COST) -> -16330.532 | K21: =IF(OR($A21>TOMATO_BED_CAP,$B21>CARROT_BED_CAP,K$4>MESCLUN_BED_CAP,$A21+$B21+K$4>TOTAL_BEDS_AVAILABLE,($D21+K$5)>TOTAL_LABOR_HOURS_CAP,MAX(0,($D21+K$5)-PERMANENT_FIELD_LABOR_HOURS)>TEMP_HOURS_CAP),"",$C21+K$6-MIN(($D21+K$5),PERMANENT_FIELD_LABOR_HOURS)*PERMANENT_HOURLY_RATE-MAX(0,($D21+K$5)-PERMANENT_FIELD_LABOR_HOURS)*TEMP_HOURLY_RATE-FIXED_SEASON_COST) -> -15382.843 | L21: =IF(OR($A21>TOMATO_BED_CAP,$B21>CARROT_BED_CAP,L$4>MESCLUN_BED_CAP,$A21+$B21+L$4>TOTAL_BEDS_AVAILABLE,($D21+L$5)>TOTAL_LABOR_HOURS_CAP,MAX(0,($D21+L$5)-PERMANENT_FIELD_LABOR_HOURS)>TEMP_HOURS_CAP),"",$C21+L$6-MIN(($D21+L$5),PERMANENT_FIELD_LABOR_HOURS)*PERMANENT_HOURLY_RATE-MAX(0,($D21+L$5)-PERMANENT_FIELD_LABOR_HOURS)*TEMP_HOURLY_RATE-FIXED_SEASON_COST) -> -14456.448 | M21: =IF(OR($A21>TOMATO_BED_CAP,$B21>CARROT_BED_CAP,M$4>MESCLUN_BED_CAP,$A21+$B21+M$4>TOTAL_BEDS_AVAILABLE,($D21+M$5)>TOTAL_LABOR_HOURS_CAP,MAX(0,($D21+M$5)-PERMANENT_FIELD_LABOR_HOURS)>TEMP_HOURS_CAP),"",$C21+M$6-MIN(($D21+M$5),PERMANENT_FIELD_LABOR_HOURS)*PERMANENT_HOURLY_RATE-MAX(0,($D21+M$5)-PERMANENT_FIELD_LABOR_HOURS)*TEMP_HOURLY_RATE-FIXED_SEASON_COST) -> -13551.745 | ... AJ21: =IF(OR($A21>TOMATO_BED_CAP,$B21>CARROT_BED_CAP,AJ$4>MESCLUN_BED_CAP,$A21+$B21+AJ$4>TOTAL_BEDS_AVAILABLE,($D21+AJ$5)>TOTAL_LABOR_HOURS_CAP,MAX(0,($D21+AJ$5)-PERMANENT_FIELD_LABOR_HOURS)>TEMP_HOURS_CAP),"",$C21+AJ$6-MIN(($D21+AJ$5),PERMANENT_FIELD_LABOR_HOURS)*PERMANENT_HOURLY_RATE-MAX(0,($D21+AJ$5)-PERMANENT_FIELD_LABOR_HOURS)*TEMP_HOURLY_RATE-FIXED_SEASON_COST) -> 253.45135
A22: =INT((ROW()-ROW($A$8))/(20+1)) -> 0 | B22: =MOD(ROW()-ROW($A$8),20+1) -> 14 | C22: =A22*(TOMATO_REVENUE_PER_BED-TOMATO_FERTILIZER_PER_BED)+B22*(CARROT_REVENUE_PER_BED-CARROT_FERTILIZER_PER_BED) -> 23156 | D22: =INDEX(TOMATO_SCHED_LABOR_HRS,A22+1)+INDEX(CARROT_SCHED_LABOR_HRS,B22+1) -> 593.21163 | E22: =IF(COUNT(F22:AJ22)=0,"",MAX(F22:AJ22)) -> 938.63548 | F22: =IF(OR($A22>TOMATO_BED_CAP,$B22>CARROT_BED_CAP,F$4>MESCLUN_BED_CAP,$A22+$B22+F$4>TOTAL_BEDS_AVAILABLE,($D22+F$5)>TOTAL_LABOR_HOURS_CAP,MAX(0,($D22+F$5)-PERMANENT_FIELD_LABOR_HOURS)>TEMP_HOURS_CAP),"",$C22+F$6-MIN(($D22+F$5),PERMANENT_FIELD_LABOR_HOURS)*PERMANENT_HOURLY_RATE-MAX(0,($D22+F$5)-PERMANENT_FIELD_LABOR_HOURS)*TEMP_HOURLY_RATE-FIXED_SEASON_COST) -> -17440.308 | G22: =IF(OR($A22>TOMATO_BED_CAP,$B22>CARROT_BED_CAP,G$4>MESCLUN_BED_CAP,$A22+$B22+G$4>TOTAL_BEDS_AVAILABLE,($D22+G$5)>TOTAL_LABOR_HOURS_CAP,MAX(0,($D22+G$5)-PERMANENT_FIELD_LABOR_HOURS)>TEMP_HOURS_CAP),"",$C22+G$6-MIN(($D22+G$5),PERMANENT_FIELD_LABOR_HOURS)*PERMANENT_HOURLY_RATE-MAX(0,($D22+G$5)-PERMANENT_FIELD_LABOR_HOURS)*TEMP_HOURLY_RATE-FIXED_SEASON_COST) -> -17202.238 | H22: =IF(OR($A22>TOMATO_BED_CAP,$B22>CARROT_BED_CAP,H$4>MESCLUN_BED_CAP,$A22+$B22+H$4>TOTAL_BEDS_AVAILABLE,($D22+H$5)>TOTAL_LABOR_HOURS_CAP,MAX(0,($D22+H$5)-PERMANENT_FIELD_LABOR_HOURS)>TEMP_HOURS_CAP),"",$C22+H$6-MIN(($D22+H$5),PERMANENT_FIELD_LABOR_HOURS)*PERMANENT_HOURLY_RATE-MAX(0,($D22+H$5)-PERMANENT_FIELD_LABOR_HOURS)*TEMP_HOURLY_RATE-FIXED_SEASON_COST) -> -17003.716 | I22: =IF(OR($A22>TOMATO_BED_CAP,$B22>CARROT_BED_CAP,I$4>MESCLUN_BED_CAP,$A22+$B22+I$4>TOTAL_BEDS_AVAILABLE,($D22+I$5)>TOTAL_LABOR_HOURS_CAP,MAX(0,($D22+I$5)-PERMANENT_FIELD_LABOR_HOURS)>TEMP_HOURS_CAP),"",$C22+I$6-MIN(($D22+I$5),PERMANENT_FIELD_LABOR_HOURS)*PERMANENT_HOURLY_RATE-MAX(0,($D22+I$5)-PERMANENT_FIELD_LABOR_HOURS)*TEMP_HOURLY_RATE-FIXED_SEASON_COST) -> -16613.942 | J22: =IF(OR($A22>TOMATO_BED_CAP,$B22>CARROT_BED_CAP,J$4>MESCLUN_BED_CAP,$A22+$B22+J$4>TOTAL_BEDS_AVAILABLE,($D22+J$5)>TOTAL_LABOR_HOURS_CAP,MAX(0,($D22+J$5)-PERMANENT_FIELD_LABOR_HOURS)>TEMP_HOURS_CAP),"",$C22+J$6-MIN(($D22+J$5),PERMANENT_FIELD_LABOR_HOURS)*PERMANENT_HOURLY_RATE-MAX(0,($D22+J$5)-PERMANENT_FIELD_LABOR_HOURS)*TEMP_HOURLY_RATE-FIXED_SEASON_COST) -> -15645.348 | K22: =IF(OR($A22>TOMATO_BED_CAP,$B22>CARROT_BED_CAP,K$4>MESCLUN_BED_CAP,$A22+$B22+K$4>TOTAL_BEDS_AVAILABLE,($D22+K$5)>TOTAL_LABOR_HOURS_CAP,MAX(0,($D22+K$5)-PERMANENT_FIELD_LABOR_HOURS)>TEMP_HOURS_CAP),"",$C22+K$6-MIN(($D22+K$5),PERMANENT_FIELD_LABOR_HOURS)*PERMANENT_HOURLY_RATE-MAX(0,($D22+K$5)-PERMANENT_FIELD_LABOR_HOURS)*TEMP_HOURLY_RATE-FIXED_SEASON_COST) -> -14697.659 | L22: =IF(OR($A22>TOMATO_BED_CAP,$B22>CARROT_BED_CAP,L$4>MESCLUN_BED_CAP,$A22+$B22+L$4>TOTAL_BEDS_AVAILABLE,($D22+L$5)>TOTAL_LABOR_HOURS_CAP,MAX(0,($D22+L$5)-PERMANENT_FIELD_LABOR_HOURS)>TEMP_HOURS_CAP),"",$C22+L$6-MIN(($D22+L$5),PERMANENT_FIELD_LABOR_HOURS)*PERMANENT_HOURLY_RATE-MAX(0,($D22+L$5)-PERMANENT_FIELD_LABOR_HOURS)*TEMP_HOURLY_RATE-FIXED_SEASON_COST) -> -13771.264 | M22: =IF(OR($A22>TOMATO_BED_CAP,$B22>CARROT_BED_CAP,M$4>MESCLUN_BED_CAP,$A22+$B22+M$4>TOTAL_BEDS_AVAILABLE,($D22+M$5)>TOTAL_LABOR_HOURS_CAP,MAX(0,($D22+M$5)-PERMANENT_FIELD_LABOR_HOURS)>TEMP_HOURS_CAP),"",$C22+M$6-MIN(($D22+M$5),PERMANENT_FIELD_LABOR_HOURS)*PERMANENT_HOURLY_RATE-MAX(0,($D22+M$5)-PERMANENT_FIELD_LABOR_HOURS)*TEMP_HOURLY_RATE-FIXED_SEASON_COST) -> -12866.561 | ... AJ22: =IF(OR($A22>TOMATO_BED_CAP,$B22>CARROT_BED_CAP,AJ$4>MESCLUN_BED_CAP,$A22+$B22+AJ$4>TOTAL_BEDS_AVAILABLE,($D22+AJ$5)>TOTAL_LABOR_HOURS_CAP,MAX(0,($D22+AJ$5)-PERMANENT_FIELD_LABOR_HOURS)>TEMP_HOURS_CAP),"",$C22+AJ$6-MIN(($D22+AJ$5),PERMANENT_FIELD_LABOR_HOURS)*PERMANENT_HOURLY_RATE-MAX(0,($D22+AJ$5)-PERMANENT_FIELD_LABOR_HOURS)*TEMP_HOURLY_RATE-FIXED_SEASON_COST) -> 938.63548
A23: =INT((ROW()-ROW($A$8))/(20+1)) -> 0 | B23: =MOD(ROW()-ROW($A$8),20+1) -> 15 | C23: =A23*(TOMATO_REVENUE_PER_BED-TOMATO_FERTILIZER_PER_BED)+B23*(CARROT_REVENUE_PER_BED-CARROT_FERTILIZER_PER_BED) -> 24810 | D23: =INDEX(TOMATO_SCHED_LABOR_HRS,A23+1)+INDEX(CARROT_SCHED_LABOR_HRS,B23+1) -> 651.47348 | E23: =IF(COUNT(F23:AJ23)=0,"",MAX(F23:AJ23)) -> 1581.2097 | F23: =IF(OR($A23>TOMATO_BED_CAP,$B23>CARROT_BED_CAP,F$4>MESCLUN_BED_CAP,$A23+$B23+F$4>TOTAL_BEDS_AVAILABLE,($D23+F$5)>TOTAL_LABOR_HOURS_CAP,MAX(0,($D23+F$5)-PERMANENT_FIELD_LABOR_HOURS)>TEMP_HOURS_CAP),"",$C23+F$6-MIN(($D23+F$5),PERMANENT_FIELD_LABOR_HOURS)*PERMANENT_HOURLY_RATE-MAX(0,($D23+F$5)-PERMANENT_FIELD_LABOR_HOURS)*TEMP_HOURLY_RATE-FIXED_SEASON_COST) -> -17809.159 | G23: =IF(OR($A23>TOMATO_BED_CAP,$B23>CARROT_BED_CAP,G$4>MESCLUN_BED_CAP,$A23+$B23+G$4>TOTAL_BEDS_AVAILABLE,($D23+G$5)>TOTAL_LABOR_HOURS_CAP,MAX(0,($D23+G$5)-PERMANENT_FIELD_LABOR_HOURS)>TEMP_HOURS_CAP),"",$C23+G$6-MIN(($D23+G$5),PERMANENT_FIELD_LABOR_HOURS)*PERMANENT_HOURLY_RATE-MAX(0,($D23+G$5)-PERMANENT_FIELD_LABOR_HOURS)*TEMP_HOURLY_RATE-FIXED_SEASON_COST) -> -17571.089 | H23: =IF(OR($A23>TOMATO_BED_CAP,$B23>CARROT_BED_CAP,H$4>MESCLUN_BED_CAP,$A23+$B23+H$4>TOTAL_BEDS_AVAILABLE,($D23+H$5)>TOTAL_LABOR_HOURS_CAP,MAX(0,($D23+H$5)-PERMANENT_FIELD_LABOR_HOURS)>TEMP_HOURS_CAP),"",$C23+H$6-MIN(($D23+H$5),PERMANENT_FIELD_LABOR_HOURS)*PERMANENT_HOURLY_RATE-MAX(0,($D23+H$5)-PERMANENT_FIELD_LABOR_HOURS)*TEMP_HOURLY_RATE-FIXED_SEASON_COST) -> -16960.484 | I23: =IF(OR($A23>TOMATO_BED_CAP,$B23>CARROT_BED_CAP,I$4>MESCLUN_BED_CAP,$A23+$B23+I$4>TOTAL_BEDS_AVAILABLE,($D23+I$5)>TOTAL_LABOR_HOURS_CAP,MAX(0,($D23+I$5)-PERMANENT_FIELD_LABOR_HOURS)>TEMP_HOURS_CAP),"",$C23+I$6-MIN(($D23+I$5),PERMANENT_FIELD_LABOR_HOURS)*PERMANENT_HOURLY_RATE-MAX(0,($D23+I$5)-PERMANENT_FIELD_LABOR_HOURS)*TEMP_HOURLY_RATE-FIXED_SEASON_COST) -> -15971.368 | J23: =IF(OR($A23>TOMATO_BED_CAP,$B23>CARROT_BED_CAP,J$4>MESCLUN_BED_CAP,$A23+$B23+J$4>TOTAL_BEDS_AVAILABLE,($D23+J$5)>TOTAL_LABOR_HOURS_CAP,MAX(0,($D23+J$5)-PERMANENT_FIELD_LABOR_HOURS)>TEMP_HOURS_CAP),"",$C23+J$6-MIN(($D23+J$5),PERMANENT_FIELD_LABOR_HOURS)*PERMANENT_HOURLY_RATE-MAX(0,($D23+J$5)-PERMANENT_FIELD_LABOR_HOURS)*TEMP_HOURLY_RATE-FIXED_SEASON_COST) -> -15002.774 | K23: =IF(OR($A23>TOMATO_BED_CAP,$B23>CARROT_BED_CAP,K$4>MESCLUN_BED_CAP,$A23+$B23+K$4>TOTAL_BEDS_AVAILABLE,($D23+K$5)>TOTAL_LABOR_HOURS_CAP,MAX(0,($D23+K$5)-PERMANENT_FIELD_LABOR_HOURS)>TEMP_HOURS_CAP),"",$C23+K$6-MIN(($D23+K$5),PERMANENT_FIELD_LABOR_HOURS)*PERMANENT_HOURLY_RATE-MAX(0,($D23+K$5)-PERMANENT_FIELD_LABOR_HOURS)*TEMP_HOURLY_RATE-FIXED_SEASON_COST) -> -14055.085 | L23: =IF(OR($A23>TOMATO_BED_CAP,$B23>CARROT_BED_CAP,L$4>MESCLUN_BED_CAP,$A23+$B23+L$4>TOTAL_BEDS_AVAILABLE,($D23+L$5)>TOTAL_LABOR_HOURS_CAP,MAX(0,($D23+L$5)-PERMANENT_FIELD_LABOR_HOURS)>TEMP_HOURS_CAP),"",$C23+L$6-MIN(($D23+L$5),PERMANENT_FIELD_LABOR_HOURS)*PERMANENT_HOURLY_RATE-MAX(0,($D23+L$5)-PERMANENT_FIELD_LABOR_HOURS)*TEMP_HOURLY_RATE-FIXED_SEASON_COST) -> -13128.69 | M23: =IF(OR($A23>TOMATO_BED_CAP,$B23>CARROT_BED_CAP,M$4>MESCLUN_BED_CAP,$A23+$B23+M$4>TOTAL_BEDS_AVAILABLE,($D23+M$5)>TOTAL_LABOR_HOURS_CAP,MAX(0,($D23+M$5)-PERMANENT_FIELD_LABOR_HOURS)>TEMP_HOURS_CAP),"",$C23+M$6-MIN(($D23+M$5),PERMANENT_FIELD_LABOR_HOURS)*PERMANENT_HOURLY_RATE-MAX(0,($D23+M$5)-PERMANENT_FIELD_LABOR_HOURS)*TEMP_HOURLY_RATE-FIXED_SEASON_COST) -> -12223.986 | ... AJ23: =IF(OR($A23>TOMATO_BED_CAP,$B23>CARROT_BED_CAP,AJ$4>MESCLUN_BED_CAP,$A23+$B23+AJ$4>TOTAL_BEDS_AVAILABLE,($D23+AJ$5)>TOTAL_LABOR_HOURS_CAP,MAX(0,($D23+AJ$5)-PERMANENT_FIELD_LABOR_HOURS)>TEMP_HOURS_CAP),"",$C23+AJ$6-MIN(($D23+AJ$5),PERMANENT_FIELD_LABOR_HOURS)*PERMANENT_HOURLY_RATE-MAX(0,($D23+AJ$5)-PERMANENT_FIELD_LABOR_HOURS)*TEMP_HOURLY_RATE-FIXED_SEASON_COST) -> 1581.2097
A24: =INT((ROW()-ROW($A$8))/(20+1)) -> 0 | B24: =MOD(ROW()-ROW($A$8),20+1) -> 16 | C24: =A24*(TOMATO_REVENUE_PER_BED-TOMATO_FERTILIZER_PER_BED)+B24*(CARROT_REVENUE_PER_BED-CARROT_FERTILIZER_PER_BED) -> 26464 | D24: =INDEX(TOMATO_SCHED_LABOR_HRS,A24+1)+INDEX(CARROT_SCHED_LABOR_HRS,B24+1) -> 712.27767 | E24: =IF(COUNT(F24:AJ24)=0,"",MAX(F24:AJ24)) -> 2179.6489 | F24: =IF(OR($A24>TOMATO_BED_CAP,$B24>CARROT_BED_CAP,F$4>MESCLUN_BED_CAP,$A24+$B24+F$4>TOTAL_BEDS_AVAILABLE,($D24+F$5)>TOTAL_LABOR_HOURS_CAP,MAX(0,($D24+F$5)-PERMANENT_FIELD_LABOR_HOURS)>TEMP_HOURS_CAP),"",$C24+F$6-MIN(($D24+F$5),PERMANENT_FIELD_LABOR_HOURS)*PERMANENT_HOURLY_RATE-MAX(0,($D24+F$5)-PERMANENT_FIELD_LABOR_HOURS)*TEMP_HOURLY_RATE-FIXED_SEASON_COST) -> -18266.281 | G24: =IF(OR($A24>TOMATO_BED_CAP,$B24>CARROT_BED_CAP,G$4>MESCLUN_BED_CAP,$A24+$B24+G$4>TOTAL_BEDS_AVAILABLE,($D24+G$5)>TOTAL_LABOR_HOURS_CAP,MAX(0,($D24+G$5)-PERMANENT_FIELD_LABOR_HOURS)>TEMP_HOURS_CAP),"",$C24+G$6-MIN(($D24+G$5),PERMANENT_FIELD_LABOR_HOURS)*PERMANENT_HOURLY_RATE-MAX(0,($D24+G$5)-PERMANENT_FIELD_LABOR_HOURS)*TEMP_HOURLY_RATE-FIXED_SEASON_COST) -> -17371.305 | H24: =IF(OR($A24>TOMATO_BED_CAP,$B24>CARROT_BED_CAP,H$4>MESCLUN_BED_CAP,$A24+$B24+H$4>TOTAL_BEDS_AVAILABLE,($D24+H$5)>TOTAL_LABOR_HOURS_CAP,MAX(0,($D24+H$5)-PERMANENT_FIELD_LABOR_HOURS)>TEMP_HOURS_CAP),"",$C24+H$6-MIN(($D24+H$5),PERMANENT_FIELD_LABOR_HOURS)*PERMANENT_HOURLY_RATE-MAX(0,($D24+H$5)-PERMANENT_FIELD_LABOR_HOURS)*TEMP_HOURLY_RATE-FIXED_SEASON_COST) -> -16362.045 | I24: =IF(OR($A24>TOMATO_BED_CAP,$B24>CARROT_BED_CAP,I$4>MESCLUN_BED_CAP,$A24+$B24+I$4>TOTAL_BEDS_AVAILABLE,($D24+I$5)>TOTAL_LABOR_HOURS_CAP,MAX(0,($D24+I$5)-PERMANENT_FIELD_LABOR_HOURS)>TEMP_HOURS_CAP),"",$C24+I$6-MIN(($D24+I$5),PERMANENT_FIELD_LABOR_HOURS)*PERMANENT_HOURLY_RATE-MAX(0,($D24+I$5)-PERMANENT_FIELD_LABOR_HOURS)*TEMP_HOURLY_RATE-FIXED_SEASON_COST) -> -15372.929 | J24: =IF(OR($A24>TOMATO_BED_CAP,$B24>CARROT_BED_CAP,J$4>MESCLUN_BED_CAP,$A24+$B24+J$4>TOTAL_BEDS_AVAILABLE,($D24+J$5)>TOTAL_LABOR_HOURS_CAP,MAX(0,($D24+J$5)-PERMANENT_FIELD_LABOR_HOURS)>TEMP_HOURS_CAP),"",$C24+J$6-MIN(($D24+J$5),PERMANENT_FIELD_LABOR_HOURS)*PERMANENT_HOURLY_RATE-MAX(0,($D24+J$5)-PERMANENT_FIELD_LABOR_HOURS)*TEMP_HOURLY_RATE-FIXED_SEASON_COST) -> -14404.334 | K24: =IF(OR($A24>TOMATO_BED_CAP,$B24>CARROT_BED_CAP,K$4>MESCLUN_BED_CAP,$A24+$B24+K$4>TOTAL_BEDS_AVAILABLE,($D24+K$5)>TOTAL_LABOR_HOURS_CAP,MAX(0,($D24+K$5)-PERMANENT_FIELD_LABOR_HOURS)>TEMP_HOURS_CAP),"",$C24+K$6-MIN(($D24+K$5),PERMANENT_FIELD_LABOR_HOURS)*PERMANENT_HOURLY_RATE-MAX(0,($D24+K$5)-PERMANENT_FIELD_LABOR_HOURS)*TEMP_HOURLY_RATE-FIXED_SEASON_COST) -> -13456.645 | L24: =IF(OR($A24>TOMATO_BED_CAP,$B24>CARROT_BED_CAP,L$4>MESCLUN_BED_CAP,$A24+$B24+L$4>TOTAL_BEDS_AVAILABLE,($D24+L$5)>TOTAL_LABOR_HOURS_CAP,MAX(0,($D24+L$5)-PERMANENT_FIELD_LABOR_HOURS)>TEMP_HOURS_CAP),"",$C24+L$6-MIN(($D24+L$5),PERMANENT_FIELD_LABOR_HOURS)*PERMANENT_HOURLY_RATE-MAX(0,($D24+L$5)-PERMANENT_FIELD_LABOR_HOURS)*TEMP_HOURLY_RATE-FIXED_SEASON_COST) -> -12530.251 | M24: =IF(OR($A24>TOMATO_BED_CAP,$B24>CARROT_BED_CAP,M$4>MESCLUN_BED_CAP,$A24+$B24+M$4>TOTAL_BEDS_AVAILABLE,($D24+M$5)>TOTAL_LABOR_HOURS_CAP,MAX(0,($D24+M$5)-PERMANENT_FIELD_LABOR_HOURS)>TEMP_HOURS_CAP),"",$C24+M$6-MIN(($D24+M$5),PERMANENT_FIELD_LABOR_HOURS)*PERMANENT_HOURLY_RATE-MAX(0,($D24+M$5)-PERMANENT_FIELD_LABOR_HOURS)*TEMP_HOURLY_RATE-FIXED_SEASON_COST) -> -11625.547 | ... AJ24: =IF(OR($A24>TOMATO_BED_CAP,$B24>CARROT_BED_CAP,AJ$4>MESCLUN_BED_CAP,$A24+$B24+AJ$4>TOTAL_BEDS_AVAILABLE,($D24+AJ$5)>TOTAL_LABOR_HOURS_CAP,MAX(0,($D24+AJ$5)-PERMANENT_FIELD_LABOR_HOURS)>TEMP_HOURS_CAP),"",$C24+AJ$6-MIN(($D24+AJ$5),PERMANENT_FIELD_LABOR_HOURS)*PERMANENT_HOURLY_RATE-MAX(0,($D24+AJ$5)-PERMANENT_FIELD_LABOR_HOURS)*TEMP_HOURLY_RATE-FIXED_SEASON_COST) -> 2179.6489
A25: =INT((ROW()-ROW($A$8))/(20+1)) -> 0 | B25: =MOD(ROW()-ROW($A$8),20+1) -> 17 | C25: =A25*(TOMATO_REVENUE_PER_BED-TOMATO_FERTILIZER_PER_BED)+B25*(CARROT_REVENUE_PER_BED-CARROT_FERTILIZER_PER_BED) -> 28118 | D25: =INDEX(TOMATO_SCHED_LABOR_HRS,A25+1)+INDEX(CARROT_SCHED_LABOR_HRS,B25+1) -> 775.7149 | E25: =IF(COUNT(F25:AJ25)=0,"",MAX(F25:AJ25)) -> 2732.3786 | F25: =IF(OR($A25>TOMATO_BED_CAP,$B25>CARROT_BED_CAP,F$4>MESCLUN_BED_CAP,$A25+$B25+F$4>TOTAL_BEDS_AVAILABLE,($D25+F$5)>TOTAL_LABOR_HOURS_CAP,MAX(0,($D25+F$5)-PERMANENT_FIELD_LABOR_HOURS)>TEMP_HOURS_CAP),"",$C25+F$6-MIN(($D25+F$5),PERMANENT_FIELD_LABOR_HOURS)*PERMANENT_HOURLY_RATE-MAX(0,($D25+F$5)-PERMANENT_FIELD_LABOR_HOURS)*TEMP_HOURLY_RATE-FIXED_SEASON_COST) -> -17847.611 | G25: =IF(OR($A25>TOMATO_BED_CAP,$B25>CARROT_BED_CAP,G$4>MESCLUN_BED_CAP,$A25+$B25+G$4>TOTAL_BEDS_AVAILABLE,($D25+G$5)>TOTAL_LABOR_HOURS_CAP,MAX(0,($D25+G$5)-PERMANENT_FIELD_LABOR_HOURS)>TEMP_HOURS_CAP),"",$C25+G$6-MIN(($D25+G$5),PERMANENT_FIELD_LABOR_HOURS)*PERMANENT_HOURLY_RATE-MAX(0,($D25+G$5)-PERMANENT_FIELD_LABOR_HOURS)*TEMP_HOURLY_RATE-FIXED_SEASON_COST) -> -16818.576 | H25: =IF(OR($A25>TOMATO_BED_CAP,$B25>CARROT_BED_CAP,H$4>MESCLUN_BED_CAP,$A25+$B25+H$4>TOTAL_BEDS_AVAILABLE,($D25+H$5)>TOTAL_LABOR_HOURS_CAP,MAX(0,($D25+H$5)-PERMANENT_FIELD_LABOR_HOURS)>TEMP_HOURS_CAP),"",$C25+H$6-MIN(($D25+H$5),PERMANENT_FIELD_LABOR_HOURS)*PERMANENT_HOURLY_RATE-MAX(0,($D25+H$5)-PERMANENT_FIELD_LABOR_HOURS)*TEMP_HOURLY_RATE-FIXED_SEASON_COST) -> -15809.315 | I25: =IF(OR($A25>TOMATO_BED_CAP,$B25>CARROT_BED_CAP,I$4>MESCLUN_BED_CAP,$A25+$B25+I$4>TOTAL_BEDS_AVAILABLE,($D25+I$5)>TOTAL_LABOR_HOURS_CAP,MAX(0,($D25+I$5)-PERMANENT_FIELD_LABOR_HOURS)>TEMP_HOURS_CAP),"",$C25+I$6-MIN(($D25+I$5),PERMANENT_FIELD_LABOR_HOURS)*PERMANENT_HOURLY_RATE-MAX(0,($D25+I$5)-PERMANENT_FIELD_LABOR_HOURS)*TEMP_HOURLY_RATE-FIXED_SEASON_COST) -> -14820.199 | J25: =IF(OR($A25>TOMATO_BED_CAP,$B25>CARROT_BED_CAP,J$4>MESCLUN_BED_CAP,$A25+$B25+J$4>TOTAL_BEDS_AVAILABLE,($D25+J$5)>TOTAL_LABOR_HOURS_CAP,MAX(0,($D25+J$5)-PERMANENT_FIELD_LABOR_HOURS)>TEMP_HOURS_CAP),"",$C25+J$6-MIN(($D25+J$5),PERMANENT_FIELD_LABOR_HOURS)*PERMANENT_HOURLY_RATE-MAX(0,($D25+J$5)-PERMANENT_FIELD_LABOR_HOURS)*TEMP_HOURLY_RATE-FIXED_SEASON_COST) -> -13851.605 | K25: =IF(OR($A25>TOMATO_BED_CAP,$B25>CARROT_BED_CAP,K$4>MESCLUN_BED_CAP,$A25+$B25+K$4>TOTAL_BEDS_AVAILABLE,($D25+K$5)>TOTAL_LABOR_HOURS_CAP,MAX(0,($D25+K$5)-PERMANENT_FIELD_LABOR_HOURS)>TEMP_HOURS_CAP),"",$C25+K$6-MIN(($D25+K$5),PERMANENT_FIELD_LABOR_HOURS)*PERMANENT_HOURLY_RATE-MAX(0,($D25+K$5)-PERMANENT_FIELD_LABOR_HOURS)*TEMP_HOURLY_RATE-FIXED_SEASON_COST) -> -12903.916 | L25: =IF(OR($A25>TOMATO_BED_CAP,$B25>CARROT_BED_CAP,L$4>MESCLUN_BED_CAP,$A25+$B25+L$4>TOTAL_BEDS_AVAILABLE,($D25+L$5)>TOTAL_LABOR_HOURS_CAP,MAX(0,($D25+L$5)-PERMANENT_FIELD_LABOR_HOURS)>TEMP_HOURS_CAP),"",$C25+L$6-MIN(($D25+L$5),PERMANENT_FIELD_LABOR_HOURS)*PERMANENT_HOURLY_RATE-MAX(0,($D25+L$5)-PERMANENT_FIELD_LABOR_HOURS)*TEMP_HOURLY_RATE-FIXED_SEASON_COST) -> -11977.521 | M25: =IF(OR($A25>TOMATO_BED_CAP,$B25>CARROT_BED_CAP,M$4>MESCLUN_BED_CAP,$A25+$B25+M$4>TOTAL_BEDS_AVAILABLE,($D25+M$5)>TOTAL_LABOR_HOURS_CAP,MAX(0,($D25+M$5)-PERMANENT_FIELD_LABOR_HOURS)>TEMP_HOURS_CAP),"",$C25+M$6-MIN(($D25+M$5),PERMANENT_FIELD_LABOR_HOURS)*PERMANENT_HOURLY_RATE-MAX(0,($D25+M$5)-PERMANENT_FIELD_LABOR_HOURS)*TEMP_HOURLY_RATE-FIXED_SEASON_COST) -> -11072.817 | ... AJ25: =IF(OR($A25>TOMATO_BED_CAP,$B25>CARROT_BED_CAP,AJ$4>MESCLUN_BED_CAP,$A25+$B25+AJ$4>TOTAL_BEDS_AVAILABLE,($D25+AJ$5)>TOTAL_LABOR_HOURS_CAP,MAX(0,($D25+AJ$5)-PERMANENT_FIELD_LABOR_HOURS)>TEMP_HOURS_CAP),"",$C25+AJ$6-MIN(($D25+AJ$5),PERMANENT_FIELD_LABOR_HOURS)*PERMANENT_HOURLY_RATE-MAX(0,($D25+AJ$5)-PERMANENT_FIELD_LABOR_HOURS)*TEMP_HOURLY_RATE-FIXED_SEASON_COST) -> 2732.3786
A26: =INT((ROW()-ROW($A$8))/(20+1)) -> 0 | B26: =MOD(ROW()-ROW($A$8),20+1) -> 18 | C26: =A26*(TOMATO_REVENUE_PER_BED-TOMATO_FERTILIZER_PER_BED)+B26*(CARROT_REVENUE_PER_BED-CARROT_FERTILIZER_PER_BED) -> 29772 | D26: =INDEX(TOMATO_SCHED_LABOR_HRS,A26+1)+INDEX(CARROT_SCHED_LABOR_HRS,B26+1) -> 841.87882 | E26: =IF(COUNT(F26:AJ26)=0,"",MAX(F26:AJ26)) -> 3237.773 | F26: =IF(OR($A26>TOMATO_BED_CAP,$B26>CARROT_BED_CAP,F$4>MESCLUN_BED_CAP,$A26+$B26+F$4>TOTAL_BEDS_AVAILABLE,($D26+F$5)>TOTAL_LABOR_HOURS_CAP,MAX(0,($D26+F$5)-PERMANENT_FIELD_LABOR_HOURS)>TEMP_HOURS_CAP),"",$C26+F$6-MIN(($D26+F$5),PERMANENT_FIELD_LABOR_HOURS)*PERMANENT_HOURLY_RATE-MAX(0,($D26+F$5)-PERMANENT_FIELD_LABOR_HOURS)*TEMP_HOURLY_RATE-FIXED_SEASON_COST) -> -17342.216 | G26: =IF(OR($A26>TOMATO_BED_CAP,$B26>CARROT_BED_CAP,G$4>MESCLUN_BED_CAP,$A26+$B26+G$4>TOTAL_BEDS_AVAILABLE,($D26+G$5)>TOTAL_LABOR_HOURS_CAP,MAX(0,($D26+G$5)-PERMANENT_FIELD_LABOR_HOURS)>TEMP_HOURS_CAP),"",$C26+G$6-MIN(($D26+G$5),PERMANENT_FIELD_LABOR_HOURS)*PERMANENT_HOURLY_RATE-MAX(0,($D26+G$5)-PERMANENT_FIELD_LABOR_HOURS)*TEMP_HOURLY_RATE-FIXED_SEASON_COST) -> -16313.181 | H26: =IF(OR($A26>TOMATO_BED_CAP,$B26>CARROT_BED_CAP,H$4>MESCLUN_BED_CAP,$A26+$B26+H$4>TOTAL_BEDS_AVAILABLE,($D26+H$5)>TOTAL_LABOR_HOURS_CAP,MAX(0,($D26+H$5)-PERMANENT_FIELD_LABOR_HOURS)>TEMP_HOURS_CAP),"",$C26+H$6-MIN(($D26+H$5),PERMANENT_FIELD_LABOR_HOURS)*PERMANENT_HOURLY_RATE-MAX(0,($D26+H$5)-PERMANENT_FIELD_LABOR_HOURS)*TEMP_HOURLY_RATE-FIXED_SEASON_COST) -> -15303.92 | I26: =IF(OR($A26>TOMATO_BED_CAP,$B26>CARROT_BED_CAP,I$4>MESCLUN_BED_CAP,$A26+$B26+I$4>TOTAL_BEDS_AVAILABLE,($D26+I$5)>TOTAL_LABOR_HOURS_CAP,MAX(0,($D26+I$5)-PERMANENT_FIELD_LABOR_HOURS)>TEMP_HOURS_CAP),"",$C26+I$6-MIN(($D26+I$5),PERMANENT_FIELD_LABOR_HOURS)*PERMANENT_HOURLY_RATE-MAX(0,($D26+I$5)-PERMANENT_FIELD_LABOR_HOURS)*TEMP_HOURLY_RATE-FIXED_SEASON_COST) -> -14314.804 | J26: =IF(OR($A26>TOMATO_BED_CAP,$B26>CARROT_BED_CAP,J$4>MESCLUN_BED_CAP,$A26+$B26+J$4>TOTAL_BEDS_AVAILABLE,($D26+J$5)>TOTAL_LABOR_HOURS_CAP,MAX(0,($D26+J$5)-PERMANENT_FIELD_LABOR_HOURS)>TEMP_HOURS_CAP),"",$C26+J$6-MIN(($D26+J$5),PERMANENT_FIELD_LABOR_HOURS)*PERMANENT_HOURLY_RATE-MAX(0,($D26+J$5)-PERMANENT_FIELD_LABOR_HOURS)*TEMP_HOURLY_RATE-FIXED_SEASON_COST) -> -13346.21 | K26: =IF(OR($A26>TOMATO_BED_CAP,$B26>CARROT_BED_CAP,K$4>MESCLUN_BED_CAP,$A26+$B26+K$4>TOTAL_BEDS_AVAILABLE,($D26+K$5)>TOTAL_LABOR_HOURS_CAP,MAX(0,($D26+K$5)-PERMANENT_FIELD_LABOR_HOURS)>TEMP_HOURS_CAP),"",$C26+K$6-MIN(($D26+K$5),PERMANENT_FIELD_LABOR_HOURS)*PERMANENT_HOURLY_RATE-MAX(0,($D26+K$5)-PERMANENT_FIELD_LABOR_HOURS)*TEMP_HOURLY_RATE-FIXED_SEASON_COST) -> -12398.521 | L26: =IF(OR($A26>TOMATO_BED_CAP,$B26>CARROT_BED_CAP,L$4>MESCLUN_BED_CAP,$A26+$B26+L$4>TOTAL_BEDS_AVAILABLE,($D26+L$5)>TOTAL_LABOR_HOURS_CAP,MAX(0,($D26+L$5)-PERMANENT_FIELD_LABOR_HOURS)>TEMP_HOURS_CAP),"",$C26+L$6-MIN(($D26+L$5),PERMANENT_FIELD_LABOR_HOURS)*PERMANENT_HOURLY_RATE-MAX(0,($D26+L$5)-PERMANENT_FIELD_LABOR_HOURS)*TEMP_HOURLY_RATE-FIXED_SEASON_COST) -> -11472.127 | M26: =IF(OR($A26>TOMATO_BED_CAP,$B26>CARROT_BED_CAP,M$4>MESCLUN_BED_CAP,$A26+$B26+M$4>TOTAL_BEDS_AVAILABLE,($D26+M$5)>TOTAL_LABOR_HOURS_CAP,MAX(0,($D26+M$5)-PERMANENT_FIELD_LABOR_HOURS)>TEMP_HOURS_CAP),"",$C26+M$6-MIN(($D26+M$5),PERMANENT_FIELD_LABOR_HOURS)*PERMANENT_HOURLY_RATE-MAX(0,($D26+M$5)-PERMANENT_FIELD_LABOR_HOURS)*TEMP_HOURLY_RATE-FIXED_SEASON_COST) -> -10567.423 | ... AJ26: =IF(OR($A26>TOMATO_BED_CAP,$B26>CARROT_BED_CAP,AJ$4>MESCLUN_BED_CAP,$A26+$B26+AJ$4>TOTAL_BEDS_AVAILABLE,($D26+AJ$5)>TOTAL_LABOR_HOURS_CAP,MAX(0,($D26+AJ$5)-PERMANENT_FIELD_LABOR_HOURS)>TEMP_HOURS_CAP),"",$C26+AJ$6-MIN(($D26+AJ$5),PERMANENT_FIELD_LABOR_HOURS)*PERMANENT_HOURLY_RATE-MAX(0,($D26+AJ$5)-PERMANENT_FIELD_LABOR_HOURS)*TEMP_HOURLY_RATE-FIXED_SEASON_COST) -> 3237.773
A27: =INT((ROW()-ROW($A$8))/(20+1)) -> 0 | B27: =MOD(ROW()-ROW($A$8),20+1) -> 19 | C27: =A27*(TOMATO_REVENUE_PER_BED-TOMATO_FERTILIZER_PER_BED)+B27*(CARROT_REVENUE_PER_BED-CARROT_FERTILIZER_PER_BED) -> 31426 | D27: =INDEX(TOMATO_SCHED_LABOR_HRS,A27+1)+INDEX(CARROT_SCHED_LABOR_HRS,B27+1) -> 910.86611 | E27: =IF(COUNT(F27:AJ27)=0,"",MAX(F27:AJ27)) -> 3694.1536 | F27: =IF(OR($A27>TOMATO_BED_CAP,$B27>CARROT_BED_CAP,F$4>MESCLUN_BED_CAP,$A27+$B27+F$4>TOTAL_BEDS_AVAILABLE,($D27+F$5)>TOTAL_LABOR_HOURS_CAP,MAX(0,($D27+F$5)-PERMANENT_FIELD_LABOR_HOURS)>TEMP_HOURS_CAP),"",$C27+F$6-MIN(($D27+F$5),PERMANENT_FIELD_LABOR_HOURS)*PERMANENT_HOURLY_RATE-MAX(0,($D27+F$5)-PERMANENT_FIELD_LABOR_HOURS)*TEMP_HOURLY_RATE-FIXED_SEASON_COST) -> -16885.836 | G27: =IF(OR($A27>TOMATO_BED_CAP,$B27>CARROT_BED_CAP,G$4>MESCLUN_BED_CAP,$A27+$B27+G$4>TOTAL_BEDS_AVAILABLE,($D27+G$5)>TOTAL_LABOR_HOURS_CAP,MAX(0,($D27+G$5)-PERMANENT_FIELD_LABOR_HOURS)>TEMP_HOURS_CAP),"",$C27+G$6-MIN(($D27+G$5),PERMANENT_FIELD_LABOR_HOURS)*PERMANENT_HOURLY_RATE-MAX(0,($D27+G$5)-PERMANENT_FIELD_LABOR_HOURS)*TEMP_HOURLY_RATE-FIXED_SEASON_COST) -> -15856.801 | H27: =IF(OR($A27>TOMATO_BED_CAP,$B27>CARROT_BED_CAP,H$4>MESCLUN_BED_CAP,$A27+$B27+H$4>TOTAL_BEDS_AVAILABLE,($D27+H$5)>TOTAL_LABOR_HOURS_CAP,MAX(0,($D27+H$5)-PERMANENT_FIELD_LABOR_HOURS)>TEMP_HOURS_CAP),"",$C27+H$6-MIN(($D27+H$5),PERMANENT_FIELD_LABOR_HOURS)*PERMANENT_HOURLY_RATE-MAX(0,($D27+H$5)-PERMANENT_FIELD_LABOR_HOURS)*TEMP_HOURLY_RATE-FIXED_SEASON_COST) -> -14847.54 | I27: =IF(OR($A27>TOMATO_BED_CAP,$B27>CARROT_BED_CAP,I$4>MESCLUN_BED_CAP,$A27+$B27+I$4>TOTAL_BEDS_AVAILABLE,($D27+I$5)>TOTAL_LABOR_HOURS_CAP,MAX(0,($D27+I$5)-PERMANENT_FIELD_LABOR_HOURS)>TEMP_HOURS_CAP),"",$C27+I$6-MIN(($D27+I$5),PERMANENT_FIELD_LABOR_HOURS)*PERMANENT_HOURLY_RATE-MAX(0,($D27+I$5)-PERMANENT_FIELD_LABOR_HOURS)*TEMP_HOURLY_RATE-FIXED_SEASON_COST) -> -13858.424 | J27: =IF(OR($A27>TOMATO_BED_CAP,$B27>CARROT_BED_CAP,J$4>MESCLUN_BED_CAP,$A27+$B27+J$4>TOTAL_BEDS_AVAILABLE,($D27+J$5)>TOTAL_LABOR_HOURS_CAP,MAX(0,($D27+J$5)-PERMANENT_FIELD_LABOR_HOURS)>TEMP_HOURS_CAP),"",$C27+J$6-MIN(($D27+J$5),PERMANENT_FIELD_LABOR_HOURS)*PERMANENT_HOURLY_RATE-MAX(0,($D27+J$5)-PERMANENT_FIELD_LABOR_HOURS)*TEMP_HOURLY_RATE-FIXED_SEASON_COST) -> -12889.83 | K27: =IF(OR($A27>TOMATO_BED_CAP,$B27>CARROT_BED_CAP,K$4>MESCLUN_BED_CAP,$A27+$B27+K$4>TOTAL_BEDS_AVAILABLE,($D27+K$5)>TOTAL_LABOR_HOURS_CAP,MAX(0,($D27+K$5)-PERMANENT_FIELD_LABOR_HOURS)>TEMP_HOURS_CAP),"",$C27+K$6-MIN(($D27+K$5),PERMANENT_FIELD_LABOR_HOURS)*PERMANENT_HOURLY_RATE-MAX(0,($D27+K$5)-PERMANENT_FIELD_LABOR_HOURS)*TEMP_HOURLY_RATE-FIXED_SEASON_COST) -> -11942.141 | L27: =IF(OR($A27>TOMATO_BED_CAP,$B27>CARROT_BED_CAP,L$4>MESCLUN_BED_CAP,$A27+$B27+L$4>TOTAL_BEDS_AVAILABLE,($D27+L$5)>TOTAL_LABOR_HOURS_CAP,MAX(0,($D27+L$5)-PERMANENT_FIELD_LABOR_HOURS)>TEMP_HOURS_CAP),"",$C27+L$6-MIN(($D27+L$5),PERMANENT_FIELD_LABOR_HOURS)*PERMANENT_HOURLY_RATE-MAX(0,($D27+L$5)-PERMANENT_FIELD_LABOR_HOURS)*TEMP_HOURLY_RATE-FIXED_SEASON_COST) -> -11015.746 | M27: =IF(OR($A27>TOMATO_BED_CAP,$B27>CARROT_BED_CAP,M$4>MESCLUN_BED_CAP,$A27+$B27+M$4>TOTAL_BEDS_AVAILABLE,($D27+M$5)>TOTAL_LABOR_HOURS_CAP,MAX(0,($D27+M$5)-PERMANENT_FIELD_LABOR_HOURS)>TEMP_HOURS_CAP),"",$C27+M$6-MIN(($D27+M$5),PERMANENT_FIELD_LABOR_HOURS)*PERMANENT_HOURLY_RATE-MAX(0,($D27+M$5)-PERMANENT_FIELD_LABOR_HOURS)*TEMP_HOURLY_RATE-FIXED_SEASON_COST) -> -10111.042 | ... AJ27: =IF(OR($A27>TOMATO_BED_CAP,$B27>CARROT_BED_CAP,AJ$4>MESCLUN_BED_CAP,$A27+$B27+AJ$4>TOTAL_BEDS_AVAILABLE,($D27+AJ$5)>TOTAL_LABOR_HOURS_CAP,MAX(0,($D27+AJ$5)-PERMANENT_FIELD_LABOR_HOURS)>TEMP_HOURS_CAP),"",$C27+AJ$6-MIN(($D27+AJ$5),PERMANENT_FIELD_LABOR_HOURS)*PERMANENT_HOURLY_RATE-MAX(0,($D27+AJ$5)-PERMANENT_FIELD_LABOR_HOURS)*TEMP_HOURLY_RATE-FIXED_SEASON_COST) -> 3694.1536
... A448: =INT((ROW()-ROW($A$8))/(20+1)) -> 20 | B448: =MOD(ROW()-ROW($A$8),20+1) -> 20 | C448: =A448*(TOMATO_REVENUE_PER_BED-TOMATO_FERTILIZER_PER_BED)+B448*(CARROT_REVENUE_PER_BED-CARROT_FERTILIZER_PER_BED) -> 191480 | D448: =INDEX(TOMATO_SCHED_LABOR_HRS,A448+1)+INDEX(CARROT_SCHED_LABOR_HRS,B448+1) -> 13092.277 | E448: =IF(COUNT(F448:AJ448)=0,"",MAX(F448:AJ448)) | F448: =IF(OR($A448>TOMATO_BED_CAP,$B448>CARROT_BED_CAP,F$4>MESCLUN_BED_CAP,$A448+$B448+F$4>TOTAL_BEDS_AVAILABLE,($D448+F$5)>TOTAL_LABOR_HOURS_CAP,MAX(0,($D448+F$5)-PERMANENT_FIELD_LABOR_HOURS)>TEMP_HOURS_CAP),"",$C448+F$6-MIN(($D448+F$5),PERMANENT_FIELD_LABOR_HOURS)*PERMANENT_HOURLY_RATE-MAX(0,($D448+F$5)-PERMANENT_FIELD_LABOR_HOURS)*TEMP_HOURLY_RATE-FIXED_SEASON_COST) | G448: =IF(OR($A448>TOMATO_BED_CAP,$B448>CARROT_BED_CAP,G$4>MESCLUN_BED_CAP,$A448+$B448+G$4>TOTAL_BEDS_AVAILABLE,($D448+G$5)>TOTAL_LABOR_HOURS_CAP,MAX(0,($D448+G$5)-PERMANENT_FIELD_LABOR_HOURS)>TEMP_HOURS_CAP),"",$C448+G$6-MIN(($D448+G$5),PERMANENT_FIELD_LABOR_HOURS)*PERMANENT_HOURLY_RATE-MAX(0,($D448+G$5)-PERMANENT_FIELD_LABOR_HOURS)*TEMP_HOURLY_RATE-FIXED_SEASON_COST) | H448: =IF(OR($A448>TOMATO_BED_CAP,$B448>CARROT_BED_CAP,H$4>MESCLUN_BED_CAP,$A448+$B448+H$4>TOTAL_BEDS_AVAILABLE,($D448+H$5)>TOTAL_LABOR_HOURS_CAP,MAX(0,($D448+H$5)-PERMANENT_FIELD_LABOR_HOURS)>TEMP_HOURS_CAP),"",$C448+H$6-MIN(($D448+H$5),PERMANENT_FIELD_LABOR_HOURS)*PERMANENT_HOURLY_RATE-MAX(0,($D448+H$5)-PERMANENT_FIELD_LABOR_HOURS)*TEMP_HOURLY_RATE-FIXED_SEASON_COST) | I448: =IF(OR($A448>TOMATO_BED_CAP,$B448>CARROT_BED_CAP,I$4>MESCLUN_BED_CAP,$A448+$B448+I$4>TOTAL_BEDS_AVAILABLE,($D448+I$5)>TOTAL_LABOR_HOURS_CAP,MAX(0,($D448+I$5)-PERMANENT_FIELD_LABOR_HOURS)>TEMP_HOURS_CAP),"",$C448+I$6-MIN(($D448+I$5),PERMANENT_FIELD_LABOR_HOURS)*PERMANENT_HOURLY_RATE-MAX(0,($D448+I$5)-PERMANENT_FIELD_LABOR_HOURS)*TEMP_HOURLY_RATE-FIXED_SEASON_COST) | J448: =IF(OR($A448>TOMATO_BED_CAP,$B448>CARROT_BED_CAP,J$4>MESCLUN_BED_CAP,$A448+$B448+J$4>TOTAL_BEDS_AVAILABLE,($D448+J$5)>TOTAL_LABOR_HOURS_CAP,MAX(0,($D448+J$5)-PERMANENT_FIELD_LABOR_HOURS)>TEMP_HOURS_CAP),"",$C448+J$6-MIN(($D448+J$5),PERMANENT_FIELD_LABOR_HOURS)*PERMANENT_HOURLY_RATE-MAX(0,($D448+J$5)-PERMANENT_FIELD_LABOR_HOURS)*TEMP_HOURLY_RATE-FIXED_SEASON_COST) | K448: =IF(OR($A448>TOMATO_BED_CAP,$B448>CARROT_BED_CAP,K$4>MESCLUN_BED_CAP,$A448+$B448+K$4>TOTAL_BEDS_AVAILABLE,($D448+K$5)>TOTAL_LABOR_HOURS_CAP,MAX(0,($D448+K$5)-PERMANENT_FIELD_LABOR_HOURS)>TEMP_HOURS_CAP),"",$C448+K$6-MIN(($D448+K$5),PERMANENT_FIELD_LABOR_HOURS)*PERMANENT_HOURLY_RATE-MAX(0,($D448+K$5)-PERMANENT_FIELD_LABOR_HOURS)*TEMP_HOURLY_RATE-FIXED_SEASON_COST) | L448: =IF(OR($A448>TOMATO_BED_CAP,$B448>CARROT_BED_CAP,L$4>MESCLUN_BED_CAP,$A448+$B448+L$4>TOTAL_BEDS_AVAILABLE,($D448+L$5)>TOTAL_LABOR_HOURS_CAP,MAX(0,($D448+L$5)-PERMANENT_FIELD_LABOR_HOURS)>TEMP_HOURS_CAP),"",$C448+L$6-MIN(($D448+L$5),PERMANENT_FIELD_LABOR_HOURS)*PERMANENT_HOURLY_RATE-MAX(0,($D448+L$5)-PERMANENT_FIELD_LABOR_HOURS)*TEMP_HOURLY_RATE-FIXED_SEASON_COST) | M448: =IF(OR($A448>TOMATO_BED_CAP,$B448>CARROT_BED_CAP,M$4>MESCLUN_BED_CAP,$A448+$B448+M$4>TOTAL_BEDS_AVAILABLE,($D448+M$5)>TOTAL_LABOR_HOURS_CAP,MAX(0,($D448+M$5)-PERMANENT_FIELD_LABOR_HOURS)>TEMP_HOURS_CAP),"",$C448+M$6-MIN(($D448+M$5),PERMANENT_FIELD_LABOR_HOURS)*PERMANENT_HOURLY_RATE-MAX(0,($D448+M$5)-PERMANENT_FIELD_LABOR_HOURS)*TEMP_HOURLY_RATE-FIXED_SEASON_COST) | ... AJ448: =IF(OR($A448>TOMATO_BED_CAP,$B448>CARROT_BED_CAP,AJ$4>MESCLUN_BED_CAP,$A448+$B448+AJ$4>TOTAL_BEDS_AVAILABLE,($D448+AJ$5)>TOTAL_LABOR_HOURS_CAP,MAX(0,($D448+AJ$5)-PERMANENT_FIELD_LABOR_HOURS)>TEMP_HOURS_CAP),"",$C448+AJ$6-MIN(($D448+AJ$5),PERMANENT_FIELD_LABOR_HOURS)*PERMANENT_HOURLY_RATE-MAX(0,($D448+AJ$5)-PERMANENT_FIELD_LABOR_HOURS)*TEMP_HOURLY_RATE-FIXED_SEASON_COST)

Sheet Checks
A1: Checks - spec.md Validation Rules (V1–V6), then supporting constraint, error, logic and hand-calculation checks
A2: Every status is a formula. FAIL shows red; PENDING (amber) means a result recorded by hand has not been entered yet. Rule numbers V1–V6 match spec.md, Validation Rules.
A4: Overall status | B4: =IF(COUNTIF(H17:H72,"FAIL")>0,"FAILURES: "&COUNTIF(H17:H72,"FAIL"),IF(COUNTIF(H17:H72,"PENDING")>0,"NO FAILURES; "&COUNTIF(H17:H72,"PENDING")&" PENDING (record Solver and Lab results)","ALL CHECKS PASS")) -> ALL CHECKS PASS | E4: =COUNTIF(H17:H72,"PASS")&" pass, "&COUNTIF(H17:H72,"FAIL")&" fail, "&COUNTIF(H17:H72,"PENDING")&" pending, "&COUNTIF(H17:H72,"INFO")&" info" -> 52 pass, 0 fail, 0 pending, 4 info
A6: Check tolerances (spec.md, Validation Rules; check settings, not model inputs)
A7: PROFIT_TOLERANCE (vs published $42,762) | B7: 25 | C7: $
A8: BED_TOLERANCE (standalone P = MC points) | B8: 1 | C8: beds
A10: Results recorded by hand (V5, V6). Fill in the yellow cells after running Solver and the Farm Profit Lab; leave blank until then.
A11: ID | B11: Run | C11: Starting mix (T / C / M) | D11: Tomato beds returned | E11: Carrot beds returned | F11: Mesclun beds returned | G11: Profit returned ($) | H11: Date run | I11: Note
A12: V5-1 | B12: Excel Solver, run 1 | C12: 0 / 0 / 0 | D12: 10 | E12: 20 | F12: 30 | G12: 42775.16 | H12: 46308 | I12: Solver found a solution.
A13: V5-2 | B13: Excel Solver, run 2 | C13: 20 / 0 / 0 | D13: 10 | E13: 20 | F13: 30 | G13: 42775.16 | H13: 46308 | I13: Started at 20 / 0 / 0 (profit about -$84,300; about 12,110 labor hours, over the 6,480-hour limit). Solver found a solution.
A14: V6 | B14: Farm Profit Lab | C14: 10 / 20 / 30 entered in the Lab | D14: — | E14: — | F14: — | G14: 42762 | H14: 46308 | I14: Farm Profit Lab (farmlab.html), mix 10 / 20 / 30.
A16: ID | B16: Category | C16: Check | D16: Expected | E16: Workbook value | F16: Difference | G16: Tolerance | H16: Status | I16: Note / reconciliation
A17: V1 | B17: Spec rule | C17: Optimal mix: tomato beds (decision cell) | D17: 10 | E17: =TOMATO_BEDS -> 10 | F17: =IF(AND(ISNUMBER(D17),ISNUMBER(E17)),E17-D17,"") -> 0 | G17: 0 | H17: =IF(E17=D17,"PASS","FAIL") -> PASS | I17: Exact, no tolerance.
A18: V1 | B18: Spec rule | C18: Optimal mix: carrot beds (decision cell) | D18: 20 | E18: =CARROT_BEDS -> 20 | F18: =IF(AND(ISNUMBER(D18),ISNUMBER(E18)),E18-D18,"") -> 0 | G18: 0 | H18: =IF(E18=D18,"PASS","FAIL") -> PASS
A19: V1 | B19: Spec rule | C19: Optimal mix: mesclun beds (decision cell) | D19: 30 | E19: =MESCLUN_BEDS -> 30 | F19: =IF(AND(ISNUMBER(D19),ISNUMBER(E19)),E19-D19,"") -> 0 | G19: 0 | H19: =IF(E19=D19,"PASS","FAIL") -> PASS
A20: V2 | B20: Spec rule | C20: Seasonal profit within PROFIT_TOLERANCE of published $42,762 | D20: 42762 | E20: =SEASONAL_PROFIT -> 42775.155 | F20: =IF(AND(ISNUMBER(D20),ISNUMBER(E20)),E20-D20,"") -> 13.155388 | G20: =PROFIT_TOLERANCE -> 25 | H20: =IF(ABS(F20)<=G20,"PASS","FAIL") -> PASS | I20: Spec formulas with the published inputs give $42,775.16. The gap is rounding of $34.72, $17.36 and 0.833; with all three exact, profit is $42,761.66 (spec.md Audit finding A2).
A21: V3 | B21: Spec rule | C21: Standalone P = MC point, tomatoes, at MC_RATE = TEMP_HOURLY_RATE | D21: 10 | E21: =TOMATO_PMC_Q -> 10 | F21: =IF(AND(ISNUMBER(D21),ISNUMBER(E21)),E21-D21,"") -> 0 | G21: =BED_TOLERANCE -> 1 | H21: =IF(ABS(F21)<=G21,"PASS","FAIL") -> PASS | I21: Largest q with REVENUE_PER_BED ≥ MARGINAL_COST(q), Marginal Cost sheet column R.
A22: V3 | B22: Spec rule | C22: Standalone P = MC point, carrots, at MC_RATE = PERMANENT_HOURLY_RATE | D22: 10 | E22: =CARROT_PMC_Q -> 10 | F22: =IF(AND(ISNUMBER(D22),ISNUMBER(E22)),E22-D22,"") -> 0 | G22: =BED_TOLERANCE -> 1 | H22: =IF(ABS(F22)<=G22,"PASS","FAIL") -> PASS | I22: Largest q with REVENUE_PER_BED ≥ MARGINAL_COST(q), Marginal Cost sheet column R.
A23: V3 | B23: Spec rule | C23: Standalone P = MC point, mesclun, at MC_RATE = PERMANENT_HOURLY_RATE | D23: 6 | E23: =MESCLUN_PMC_Q -> 6 | F23: =IF(AND(ISNUMBER(D23),ISNUMBER(E23)),E23-D23,"") -> 0 | G23: =BED_TOLERANCE -> 1 | H23: =IF(ABS(F23)<=G23,"PASS","FAIL") -> PASS | I23: Largest q with REVENUE_PER_BED ≥ MARGINAL_COST(q), Marginal Cost sheet column R.
A24: V4 | B24: Spec rule | C24: Hand check: tomato LABOR_HOURS(1) = 2.5 × 36 × 1.10 | D24: 99 | E24: =INDEX(TOMATO_SCHED_LABOR_HRS,2) -> 99 | F24: =IF(AND(ISNUMBER(D24),ISNUMBER(E24)),E24-D24,"") -> 0 | G24: 0.01 | H24: =IF(ABS(F24)<=G24,"PASS","FAIL") -> PASS | I24: Expected value worked by hand (typed constant).
A25: V4 | B25: Spec rule | C25: Hand check: carrot LABOR_HOURS(1) = 0.833 × 36 × 1.025 | D25: 30.74 | E25: =INDEX(CARROT_SCHED_LABOR_HRS,2) -> 30.7377 | F25: =IF(AND(ISNUMBER(D25),ISNUMBER(E25)),E25-D25,"") -> -0.0023 | G25: 0.01 | H25: =IF(ABS(F25)<=G25,"PASS","FAIL") -> PASS | I25: Expected value worked by hand (typed constant).
A26: V4 | B26: Spec rule | C26: Hand check: mesclun LABOR_HOURS(1) = 1.25 × 36 × 1.0125 | D26: 45.56 | E26: =INDEX(MESCLUN_SCHED_LABOR_HRS,2) -> 45.5625 | F26: =IF(AND(ISNUMBER(D26),ISNUMBER(E26)),E26-D26,"") -> 0.0025 | G26: 0.01 | H26: =IF(ABS(F26)<=G26,"PASS","FAIL") -> PASS | I26: Expected value worked by hand (typed constant).
A27: V4 | B27: Spec rule | C27: Hand check: SEASONAL_PROFIT at mix 1 / 0 / 0 = 8,800 − 880 − 99 × 34.72 − 20,000 | D27: -15517.28 | E27: =INDEX(ENUM_GRID,1*(20+1)+0+1,0+1) -> -15517.28 | F27: =IF(AND(ISNUMBER(D27),ISNUMBER(E27)),E27-D27,"") -> 0 | G27: 0.01 | H27: =IF(ABS(F27)<=G27,"PASS","FAIL") -> PASS | I27: Workbook value read from the Enumeration sheet (tomato 1, carrot 0, mesclun 0). All 99 hours are permanent hours.
A28: V5 | B28: Spec rule | C28: Solver from 0 / 0 / 0 returns 10 / 20 / 30 and passes V2 | D28: 10 / 20 / 30; profit within PROFIT_TOLERANCE | E28: =IF(COUNT(D12:G12)<4,"not yet recorded",D12&" / "&E12&" / "&F12&"; $"&TEXT(G12,"#,##0.00")) -> 10 / 20 / 30; $42,775.16 | F28: =IF(ISNUMBER(G12),G12-42762,"") -> 13.16 | G28: =PROFIT_TOLERANCE -> 25 | H28: =IF(COUNT(D12:G12)<4,"PENDING",IF(AND(D12=10,E12=20,F12=30,ABS(G12-42762)<=PROFIT_TOLERANCE),"PASS","FAIL")) -> PASS | I28: Enter the result in row 12 above.
A29: V5 | B29: Spec rule | C29: Solver from 20 / 0 / 0 returns 10 / 20 / 30 and passes V2 | D29: 10 / 20 / 30; profit within PROFIT_TOLERANCE | E29: =IF(COUNT(D13:G13)<4,"not yet recorded",D13&" / "&E13&" / "&F13&"; $"&TEXT(G13,"#,##0.00")) -> 10 / 20 / 30; $42,775.16 | F29: =IF(ISNUMBER(G13),G13-42762,"") -> 13.16 | G29: =PROFIT_TOLERANCE -> 25 | H29: =IF(COUNT(D13:G13)<4,"PENDING",IF(AND(D13=10,E13=20,F13=30,ABS(G13-42762)<=PROFIT_TOLERANCE),"PASS","FAIL")) -> PASS | I29: Enter the result in row 13 above.
A30: V6 | B30: Spec rule | C30: Farm Profit Lab profit at 10 / 20 / 30 agrees with SEASONAL_PROFIT | D30: =SEASONAL_PROFIT -> 42775.155 | E30: =IF(ISNUMBER(G14),G14,"not yet recorded") -> 42762 | F30: =IF(ISNUMBER(G14),G14-SEASONAL_PROFIT,"") -> -13.155388 | G30: =PROFIT_TOLERANCE -> 25 | H30: =IF(ISNUMBER(G14),IF(ABS(G14-SEASONAL_PROFIT)<=PROFIT_TOLERANCE,"PASS","FAIL"),"PENDING") -> PASS | I30: Enter the Lab's profit in row 14 above.
A31: O1 | B31: Optimum | C31: Enumerated global optimum, tomato beds | D31: 10 | E31: =ENUM_BEST_TOMATO -> 10 | F31: =IF(AND(ISNUMBER(D31),ISNUMBER(E31)),E31-D31,"") -> 0 | G31: 0 | H31: =IF(E31=D31,"PASS","FAIL") -> PASS | I31: Solver-independent.
A32: O2 | B32: Optimum | C32: Enumerated global optimum, carrot beds | D32: 20 | E32: =ENUM_BEST_CARROT -> 20 | F32: =IF(AND(ISNUMBER(D32),ISNUMBER(E32)),E32-D32,"") -> 0 | G32: 0 | H32: =IF(E32=D32,"PASS","FAIL") -> PASS | I32: Solver-independent.
A33: O3 | B33: Optimum | C33: Enumerated global optimum, mesclun beds | D33: 30 | E33: =ENUM_BEST_MESCLUN -> 30 | F33: =IF(AND(ISNUMBER(D33),ISNUMBER(E33)),E33-D33,"") -> 0 | G33: 0 | H33: =IF(E33=D33,"PASS","FAIL") -> PASS | I33: Solver-independent.
A34: O4 | B34: Optimum | C34: Optimum is unique (no tied mix) | D34: 1 | E34: =ENUM_TIES -> 1 | F34: =IF(AND(ISNUMBER(D34),ISNUMBER(E34)),E34-D34,"") -> 0 | G34: 0 | H34: =IF(E34=D34,"PASS","FAIL") -> PASS
A35: O5 | B35: Optimum | C35: Decision cells equal the enumerated global optimum | D35: =ENUM_BEST_PROFIT -> 42775.155 | E35: =SEASONAL_PROFIT -> 42775.155 | F35: =IF(AND(ISNUMBER(D35),ISNUMBER(E35)),E35-D35,"") -> 0 | G35: 0 | H35: =IF(AND(TOMATO_BEDS=ENUM_BEST_TOMATO,CARROT_BEDS=ENUM_BEST_CARROT,MESCLUN_BEDS=ENUM_BEST_MESCLUN),"PASS","FAIL") -> PASS | I35: Fails if Solver stops at a local optimum or the decision cells are edited.
A36: O6 | B36: Optimum | C36: Local optimality: no feasible ±1 bed move raises profit | D36: 0 improving moves | E36: =SUMPRODUCT(--(TOMATO_PLUS1_FEASIBLE*(TOMATO_DPROFIT_PLUS1>0.000000001)))+SUMPRODUCT(--(CARROT_PLUS1_FEASIBLE*(CARROT_DPROFIT_PLUS1>0.000000001)))+SUMPRODUCT(--(MESCLUN_PLUS1_FEASIBLE*(MESCLUN_DPROFIT_PLUS1>0.000000001)))+IF(ISNUMBER(TOMATO_DPROFIT_MINUS1),--(TOMATO_DPROFIT_MINUS1>0.000000001),0)+IF(ISNUMBER(CARROT_DPROFIT_MINUS1),--(CARROT_DPROFIT_MINUS1>0.000000001),0)+IF(ISNUMBER(MESCLUN_DPROFIT_MINUS1),--(MESCLUN_DPROFIT_MINUS1>0.000000001),0) -> 0 | H36: =IF(E36=0,"PASS","FAIL") -> PASS
A37: R1 | B37: Reconciliation | C37: Brief hypothesis 12 T / 20 C / 30 M: profit vs optimum | D37: =ENUM_BEST_PROFIT -> 42775.155 | E37: =INDEX(ENUM_GRID,12*(20+1)+20+1,30+1) -> 40298.022 | F37: =IF(AND(ISNUMBER(D37),ISNUMBER(E37)),E37-D37,"") -> -2477.1338 | H37: =IF(E37<D37,"INFO","FAIL") -> INFO | I37: INFO: 12/20/30 is feasible but earns less than 10/20/30. It is the brief's hypothesis, not an acceptance figure (spec.md, Expected Outputs).
A38: C1 | B38: Constraint | C38: TOMATO_BEDS ≤ TOMATO_BED_CAP | E38: =Optimization!B15 -> 10 | H38: =IF(Optimization!F15="OK","PASS","FAIL") -> PASS | I38: =Optimization!G15 -> Not binding
A39: C2 | B39: Constraint | C39: CARROT_BEDS ≤ CARROT_BED_CAP | E39: =Optimization!B16 -> 20 | H39: =IF(Optimization!F16="OK","PASS","FAIL") -> PASS | I39: =Optimization!G16 -> Binding
A40: C3 | B40: Constraint | C40: MESCLUN_BEDS ≤ MESCLUN_BED_CAP | E40: =Optimization!B17 -> 30 | H40: =IF(Optimization!F17="OK","PASS","FAIL") -> PASS | I40: =Optimization!G17 -> Binding
A41: C4 | B41: Constraint | C41: TOTAL_BEDS_USED ≤ TOTAL_BEDS_AVAILABLE | E41: =Optimization!B18 -> 60 | H41: =IF(Optimization!F18="OK","PASS","FAIL") -> PASS | I41: =Optimization!G18 -> Not binding
A42: C5 | B42: Constraint | C42: TEMP_HOURS_USED ≤ TEMP_HOURS_CAP | E42: =Optimization!B19 -> 4556.8228 | H42: =IF(Optimization!F19="OK","PASS","FAIL") -> PASS | I42: =Optimization!G19 -> Not binding
A43: C6 | B43: Constraint | C43: TOTAL_LABOR_HOURS ≤ TOTAL_LABOR_HOURS_CAP | E43: =Optimization!B20 -> 5276.8228 | H43: =IF(Optimization!F20="OK","PASS","FAIL") -> PASS | I43: =Optimization!G20 -> Not binding
A44: C7 | B44: Constraint | C44: Decision cells integer | D44: 0 | E44: =SUMPRODUCT(--(Optimization!C6:C8<>INT(Optimization!C6:C8))) -> 0 | F44: =IF(AND(ISNUMBER(D44),ISNUMBER(E44)),E44-D44,"") -> 0 | G44: 0 | H44: =IF(E44=D44,"PASS","FAIL") -> PASS
A45: C8 | B45: Constraint | C45: Decision cells non-negative | D45: 0 | E45: =COUNTIF(Optimization!C6:C8,"<0") -> 0 | F45: =IF(AND(ISNUMBER(D45),ISNUMBER(E45)),E45-D45,"") -> 0 | G45: 0 | H45: =IF(E45=D45,"PASS","FAIL") -> PASS
A46: C9 | B46: Constraint | C46: All Optimization constraint rows OK | D46: 0 | E46: =COUNTIF(CONSTRAINT_STATUS,"VIOLATED") -> 0 | F46: =IF(AND(ISNUMBER(D46),ISNUMBER(E46)),E46-D46,"") -> 0 | G46: 0 | H46: =IF(E46=D46,"PASS","FAIL") -> PASS
A47: E1 | B47: Errors | C47: Excel error states on Inputs | D47: 0 | E47: =SUMPRODUCT(--ISERROR(Inputs!B5:B32)) -> 0 | F47: =IF(AND(ISNUMBER(D47),ISNUMBER(E47)),E47-D47,"") -> 0 | G47: 0 | H47: =IF(E47=D47,"PASS","FAIL") -> PASS
A48: E2 | B48: Errors | C48: Excel error states on Cost Structure | D48: 0 | E48: =SUMPRODUCT(--ISERROR('Cost Structure'!A4:J41)) -> 0 | F48: =IF(AND(ISNUMBER(D48),ISNUMBER(E48)),E48-D48,"") -> 0 | G48: 0 | H48: =IF(E48=D48,"PASS","FAIL") -> PASS
A49: E3 | B49: Errors | C49: Excel error states on Marginal Cost | D49: 0 | E49: =SUMPRODUCT(--ISERROR('Marginal Cost'!A5:V93)) -> 0 | F49: =IF(AND(ISNUMBER(D49),ISNUMBER(E49)),E49-D49,"") -> 0 | G49: 0 | H49: =IF(E49=D49,"PASS","FAIL") -> PASS
A50: E4 | B50: Errors | C50: Excel error states on Optimization | D50: 0 | E50: =SUMPRODUCT(--ISERROR(Optimization!A5:K48)) -> 0 | F50: =IF(AND(ISNUMBER(D50),ISNUMBER(E50)),E50-D50,"") -> 0 | G50: 0 | H50: =IF(E50=D50,"PASS","FAIL") -> PASS
A51: E5 | B51: Errors | C51: Excel error states on Enumeration | D51: 0 | E51: =SUMPRODUCT(--ISERROR(Enumeration!A4:AM448)) -> 0 | F51: =IF(AND(ISNUMBER(D51),ISNUMBER(E51)),E51-D51,"") -> 0 | G51: 0 | H51: =IF(E51=D51,"PASS","FAIL") -> PASS
A52: E6 | B52: Errors | C52: Negative or non-numeric inputs | D52: 0 | E52: =COUNTIF(Inputs!B5:B27,"<0")+ROWS(Inputs!B5:B27)-COUNT(Inputs!B5:B27) -> 0 | F52: =IF(AND(ISNUMBER(D52),ISNUMBER(E52)),E52-D52,"") -> 0 | G52: 0 | H52: =IF(E52=D52,"PASS","FAIL") -> PASS
A53: E7 | B53: Errors | C53: Non-integer bed caps / bed availability inputs | D53: 0 | E53: =SUMPRODUCT(--(MOD(TOMATO_BED_CAP,1)<>0))+SUMPRODUCT(--(MOD(CARROT_BED_CAP,1)<>0))+SUMPRODUCT(--(MOD(MESCLUN_BED_CAP,1)<>0))+SUMPRODUCT(--(MOD(TOTAL_BEDS_AVAILABLE,1)<>0))+SUMPRODUCT(--(MOD(TEMP_WORKER_CAP,1)<>0)) -> 0 | F53: =IF(AND(ISNUMBER(D53),ISNUMBER(E53)),E53-D53,"") -> 0 | G53: 0 | H53: =IF(E53=D53,"PASS","FAIL") -> PASS
A54: E8 | B54: Errors | C54: Division by zero guard: TOTAL_LABOR_HOURS > 0 for blended rate | D54: > 0 | E54: =TOTAL_LABOR_HOURS -> 5276.8228 | H54: =IF(E54>0,"PASS","FAIL") -> PASS | I54: BLENDED_LABOR_RATE returns a text note, and crop labor costs return 0, when labor is zero.
A55: E9 | B55: Errors | C55: Divisors non-zero: TEMP_HOURS_LABOR_PER_WORKER | D55: > 0 | E55: =TEMP_HOURS_LABOR_PER_WORKER -> 1440 | H55: =IF(E55>0,"PASS","FAIL") -> PASS
A56: E10 | B56: Errors | C56: LABOR_HOURS(0) = 0 for every crop | D56: 0 | E56: =INDEX(TOMATO_SCHED_LABOR_HRS,1)+INDEX(CARROT_SCHED_LABOR_HRS,1)+INDEX(MESCLUN_SCHED_LABOR_HRS,1) -> 0 | F56: =IF(AND(ISNUMBER(D56),ISNUMBER(E56)),E56-D56,"") -> 0 | G56: 0 | H56: =IF(E56=D56,"PASS","FAIL") -> PASS
A57: E11 | B57: Errors | C57: Tomato single-rate marginal cost never falls (MC_RATE, permanent and temporary schedules) | D57: 0 | E57: =SUMPRODUCT(--('Marginal Cost'!J15:J33<'Marginal Cost'!J14:J32))+SUMPRODUCT(--('Marginal Cost'!K15:K33<'Marginal Cost'!K14:K32))+SUMPRODUCT(--('Marginal Cost'!Q15:Q33<'Marginal Cost'!Q14:Q32)) -> 0 | F57: =IF(AND(ISNUMBER(D57),ISNUMBER(E57)),E57-D57,"") -> 0 | G57: 0 | H57: =IF(E57=D57,"PASS","FAIL") -> PASS | I57: The permanent-hours-first schedule is expected to fall where the 720 permanent hours run out and is not tested here; see I1–I3 and spec.md Audit finding A1.
A58: E12 | B58: Errors | C58: Carrot single-rate marginal cost never falls (MC_RATE, permanent and temporary schedules) | D58: 0 | E58: =SUMPRODUCT(--('Marginal Cost'!J40:J58<'Marginal Cost'!J39:J57))+SUMPRODUCT(--('Marginal Cost'!K40:K58<'Marginal Cost'!K39:K57))+SUMPRODUCT(--('Marginal Cost'!Q40:Q58<'Marginal Cost'!Q39:Q57)) -> 0 | F58: =IF(AND(ISNUMBER(D58),ISNUMBER(E58)),E58-D58,"") -> 0 | G58: 0 | H58: =IF(E58=D58,"PASS","FAIL") -> PASS | I58: The permanent-hours-first schedule is expected to fall where the 720 permanent hours run out and is not tested here; see I1–I3 and spec.md Audit finding A1.
A59: E13 | B59: Errors | C59: Mesclun single-rate marginal cost never falls (MC_RATE, permanent and temporary schedules) | D59: 0 | E59: =SUMPRODUCT(--('Marginal Cost'!J65:J93<'Marginal Cost'!J64:J92))+SUMPRODUCT(--('Marginal Cost'!K65:K93<'Marginal Cost'!K64:K92))+SUMPRODUCT(--('Marginal Cost'!Q65:Q93<'Marginal Cost'!Q64:Q92)) -> 0 | F59: =IF(AND(ISNUMBER(D59),ISNUMBER(E59)),E59-D59,"") -> 0 | G59: 0 | H59: =IF(E59=D59,"PASS","FAIL") -> PASS | I59: The permanent-hours-first schedule is expected to fall where the 720 permanent hours run out and is not tested here; see I1–I3 and spec.md Audit finding A1.
A60: E14 | B60: Coverage | C60: Tomato schedule and enumeration cover q = 0 … TOMATO_BED_CAP | D60: =TOMATO_BED_CAP -> 20 | E60: =ROWS(TOMATO_SCHED_Q)-1 -> 20 | F60: =IF(AND(ISNUMBER(D60),ISNUMBER(E60)),E60-D60,"") -> 0 | H60: =IF(E60>=D60,"PASS","FAIL") -> PASS | I60: If a cap is raised above the schedule length, extend the Marginal Cost and Enumeration sheets.
A61: E15 | B61: Coverage | C61: Carrot schedule and enumeration cover q = 0 … CARROT_BED_CAP | D61: =CARROT_BED_CAP -> 20 | E61: =ROWS(CARROT_SCHED_Q)-1 -> 20 | F61: =IF(AND(ISNUMBER(D61),ISNUMBER(E61)),E61-D61,"") -> 0 | H61: =IF(E61>=D61,"PASS","FAIL") -> PASS | I61: If a cap is raised above the schedule length, extend the Marginal Cost and Enumeration sheets.
A62: E16 | B62: Coverage | C62: Mesclun schedule and enumeration cover q = 0 … MESCLUN_BED_CAP | D62: =MESCLUN_BED_CAP -> 30 | E62: =ROWS(MESCLUN_SCHED_Q)-1 -> 30 | F62: =IF(AND(ISNUMBER(D62),ISNUMBER(E62)),E62-D62,"") -> 0 | H62: =IF(E62>=D62,"PASS","FAIL") -> PASS | I62: If a cap is raised above the schedule length, extend the Marginal Cost and Enumeration sheets.
A63: L1 | B63: Logic | C63: Crop labor costs (blended rate) sum to TOTAL_LABOR_COST | D63: =TOTAL_LABOR_COST -> 104104.84 | E63: =TOMATO_LABOR_COST+CARROT_LABOR_COST+MESCLUN_LABOR_COST -> 104104.84 | F63: =IF(AND(ISNUMBER(D63),ISNUMBER(E63)),E63-D63,"") -> 0 | G63: 0.01 | H63: =IF(ABS(F63)<=G63,"PASS","FAIL") -> PASS | I63: spec.md, Calculation Logic: labor cost by crop.
A64: L2 | B64: Logic | C64: Labor allocation reconciles: permanent + temporary = total hours | D64: =TOTAL_LABOR_HOURS -> 5276.8228 | E64: =PERMANENT_HOURS_USED+TEMP_HOURS_USED -> 5276.8228 | F64: =IF(AND(ISNUMBER(D64),ISNUMBER(E64)),E64-D64,"") -> 0 | G64: 1e-06 | H64: =IF(ABS(F64)<=G64,"PASS","FAIL") -> PASS
A65: L3 | B65: Logic | C65: Profit identity: revenue − total costs = seasonal profit | D65: =SEASONAL_PROFIT -> 42775.155 | E65: =TOTAL_REVENUE-TOTAL_COSTS -> 42775.155 | F65: =IF(AND(ISNUMBER(D65),ISNUMBER(E65)),E65-D65,"") -> 0 | G65: 1e-06 | H65: =IF(ABS(F65)<=G65,"PASS","FAIL") -> PASS
A66: I1 | B66: Information | C66: Tomato: permanent-hours-first schedule — P = MC point and times marginal cost falls | D66: info | E66: =TOMATO_PMC_Q_OWNER&" beds; MC falls "&TOMATO_MC_FALLS_OWNER&" time(s)" -> 10 beds; MC falls 1 time(s) | H66: ="INFO" -> INFO | I66: Expected to fall where the 720 permanent hours run out: once for tomatoes (bed 6), twice for carrots (beds 17–18) and mesclun (beds 14–15), because the crossing bed is split between the two rates (spec.md Audit finding A1). Information only.
A67: I2 | B67: Information | C67: Carrot: permanent-hours-first schedule — P = MC point and times marginal cost falls | D67: info | E67: =CARROT_PMC_Q_OWNER&" beds; MC falls "&CARROT_MC_FALLS_OWNER&" time(s)" -> 20 beds; MC falls 2 time(s) | H67: ="INFO" -> INFO | I67: Expected to fall where the 720 permanent hours run out: once for tomatoes (bed 6), twice for carrots (beds 17–18) and mesclun (beds 14–15), because the crossing bed is split between the two rates (spec.md Audit finding A1). Information only.
A68: I3 | B68: Information | C68: Mesclun: permanent-hours-first schedule — P = MC point and times marginal cost falls | D68: info | E68: =MESCLUN_PMC_Q_OWNER&" beds; MC falls "&MESCLUN_MC_FALLS_OWNER&" time(s)" -> 30 beds; MC falls 2 time(s) | H68: ="INFO" -> INFO | I68: Expected to fall where the 720 permanent hours run out: once for tomatoes (bed 6), twice for carrots (beds 17–18) and mesclun (beds 14–15), because the crossing bed is split between the two rates (spec.md Audit finding A1). Information only.
A69: H1 | B69: Hand calc | C69: Tomato labor hours at 10 beds: 10 × 2.5 × 36 × 1.10^10 | D69: =10*2.5*36*1.1^10 -> 2334.3682 | E69: =TOMATO_LABOR_HRS -> 2334.3682 | F69: =IF(AND(ISNUMBER(D69),ISNUMBER(E69)),E69-D69,"") -> 0 | G69: 0.001 | H69: =IF(ABS(F69)<=G69,"PASS","FAIL") -> PASS | I69: Base case only (typed numbers). Fails by design if inputs or decision cells change.
A70: H2 | B70: Hand calc | C70: Carrot labor hours at 20 beds: 20 × 0.833 × 36 × 1.025^20 | D70: =20*0.833*36*1.025^20 -> 982.7766 | E70: =CARROT_LABOR_HRS -> 982.7766 | F70: =IF(AND(ISNUMBER(D70),ISNUMBER(E70)),E70-D70,"") -> 0 | G70: 0.001 | H70: =IF(ABS(F70)<=G70,"PASS","FAIL") -> PASS | I70: Base case only.
A71: H3 | B71: Hand calc | C71: Mesclun labor hours at 30 beds: 30 × 1.25 × 36 × 1.0125^30 | D71: =30*1.25*36*1.0125^30 -> 1959.678 | E71: =MESCLUN_LABOR_HRS -> 1959.678 | F71: =IF(AND(ISNUMBER(D71),ISNUMBER(E71)),E71-D71,"") -> 0 | G71: 0.001 | H71: =IF(ABS(F71)<=G71,"PASS","FAIL") -> PASS | I71: Base case only.
A72: H4 | B72: Hand calc | C72: Profit: revenue − fertilizer − (720 × $34.72 + rest × $17.36) − $20,000 | D72: =(10*8800+20*2094+30*2700)-(10*880+20*440+30*880)-(720*34.72+(10*2.5*36*1.1^10+20*0.833*36*1.025^20+30*1.25*36*1.0125^30-720)*17.36)-20000 -> 42775.155 | E72: =SEASONAL_PROFIT -> 42775.155 | F72: =IF(AND(ISNUMBER(D72),ISNUMBER(E72)),E72-D72,"") -> 0 | G72: 0.01 | H72: =IF(ABS(F72)<=G72,"PASS","FAIL") -> PASS | I72: Base case only.
